Workbook

Sheet Capa
B2: Lista de Exercícios — Análise de Insumo-Produto
B5: Disciplina | C5: Análise de Insumo-Produto · PPGEco/UFES · 2026/1
B6: Professor | C6: Prof. Dr. Celso Bissoli Sessa
B7: Aluno | C7: Felipe Carvalho de Souza Santos
B8: Entrega | C8: 24/07/2026
B9: Dados | C9: Matrizes de Insumo-Produto do Brasil, 2010 e 2020 (Nível 68, NEREUS/CECEG; R$ milhões correntes)
B10: Ferramenta | C10: Arcabouço do repositório fcarva/es-insumo-produto (src/io_core.py; convenções de pesquisa/01, 17 e 25) — gerado por lista/resolver_lista.py
B12: Guia das abas
B13: Aba | C13: Conteúdo
B14: Metodologia | C14: Notas metodológicas e todas as premissas assumidas
B15: Setores | C15: Classificação setorial (Nível 68, comum a 2010 e 2020)
B16: Q1_Multiplicadores | C16: Multiplicadores de produção, emprego, renda e VA (tipos I e II) + rankings
B17: Q2_Choques | C17: Choques de R$ 10 bi: exportações da agricultura × FBCF
B18: Q3_UPCF | C18: Reajuste do salário mínimo (R$ 120 bi): importações e emprego
B19: Q4_RH | C19: Rasmussen-Hirschman 2010 × 2020 e setores-chave
B20: Q5_CampoInfluencia | C20: Campos de influência (Sonis-Hewings), Brasil 2010
B21: Q6_Extracao | C21: Extração hipotética total do setor escolhido (2020)
B22: Q7_SDA | C22: Decomposição estrutural 2010→2020 com atualização pelo IPCA
B23: Dados_2020 / Dados_2010 | C23: Vetores da MIP e coeficientes diretos (fórmulas)
B24: A, B, G, B2 | C24: Coeficientes técnicos, inversa de Leontief, inversa de Ghosh e modelo fechado (valores documentados — base das fórmulas)
B26: Legenda de células
B27: célula | C27: Amarelo-pastel, texto azul — entrada editável (choques, IPCA): a pasta recalcula
B28: célula | C28: Cinza-quente — parâmetros lidos da MIP (aba 12)
B29: célula | C29: Verde-pastel — linhas-síntese e totais
B30: célula | C30: Sem preenchimento — fórmula viva sobre as abas de dados/matrizes

Sheet Metodologia
B2: Notas metodológicas e premissas
B3: Todas as hipóteses assumidas na resolução estão listadas aqui; as fórmulas citadas seguem Miller & Blair (2009).
B5: 1. Modelo aberto: A = Z·x̂⁻¹ sobre os fluxos NACIONAIS (aba 12 da MIP-BR); B = (I−A)⁻¹ (Leontief); Ghosh: G = (I−x̂⁻¹Z)⁻¹. As matrizes B, G e B2 estão coladas como VALORES (inversão 68×68 feita externamente em NumPy — conferível por MINVERSE; a matriz A reproduz a aba 13 do arquivo-fonte com desvio < 1e-15); todas as demais células derivam delas por fórmula e recalculam.
B6: 2. Tipo II: modelo fechado para as famílias na CONVENÇÃO DA PLANILHA DO PROFESSOR (abas 20/22/23 da MIP) — a renda das famílias é o VALOR ADICIONADO BRUTO: linha adicional = VA por unidade de produção (v_va); coluna adicional = consumo das famílias por unidade da massa de VA. Reproduz a aba 23 (mult. tipo II) e a aba 22 (geradores tipo II) com desvio < 1e-14. O fechamento por remunerações (renda do trabalho apenas), usado no artigo do ES em pesquisa/17, é uma alternativa mais estreita.
B7: 3. Multiplicador de emprego em OCUPAÇÕES por R$ 1 milhão de demanda final; renda e VA em R$ por R$ de demanda final.
B8: 4. Q2: choque de R$ 10 bi = 10.000 (R$ milhões). Cenário (a): tudo na linha de exportações do setor Agricultura. Cenário (b): distribuído pela estrutura observada da coluna FBCF (produtos nacionais). Premissa: o choque recai sobre produtos nacionais nos dois cenários (célula de entrada editável).
B9: 5. Q3 (UPCF): o incremento de R$ 120 bi é repartido pela cesta observada do consumo das famílias a preço de CONSUMIDOR — nacional a preço básico + importados + impostos + margens (linhas Importação/Impostos/Margens × coluna Famílias da aba 12; a soma reproduz exatamente o consumo total). Margens são demanda por serviços de comércio e transporte e voltam ao vetor de choque nesses setores (rateio pelo VBP do grupo); impostos não geram produção; a parcela importada é importação DIRETA; a produção induzida gera importação INDUZIDA via m = importação intermediária/x. Emprego pelo modelo aberto (o choque JÁ é o consumo induzido).
B10: 6. Q4: índices de Rasmussen-Hirschman na convenção da aba 14 da MIP — AMBOS pela inversa de Leontief, normalizados pela média geral: para trás = soma de coluna de B (poder de dispersão); para frente = soma de linha de B (sensibilidade da dispersão); setor-chave: ambos > 1. Reproduz a aba 14 com desvio < 1e-14. A inversa de Ghosh (abas G_2010/G_2020) é uma medida alternativa de sensibilidade da oferta.
B11: 7. Q5: campo de influência (Sonis & Hewings) com ε = 0.001; S(i,j) = Σ dos quadrados de F = [B(ε)−B]/ε para perturbação unitária em a(i,j). Cálculo fechado por Sherman-Morrison — numericamente idêntico ao laço do material de apoio em R (Vale & Perobelli). Matriz S colada como valor; agregações por fórmula.
B12: 8. Q6: extração hipotética TOTAL (zera linha e coluna do setor em A e sua demanda final); perda medida contra o baseline modelado x = B·y.
B13: 9. Q7: SDA bipolar média (Dietzenbacher & Los): Δx = ½ΔB·(y0*+y1) + ½(B0+B1)·Δy, com y0* = y(2010)·fator IPCA. O deflator único (IPCA acumulado dez/2010→dez/2020, células editáveis na aba Q7) não altera A nem B de 2010 — coeficientes são razões —, agindo apenas sobre os níveis. Limitação declarada: o ideal seriam deflatores setoriais (duplo deflacionamento); o enunciado pede IPCA.
B14: 10. Unidades: R$ milhões correntes do ano de cada matriz (Q7 em preços de 2020).
... B19: Arquivo 2010: dados/MIP-BR 2010 (Nível 68).xlsm

Sheet Setores
B2: Classificação setorial
B3: Nível 68 (NEREUS/CECEG) — comum às matrizes de 2010 e 2020.
B6: Código | C6: Atividades | D6: nº
B7: 0191 | C7: Agricultura, inclusive o apoio à agricultura e a pós-colheita | D7: 1
B8: 0192 | C8: Pecuária, inclusive o apoio à pecuária | D8: 2
B9: 0280 | C9: Produção florestal; pesca e aquicultura | D9: 3
B10: 0580 | C10: Extração de carvão mineral e de minerais não-metálicos | D10: 4
B11: 0680 | C11: Extração de petróleo e gás, inclusive as atividades de apoio | D11: 5
B12: 0791 | C12: Extração de minério de ferro, inclusive beneficiamentos e a aglomeração | D12: 6
B13: 0792 | C13: Extração de minerais metálicos não-ferrosos, inclusive beneficiamentos | D13: 7
B14: 1091 | C14: Abate e produtos de carne, inclusive os produtos do laticínio e da pesca | D14: 8
B15: 1092 | C15: Fabricação e refino de açúcar | D15: 9
B16: 1093 | C16: Outros produtos alimentares | D16: 10
B17: 1100 | C17: Fabricação de bebidas | D17: 11
B18: 1200 | C18: Fabricação de produtos do fumo | D18: 12
... B74: 9700 | C74: Serviços domésticos | D74: 68

Sheet Dados_2020
B2: Dados — MIP Brasil 2020
B3: Valores correntes em R$ milhões; ocupações em pessoas. Vetores extraídos da aba 12 da MIP-BR (Nível 68), NEREUS/CECEG; coeficientes por unidade de produção calculados por fórmula nas colunas Q a T.
B6: Código | C6: Atividades | D6: nº | E6: VBP (x) | F6: Remunerações | G6: VA (PIB) | H6: Ocupações | I6: Importação intermediária | J6: Exportações | K6: Governo | L6: ISFLSF | M6: Consumo das famílias (nac.) | N6: FBCF | O6: Variação de estoques | P6: Demanda final total | Q6: w = ocup/x | R6: v renda = rem/x | S6: v VA = VA/x | T6: m = imp/x
B7: 0191 | C7: Agricultura, inclusive o apoio à agricultura e a pós-colheita | D7: 1 | E7: 549087 | F7: 32361 | G7: 303359 | H7: 6337753 | I7: 34265.178 | J7: 208838.11 | K7: 143.84694 | L7: 0 | M7: 99806.846 | N7: 3614.081 | O7: -3039.5917 | P7: =SUM(J7:O7) -> 309363.29 | Q7: =IF(E7=0,0,H7/E7) -> 11.542348 | R7: =IF(E7=0,0,F7/E7) -> 0.058936016 | S7: =IF(E7=0,0,G7/E7) -> 0.55247893 | T7: =IF(E7=0,0,I7/E7) -> 0.062403914
B8: 0192 | C8: Pecuária, inclusive o apoio à pecuária | D8: 2 | E8: 204149 | F8: 21595 | G8: 99993 | H8: 5525366 | I8: 7687.0251 | J8: 8459.0322 | K8: 8.9494976 | L8: 0 | M8: 34591.194 | N8: 20796.752 | O8: -886.61833 | P8: =SUM(J8:O8) -> 62969.309 | Q8: =IF(E8=0,0,H8/E8) -> 27.065359 | R8: =IF(E8=0,0,F8/E8) -> 0.10578058 | S8: =IF(E8=0,0,G8/E8) -> 0.48980402 | T8: =IF(E8=0,0,I8/E8) -> 0.037653994
B9: 0280 | C9: Produção florestal; pesca e aquicultura | D9: 3 | E9: 42525 | F9: 2470 | G9: 31269 | H9: 697280 | I9: 645.55509 | J9: 3465.3745 | K9: 4.1419293 | L9: 0 | M9: 20328.245 | N9: 1182.8698 | O9: -1148.6206 | P9: =SUM(J9:O9) -> 23832.01 | Q9: =IF(E9=0,0,H9/E9) -> 16.396943 | R9: =IF(E9=0,0,F9/E9) -> 0.05808348 | S9: =IF(E9=0,0,G9/E9) -> 0.73530864 | T9: =IF(E9=0,0,I9/E9) -> 0.015180602
B10: 0580 | C10: Extração de carvão mineral e de minerais não-metálicos | D10: 4 | E10: 23233 | F10: 4009 | G10: 9747 | H10: 104947 | I10: 1750.605 | J10: 1771.3915 | K10: 0.029836272 | L10: 0 | M10: 207.9483 | N10: 13.82895 | O10: 204.80208 | P10: =SUM(J10:O10) -> 2198.0007 | Q10: =IF(E10=0,0,H10/E10) -> 4.5171523 | R10: =IF(E10=0,0,F10/E10) -> 0.17255628 | S10: =IF(E10=0,0,G10/E10) -> 0.41953256 | T10: =IF(E10=0,0,I10/E10) -> 0.075349933
B11: 0680 | C11: Extração de petróleo e gás, inclusive as atividades de apoio | D11: 5 | E11: 238713 | F11: 19400 | G11: 90642 | H11: 51889 | I11: 30481.875 | J11: 90261.888 | K11: 0 | L11: 0 | M11: 636.09401 | N11: 35013.456 | O11: -17980.38 | P11: =SUM(J11:O11) -> 107931.06 | Q11: =IF(E11=0,0,H11/E11) -> 0.21736981 | R11: =IF(E11=0,0,F11/E11) -> 0.081269139 | S11: =IF(E11=0,0,G11/E11) -> 0.3797112 | T11: =IF(E11=0,0,I11/E11) -> 0.12769256
B12: 0791 | C12: Extração de minério de ferro, inclusive beneficiamentos e a aglomeração | D12: 6 | E12: 156454 | F12: 4870 | G12: 85756 | H12: 27455 | I12: 9552.8351 | J12: 119308.51 | K12: 0 | L12: 0 | M12: 37.09972 | N12: 1574.2415 | O12: -5378.3956 | P12: =SUM(J12:O12) -> 115541.46 | Q12: =IF(E12=0,0,H12/E12) -> 0.17548289 | R12: =IF(E12=0,0,F12/E12) -> 0.03112736 | S12: =IF(E12=0,0,G12/E12) -> 0.54812277 | T12: =IF(E12=0,0,I12/E12) -> 0.061058427
B13: 0792 | C13: Extração de minerais metálicos não-ferrosos, inclusive beneficiamentos | D13: 7 | E13: 23631 | F13: 2751 | G13: 7470 | H13: 27983 | I13: 2164.7747 | J13: 12255.885 | K13: 0 | L13: 0 | M13: 11.881807 | N13: 7.4426116 | O13: -1043.4319 | P13: =SUM(J13:O13) -> 11231.778 | Q13: =IF(E13=0,0,H13/E13) -> 1.1841649 | R13: =IF(E13=0,0,F13/E13) -> 0.11641488 | S13: =IF(E13=0,0,G13/E13) -> 0.31611019 | T13: =IF(E13=0,0,I13/E13) -> 0.09160741
B14: 1091 | C14: Abate e produtos de carne, inclusive os produtos do laticínio e da pesca | D14: 8 | E14: 398215 | F14: 34281 | G14: 58616 | H14: 818425 | I14: 8595.3699 | J14: 72631.118 | K14: 75.498021 | L14: 0 | M14: 245746.16 | N14: 224.92223 | O14: 1429.8181 | P14: =SUM(J14:O14) -> 320107.52 | Q14: =IF(E14=0,0,H14/E14) -> 2.055234 | R14: =IF(E14=0,0,F14/E14) -> 0.086086662 | S14: =IF(E14=0,0,G14/E14) -> 0.14719687 | T14: =IF(E14=0,0,I14/E14) -> 0.021584747
B15: 1092 | C15: Fabricação e refino de açúcar | D15: 9 | E15: 71299 | F15: 8261 | G15: 14749 | H15: 130365 | I15: 1332.2129 | J15: 32213.891 | K15: 0.10164997 | L15: 0 | M15: 16698.21 | N15: 208.07043 | O15: -1813.6346 | P15: =SUM(J15:O15) -> 47306.639 | Q15: =IF(E15=0,0,H15/E15) -> 1.8284268 | R15: =IF(E15=0,0,F15/E15) -> 0.11586418 | S15: =IF(E15=0,0,G15/E15) -> 0.20686125 | T15: =IF(E15=0,0,I15/E15) -> 0.018684876
B16: 1093 | C16: Outros produtos alimentares | D16: 10 | E16: 393619 | F16: 36586 | G16: 67425 | H16: 1223741 | I16: 18949.217 | J16: 43890.453 | K16: 73.366774 | L16: 0 | M16: 205118.62 | N16: 295.47642 | O16: 4940.4675 | P16: =SUM(J16:O16) -> 254318.39 | Q16: =IF(E16=0,0,H16/E16) -> 3.108948 | R16: =IF(E16=0,0,F16/E16) -> 0.092947749 | S16: =IF(E16=0,0,G16/E16) -> 0.17129508 | T16: =IF(E16=0,0,I16/E16) -> 0.048141011
B17: 1100 | C17: Fabricação de bebidas | D17: 11 | E17: 97251 | F17: 10044 | G17: 24280 | H17: 188466 | I17: 4539.1409 | J17: 2266.6768 | K17: 0.61871224 | L17: 0 | M17: 55191.928 | N17: 137.02848 | O17: 2849.024 | P17: =SUM(J17:O17) -> 60445.276 | Q17: =IF(E17=0,0,H17/E17) -> 1.9379338 | R17: =IF(E17=0,0,F17/E17) -> 0.10327914 | S17: =IF(E17=0,0,G17/E17) -> 0.24966324 | T17: =IF(E17=0,0,I17/E17) -> 0.046674491
B18: 1200 | C18: Fabricação de produtos do fumo | D18: 12 | E18: 17271 | F18: 1839 | G18: 3834 | H18: 16862 | I18: 881.86997 | J18: 2908.666 | K18: 0 | L18: 0 | M18: 13566.817 | N18: 105.93811 | O18: -78.811753 | P18: =SUM(J18:O18) -> 16502.61 | Q18: =IF(E18=0,0,H18/E18) -> 0.97631868 | R18: =IF(E18=0,0,F18/E18) -> 0.10647907 | S18: =IF(E18=0,0,G18/E18) -> 0.22199062 | T18: =IF(E18=0,0,I18/E18) -> 0.051060736
... B74: 9700 | C74: Serviços domésticos | D74: 68 | E74: 59474 | F74: 59474 | G74: 59474 | H74: 5518847 | I74: 0 | J74: 0 | K74: 0 | L74: 0 | M74: 59474 | N74: 0 | O74: 0 | P74: =SUM(J74:O74) -> 59474 | Q74: =IF(E74=0,0,H74/E74) -> 92.79428 | R74: =IF(E74=0,0,F74/E74) -> 1 | S74: =IF(E74=0,0,G74/E74) -> 1 | T74: =IF(E74=0,0,I74/E74) -> 0
C75: TOTAL | E75: =SUM(E7:E74) -> 13306199 | F75: =SUM(F7:F74) -> 3192343 | G75: =SUM(G7:G74) -> 6594937 | H75: =SUM(H7:H74) -> 99254676 | I75: =SUM(I7:I74) -> 723062.02 | J75: =SUM(J7:J74) -> 1061746.5 | K75: =SUM(K7:K74) -> 1524987.7 | L75: =SUM(L7:L74) -> 101399.63 | ... P75: =SUM(P7:P74) -> 7161994.7

Sheet Dados_2010
B2: Dados — MIP Brasil 2010
B3: Valores correntes em R$ milhões; ocupações em pessoas. Vetores extraídos da aba 12 da MIP-BR (Nível 68), NEREUS/CECEG; coeficientes por unidade de produção calculados por fórmula nas colunas Q a T.
B6: Código | C6: Atividades | D6: nº | E6: VBP (x) | F6: Remunerações | G6: VA (PIB) | H6: Ocupações | I6: Importação intermediária | J6: Exportações | K6: Governo | L6: ISFLSF | M6: Consumo das famílias (nac.) | N6: FBCF | O6: Variação de estoques | P6: Demanda final total | Q6: w = ocup/x | R6: v renda = rem/x | S6: v VA = VA/x | T6: m = imp/x
B7: 0191 | C7: Agricultura, inclusive o apoio à agricultura e a pós-colheita | D7: 1 | E7: 168861 | F7: 21587 | G7: 100111 | H7: 6965949 | I7: 5556.3335 | J7: 31349.798 | K7: 162.53816 | L7: 0 | M7: 38738.809 | N7: 1972.731 | O7: 384.79463 | P7: =SUM(J7:O7) -> 72608.671 | Q7: =IF(E7=0,0,H7/E7) -> 41.252563 | R7: =IF(E7=0,0,F7/E7) -> 0.12783887 | S7: =IF(E7=0,0,G7/E7) -> 0.5928604 | T7: =IF(E7=0,0,I7/E7) -> 0.032904777
B8: 0192 | C8: Pecuária, inclusive o apoio à pecuária | D8: 2 | E8: 83448 | F8: 14062 | G8: 44863 | H8: 7473681 | I8: 1980.0532 | J8: 2712.8882 | K8: 10.515784 | L8: 0 | M8: 13254.171 | N8: 10470.544 | O8: 1034.3665 | P8: =SUM(J8:O8) -> 27482.485 | Q8: =IF(E8=0,0,H8/E8) -> 89.560936 | R8: =IF(E8=0,0,F8/E8) -> 0.16851213 | S8: =IF(E8=0,0,G8/E8) -> 0.53761624 | T8: =IF(E8=0,0,I8/E8) -> 0.023727989
B9: 0280 | C9: Produção florestal; pesca e aquicultura | D9: 3 | E9: 20332 | F9: 1983 | G9: 14958 | H9: 1041304 | I9: 299.92137 | J9: 457.17801 | K9: 2.5459381 | L9: 0 | M9: 7475.6452 | N9: 1252.48 | O9: -118.33432 | P9: =SUM(J9:O9) -> 9069.5148 | Q9: =IF(E9=0,0,H9/E9) -> 51.21503 | R9: =IF(E9=0,0,F9/E9) -> 0.097530986 | S9: =IF(E9=0,0,G9/E9) -> 0.73568759 | T9: =IF(E9=0,0,I9/E9) -> 0.014751199
B10: 0580 | C10: Extração de carvão mineral e de minerais não-metálicos | D10: 4 | E10: 14838 | F10: 2772 | G10: 6592 | H10: 138960 | I10: 768.64363 | J10: 593.77909 | K10: 0.089084302 | L10: 0 | M10: 465.81338 | N10: 35.818985 | O10: -306.27138 | P10: =SUM(J10:O10) -> 789.22915 | Q10: =IF(E10=0,0,H10/E10) -> 9.3651436 | R10: =IF(E10=0,0,F10/E10) -> 0.18681763 | S10: =IF(E10=0,0,G10/E10) -> 0.44426473 | T10: =IF(E10=0,0,I10/E10) -> 0.051802374
B11: 0680 | C11: Extração de petróleo e gás, inclusive as atividades de apoio | D11: 5 | E11: 117330 | F11: 12201 | G11: 63474 | H11: 60278 | I11: 8185.7564 | J11: 23128.241 | K11: 0 | L11: 0 | M11: 285.48345 | N11: 12022.338 | O11: -455.91922 | P11: =SUM(J11:O11) -> 34980.142 | Q11: =IF(E11=0,0,H11/E11) -> 0.51374755 | R11: =IF(E11=0,0,F11/E11) -> 0.10398875 | S11: =IF(E11=0,0,G11/E11) -> 0.54098696 | T11: =IF(E11=0,0,I11/E11) -> 0.069766951
B12: 0791 | C12: Extração de minério de ferro, inclusive beneficiamentos e a aglomeração | D12: 6 | E12: 56525 | F12: 3687 | G12: 36491 | H12: 35928 | I12: 1964.8914 | J12: 44613.201 | K12: 0 | L12: 0 | M12: 5.7744916 | N12: 187.08454 | O12: -216.70866 | P12: =SUM(J12:O12) -> 44589.351 | Q12: =IF(E12=0,0,H12/E12) -> 0.63561256 | R12: =IF(E12=0,0,F12/E12) -> 0.065227775 | S12: =IF(E12=0,0,G12/E12) -> 0.64557276 | T12: =IF(E12=0,0,I12/E12) -> 0.034761458
B13: 0792 | C13: Extração de minerais metálicos não-ferrosos, inclusive beneficiamentos | D13: 7 | E13: 9864 | F13: 1507 | G13: 3408 | H13: 31775 | I13: 659.06501 | J13: 2232.2045 | K13: 0 | L13: 0 | M13: 3.930707 | N13: 0 | O13: 360.15829 | P13: =SUM(J13:O13) -> 2596.2935 | Q13: =IF(E13=0,0,H13/E13) -> 3.2213098 | R13: =IF(E13=0,0,F13/E13) -> 0.15277778 | S13: =IF(E13=0,0,G13/E13) -> 0.34549878 | T13: =IF(E13=0,0,I13/E13) -> 0.066815187
B14: 1091 | C14: Abate e produtos de carne, inclusive os produtos do laticínio e da pesca | D14: 8 | E14: 137527 | F14: 13111 | G14: 20849 | H14: 638392 | I14: 1944.2879 | J14: 18341.431 | K14: 35.819844 | L14: 0 | M14: 91316.525 | N14: 45.574045 | O14: 1496.6954 | P14: =SUM(J14:O14) -> 111236.05 | Q14: =IF(E14=0,0,H14/E14) -> 4.6419394 | R14: =IF(E14=0,0,F14/E14) -> 0.095334007 | S14: =IF(E14=0,0,G14/E14) -> 0.15159932 | T14: =IF(E14=0,0,I14/E14) -> 0.0141375
B15: 1092 | C15: Fabricação e refino de açúcar | D15: 9 | E15: 44422 | F15: 6175 | G15: 9545 | H15: 228655 | I15: 565.65449 | J15: 16579.453 | K15: 2.2025413 | L15: 0 | M15: 13243.258 | N15: 224.56534 | O15: 725.7809 | P15: =SUM(J15:O15) -> 30775.26 | Q15: =IF(E15=0,0,H15/E15) -> 5.1473369 | R15: =IF(E15=0,0,F15/E15) -> 0.1390077 | S15: =IF(E15=0,0,G15/E15) -> 0.21487101 | T15: =IF(E15=0,0,I15/E15) -> 0.012733657
B16: 1093 | C16: Outros produtos alimentares | D16: 10 | E16: 153990 | F16: 16095 | G16: 27485 | H16: 1115497 | I16: 6123.3806 | J16: 13882.687 | K16: 33.26736 | L16: 0 | M16: 88499.476 | N16: 264.68219 | O16: 2828.4347 | P16: =SUM(J16:O16) -> 105508.55 | Q16: =IF(E16=0,0,H16/E16) -> 7.2439574 | R16: =IF(E16=0,0,F16/E16) -> 0.10451977 | S16: =IF(E16=0,0,G16/E16) -> 0.17848562 | T16: =IF(E16=0,0,I16/E16) -> 0.039764794
B17: 1100 | C17: Fabricação de bebidas | D17: 11 | E17: 53034 | F17: 5267 | G17: 17224 | H17: 161508 | I17: 1575.4188 | J17: 969.91061 | K17: 1.7504317 | L17: 0 | M17: 30131.334 | N17: 150.36957 | O17: 634.4348 | P17: =SUM(J17:O17) -> 31887.799 | Q17: =IF(E17=0,0,H17/E17) -> 3.0453671 | R17: =IF(E17=0,0,F17/E17) -> 0.099313648 | S17: =IF(E17=0,0,G17/E17) -> 0.32477279 | T17: =IF(E17=0,0,I17/E17) -> 0.029705826
B18: 1200 | C18: Fabricação de produtos do fumo | D18: 12 | E18: 13405 | F18: 1148 | G18: 3595 | H18: 19343 | I18: 538.84466 | J18: 2508.8771 | K18: 0 | L18: 0 | M18: 9906.8051 | N18: 39.48518 | O18: -56.785708 | P18: =SUM(J18:O18) -> 12398.382 | Q18: =IF(E18=0,0,H18/E18) -> 1.442969 | R18: =IF(E18=0,0,F18/E18) -> 0.085639687 | S18: =IF(E18=0,0,G18/E18) -> 0.26818351 | T18: =IF(E18=0,0,I18/E18) -> 0.040197289
... B74: 9700 | C74: Serviços domésticos | D74: 68 | E74: 40334 | F74: 40334 | G74: 40334 | H74: 6780014 | I74: 0 | J74: 0 | K74: 0 | L74: 0 | M74: 40334 | N74: 0 | O74: 0 | P74: =SUM(J74:O74) -> 40334 | Q74: =IF(E74=0,0,H74/E74) -> 168.09674 | R74: =IF(E74=0,0,F74/E74) -> 1 | S74: =IF(E74=0,0,G74/E74) -> 1 | T74: =IF(E74=0,0,I74/E74) -> 0
C75: TOTAL | E75: =SUM(E7:E74) -> 6599149 | F75: =SUM(F7:F74) -> 1618190 | G75: =SUM(G7:G74) -> 3302840 | H75: =SUM(H7:H74) -> 98116218 | I75: =SUM(I7:I74) -> 274871.08 | J75: =SUM(J7:J74) -> 352943.89 | K75: =SUM(K7:K74) -> 733881.93 | L75: =SUM(L7:L74) -> 59667.456 | ... P75: =SUM(P7:P74) -> 3568197.1

Sheet A_2020
B2: Matriz A — coeficientes técnicos nacionais (2020)
B3: a(i,j) = Z(i,j)/x(j); reproduz a aba 13 do arquivo-fonte (desvio < 1e-15).
B6: Código | C6: Atividades | E6: 1 | F6: 2 | G6: 3 | H6: 4 | I6: 5 | J6: 6 | K6: 7 | L6: 8 | M6: 9 | N6: 10 | O6: 11 | P6: 12 | Q6: 13 | R6: 14 | S6: 15 | T6: 16 | U6: 17 | V6: 18 | W6: 19 | X6: 20 | Y6: 21 | Z6: 22 | AA6: 23 | AB6: 24 | AC6: 25 | AD6: 26 | AE6: 27 | AF6: 28 | AG6: 29 | AH6: 30 | AI6: 31 | AJ6: 32 | AK6: 33 | AL6: 34 | AM6: 35 | AN6: 36 | AO6: 37 | AP6: 38 | AQ6: 39 | AR6: 40 | AS6: 41 | AT6: 42 | AU6: 43 | AV6: 44 | AW6: 45 | AX6: 46 | AY6: 47 | AZ6: 48 | BA6: 49 | BB6: 50 | BC6: 51 | BD6: 52 | BE6: 53 | BF6: 54 | BG6: 55 | BH6: 56 | BI6: 57 | BJ6: 58 | BK6: 59 | BL6: 60 | BM6: 61 | BN6: 62 | BO6: 63 | BP6: 64 | BQ6: 65 | BR6: 66 | BS6: 67 | BT6: 68
B7: 0191 | C7: Agricultura, inclusive o apoio à agricultura e a pós-colheita | D7: 1 | E7: 0.021716404 | F7: 0.042666048 | G7: 0.0045552159 | H7: 7.1846084e-05 | I7: 3.7636312e-05 | J7: 8.8366484e-05 | K7: 0.00011683352 | L7: 0.025890695 | M7: 0.46812247 | N7: 0.27620531 | O7: 0.030180497 | P7: 0.2785277 | Q7: 0.12431647 | R7: 0.011885214 | S7: 0.00016757449 | T7: 0.002279003 | U7: 0.0016318554 | V7: 1.1546433e-05 | W7: 2.3165475e-05 | X7: 0.37813778 | Y7: 8.8851249e-05 | Z7: 0.00015079689 | AA7: 4.1695044e-05 | AB7: 0.00022608255 | AC7: 0.00024727771 | AD7: 0.00016221647 | AE7: 0.00027528654 | AF7: 0.0003581842 | AG7: 3.1071834e-05 | AH7: 2.1327893e-06 | AI7: 3.0984664e-06 | AJ7: 5.1031497e-06 | AK7: 3.0017581e-06 | AL7: 3.4014765e-06 | AM7: 1.1562853e-05 | AN7: 0.00015348694 | AO7: 6.191892e-07 | AP7: 1.3871582e-06 | AQ7: 0.00047540239 | AR7: 0.00069794348 | AS7: 1.5421603e-05 | AT7: 0.01189369 | AU7: 2.5553073e-06 | AV7: 1.6103305e-06 | AW7: 6.5902006e-06 | AX7: 9.2573236e-05 | AY7: 0.012027636 | AZ7: 0.019245253 | BA7: 5.0271801e-06 | BB7: 1.3301733e-05 | BC7: 0.00023436517 | BD7: 1.2975865e-05 | BE7: 2.0299995e-05 | BF7: 2.9840003e-05 | BG7: 3.5749744e-05 | BH7: 0.00018406429 | BI7: 8.6242898e-06 | BJ7: 1.3416509e-05 | BK7: 0.00055741825 | BL7: 5.9768536e-06 | BM7: 0.0011680788 | BN7: 0.0010269768 | BO7: 0.00046819122 | BP7: 0.0020736436 | BQ7: 0.00064829248 | BR7: 7.5968112e-05 | BS7: 0.0019645627 | BT7: 0
B8: 0192 | C8: Pecuária, inclusive o apoio à pecuária | D8: 2 | E8: 0.0026517889 | F8: 0.043924466 | G8: 0.0059273028 | H8: 0.00016511796 | I8: 8.7857976e-05 | J8: 0.00015404297 | K8: 0.00020587229 | L8: 0.29513066 | M8: 0.0025505128 | N8: 0.01531257 | O8: 0.00083791281 | P8: 0.011801096 | Q8: 0.0067616618 | R8: 0.0047026335 | S8: 0.00015357649 | T8: 0.0043306958 | U8: 0.0027491695 | V8: 2.0020176e-05 | W8: 1.8355937e-06 | X8: 0.0033243315 | Y8: 0.00029496044 | Z8: 6.8681439e-05 | AA8: 9.9306981e-05 | AB8: 9.3589536e-05 | AC8: 0.00039124623 | AD8: 0.00070750645 | AE8: 0.00055086639 | AF8: 0.00065513915 | AG8: 2.5887911e-05 | AH8: 4.8088528e-06 | AI8: 9.8214091e-06 | AJ8: 1.0394753e-05 | AK8: 5.6524653e-06 | AL8: 8.000317e-06 | AM8: 1.7635354e-05 | AN8: 9.3253724e-05 | AO8: 1.7539227e-06 | AP8: 2.1412793e-06 | AQ8: 7.9154276e-05 | AR8: 0.0013038434 | AS8: 1.8202671e-05 | AT8: 0.00034303258 | AU8: 2.3796621e-06 | AV8: 1.8124664e-06 | AW8: 6.6712651e-06 | AX8: 0.00015769004 | AY8: 0.014225233 | AZ8: 0.0085150241 | BA8: 9.3507018e-06 | BB8: 2.2867286e-05 | BC8: 0.00040818755 | BD8: 2.3370185e-05 | BE8: 3.3189614e-05 | BF8: 5.4937531e-05 | BG8: 2.9751018e-05 | BH8: 0.00022280744 | BI8: 7.0918548e-05 | BJ8: 1.8907603e-05 | BK8: 0.00012171706 | BL8: 8.2264673e-06 | BM8: 0.00038341884 | BN8: 0.00034609117 | BO8: 0.00016861049 | BP8: 0.00062664671 | BQ8: 0.00032563404 | BR8: 8.0549455e-05 | BS8: 0.00026727641 | BT8: 0
B9: 0280 | C9: Produção florestal; pesca e aquicultura | D9: 3 | E9: 0.0032342991 | F9: 0.008539683 | G9: 0.05841453 | H9: 7.7652587e-05 | I9: 6.7404855e-06 | J9: 1.1163426e-05 | K9: 1.4680667e-05 | L9: 0.0065225064 | M9: 9.1731872e-06 | N9: 0.00079975602 | O9: 0.00016095405 | P9: 0.0007300534 | Q9: 0.0005900436 | R9: 0.00015330969 | S9: 0.00015094432 | T9: 0.051892405 | U9: 0.032259109 | V9: 1.527558e-06 | W9: 1.5015903e-07 | X9: 6.8392122e-05 | Y9: 0.0011104097 | Z9: 2.3890094e-05 | AA9: 1.4503091e-06 | AB9: 1.8433686e-06 | AC9: 0.004465193 | AD9: 0.00078334434 | AE9: 0.006181333 | AF9: 4.6940691e-05 | AG9: 5.6056106e-05 | AH9: 4.8442493e-07 | AI9: 9.04961e-07 | AJ9: 1.1227704e-06 | AK9: 5.565342e-07 | AL9: 7.8149627e-07 | AM9: 1.4629875e-06 | AN9: 3.4603681e-05 | AO9: 2.0472105e-07 | AP9: 3.5864194e-07 | AQ9: 5.6308698e-06 | AR9: 0.0013042173 | AS9: 1.9278386e-06 | AT9: 0.00016894888 | AU9: 3.0875136e-07 | AV9: 2.4284569e-07 | AW9: 5.6215158e-07 | AX9: 1.1947762e-05 | AY9: 0.0014922131 | AZ9: 0.002040406 | BA9: 1.1978847e-06 | BB9: 2.3944198e-06 | BC9: 2.9316507e-05 | BD9: 2.1835791e-06 | BE9: 2.6144106e-06 | BF9: 4.1048843e-06 | BG9: 2.8327544e-06 | BH9: 5.3918899e-05 | BI9: 1.0676524e-06 | BJ9: 2.0639463e-06 | BK9: 8.4945108e-06 | BL9: 8.6073155e-07 | BM9: 0.00011991758 | BN9: 0.00019805992 | BO9: 7.5899535e-05 | BP9: 0.00038265428 | BQ9: 5.4535912e-05 | BR9: 8.4571076e-06 | BS9: 1.7326071e-05 | BT9: 0
B10: 0580 | C10: Extração de carvão mineral e de minerais não-metálicos | D10: 4 | E10: 0.00029086183 | F10: 0.0024691239 | G10: 0.00034778484 | H10: 0.011913425 | I10: 0.0028747825 | J10: 6.2585455e-06 | K10: 0.00034513864 | L10: 0.00017949367 | M10: 0.00015398242 | N10: 0.00076075716 | O10: 0.00021787858 | P10: 8.4868187e-06 | Q10: 1.7040905e-05 | R10: 1.0339947e-05 | S10: 2.1119754e-05 | T10: 7.1133004e-06 | U10: 0.0001175198 | V10: 1.8469204e-05 | W10: 1.4979592e-05 | X10: 0.0026941647 | Y10: 0.017288895 | Z10: 0.00073244339 | AA10: 0.00010981474 | AB10: 2.4114014e-05 | AC10: 4.8413447e-05 | AD10: 0.053912593 | AE10: 0.009435352 | AF10: 0.0048117851 | AG10: 6.2237438e-05 | AH10: 6.7361461e-06 | AI10: 0.00053303912 | AJ10: 4.8122893e-05 | AK10: 0.00010293603 | AL10: 0.00034634055 | AM10: 5.6060458e-05 | AN10: 0.00037454829 | AO10: 4.3463248e-05 | AP10: 0.00059243303 | AQ10: 0.0047901992 | AR10: 0.010132676 | AS10: 2.4452797e-05 | AT10: 8.7319236e-05 | AU10: 2.1695768e-06 | AV10: 3.119142e-06 | AW10: 1.7655844e-06 | AX10: 3.9124347e-05 | AY10: 9.6307522e-05 | AZ10: 5.2558834e-05 | BA10: 1.6870646e-05 | BB10: 1.3622628e-05 | BC10: 1.6001734e-05 | BD10: 8.6260455e-06 | BE10: 4.842772e-06 | BF10: 0.00049875543 | BG10: 1.5736778e-05 | BH10: 2.5739559e-05 | BI10: 8.2856462e-06 | BJ10: 1.2740585e-05 | BK10: 1.2671905e-05 | BL10: 5.0488828e-06 | BM10: 8.3478908e-05 | BN10: 4.6095243e-05 | BO10: 2.5311686e-05 | BP10: 4.6695328e-05 | BQ10: 1.4809083e-05 | BR10: 6.1032838e-05 | BS10: 2.6773111e-05 | BT10: 0
B11: 0680 | C11: Extração de petróleo e gás, inclusive as atividades de apoio | D11: 5 | E11: 4.6337279e-05 | F11: 8.2878207e-05 | G11: 2.2827539e-05 | H11: 0.00013030638 | I11: 0.029883749 | J11: 0.0050617839 | K11: 0.0027417904 | L11: 0.0001250213 | M11: 7.3804608e-06 | N11: 0.0011743502 | O11: 0.00089422503 | P11: 8.9975296e-06 | Q11: 0.0011785302 | R11: 1.5717731e-05 | S11: 3.1915478e-05 | T11: 0.00080367052 | U11: 0.0035681681 | V11: 6.4634479e-06 | W11: 0.23394728 | X11: 6.5123529e-06 | Y11: 0.0053042223 | Z11: 0.00049673019 | AA11: 0.00031277567 | AB11: 0.00025057124 | AC11: 0.00043633189 | AD11: 0.0035041154 | AE11: 0.0014986019 | AF11: 0.0022485303 | AG11: 0.001742177 | AH11: 4.4761673e-06 | AI11: 0.00021777373 | AJ11: 8.4157847e-05 | AK11: 0.00018677814 | AL11: 0.00076132768 | AM11: 7.9635343e-06 | AN11: 1.7867295e-05 | AO11: 3.6114401e-05 | AP11: 0.025672189 | AQ11: 0.013231583 | AR11: 0.0022016498 | AS11: 5.2001975e-05 | AT11: 0.00013327693 | AU11: 0.00027221488 | AV11: 3.9373774e-05 | AW11: 6.8546218e-06 | AX11: 0.00064583993 | AY11: 0.00011233301 | AZ11: 0.00016344766 | BA11: 2.5110283e-05 | BB11: 2.9170729e-05 | BC11: 0.00089145709 | BD11: 2.8632258e-05 | BE11: 1.8620485e-05 | BF11: 7.9338412e-06 | BG11: 5.726936e-05 | BH11: 0.00090192013 | BI11: 3.0478478e-05 | BJ11: 9.6897747e-05 | BK11: 3.2231068e-05 | BL11: 1.7031789e-05 | BM11: 0.0026972984 | BN11: 6.4451933e-05 | BO11: 9.4898863e-05 | BP11: 6.9070784e-06 | BQ11: 2.2467326e-05 | BR11: 0.0002358578 | BS11: 0.00020074591 | BT11: 0
B12: 0791 | C12: Extração de minério de ferro, inclusive beneficiamentos e a aglomeração | D12: 6 | E12: 1.1437166e-06 | F12: 6.2244961e-06 | G12: 2.371864e-06 | H12: 1.5537172e-05 | I12: 0.0002370286 | J12: 0.024516073 | K12: 0.0041847665 | L12: 2.0333408e-06 | M12: 7.7718662e-07 | N12: 2.3684825e-06 | O12: 2.5143723e-06 | P12: 3.0789204e-06 | Q12: 2.8423699e-06 | R12: 7.2237545e-07 | S12: 1.2803549e-06 | T12: 1.9421555e-05 | U12: 4.5878335e-06 | V12: 2.1410183e-05 | W12: 4.3264916e-07 | X12: 7.4004011e-08 | Y12: 1.3933087e-06 | Z12: 3.0784572e-06 | AA12: 2.8190768e-06 | AB12: 7.2459332e-06 | AC12: 5.9929882e-06 | AD12: 0.0024070866 | AE12: 0.23271843 | AF12: 0.0012278784 | AG12: 3.5414741e-05 | AH12: 6.5376637e-06 | AI12: 0.00013852335 | AJ12: 0.00086451737 | AK12: 5.8618327e-05 | AL12: 4.1804916e-05 | AM12: 9.5940529e-05 | AN12: 3.452824e-05 | AO12: 0.00080621449 | AP12: 1.0395187e-06 | AQ12: 0.00023189965 | AR12: 0.00032917043 | AS12: 1.3261949e-05 | AT12: 4.6890289e-06 | AU12: 3.4998926e-06 | AV12: 5.5261814e-05 | AW12: 7.7893429e-08 | AX12: 6.0573087e-05 | AY12: 1.1577791e-05 | AZ12: 1.1332408e-05 | BA12: 5.8691608e-07 | BB12: 3.202353e-07 | BC12: 0.00012364324 | BD12: 1.8692796e-06 | BE12: 7.3982004e-06 | BF12: 1.2130537e-05 | BG12: 6.3000169e-06 | BH12: 0.00015228235 | BI12: 7.1816466e-07 | BJ12: 1.985298e-06 | BK12: 6.3643746e-05 | BL12: 1.459038e-06 | BM12: 5.9691024e-05 | BN12: 5.9116415e-06 | BO12: 1.0961119e-06 | BP12: 6.5897275e-05 | BQ12: 3.0209657e-07 | BR12: 1.7561109e-05 | BS12: 3.1306924e-06 | BT12: 0
B13: 0792 | C13: Extração de minerais metálicos não-ferrosos, inclusive beneficiamentos | D13: 7 | E13: 8.2611066e-06 | F13: 1.2354555e-05 | G13: 1.9655612e-06 | H13: 6.9420942e-06 | I13: 0.00032562436 | J13: 0.00011663137 | K13: 0.068188001 | L13: 2.3048991e-05 | M13: 2.4848571e-06 | N13: 4.1766491e-05 | O13: 2.3109577e-05 | P13: 2.1113233e-07 | Q13: 4.2695793e-07 | R13: 3.8003621e-08 | S13: 6.0262805e-07 | T13: 5.7300072e-08 | U13: 5.9721489e-05 | V13: 0.00029467803 | W13: 0 | X13: 1.0499426e-06 | Y13: 3.1527027e-05 | Z13: 4.8554118e-05 | AA13: 9.655364e-06 | AB13: 4.3433658e-06 | AC13: 1.8110123e-05 | AD13: 0.00060468634 | AE13: 0.011375087 | AF13: 0.096345806 | AG13: 0.00054570198 | AH13: 3.1526276e-05 | AI13: 0.0017936223 | AJ13: 0.00015123457 | AK13: 7.878162e-05 | AL13: 0.00073079567 | AM13: 0.00044542384 | AN13: 0.00061383958 | AO13: 0.00010900888 | AP13: 3.0394723e-06 | AQ13: 3.4585739e-05 | AR13: 0.00014936445 | AS13: 1.1850119e-06 | AT13: 5.8420479e-07 | AU13: 7.0114737e-07 | AV13: 0 | AW13: 0 | AX13: 9.4542065e-09 | AY13: 6.7642398e-06 | AZ13: 2.5851402e-06 | BA13: 2.1076805e-08 | BB13: 0 | BC13: 5.275722e-08 | BD13: 1.0790378e-07 | BE13: 1.4864361e-09 | BF13: 4.5924346e-06 | BG13: 0 | BH13: 1.2011854e-05 | BI13: 3.0031778e-09 | BJ13: 8.6318035e-08 | BK13: 3.2002486e-07 | BL13: 0 | BM13: 7.3212959e-07 | BN13: 5.341172e-07 | BO13: 1.2381456e-09 | BP13: 1.1049086e-06 | BQ13: 4.9844552e-07 | BR13: 1.396628e-08 | BS13: 6.8606642e-07 | BT13: 0
B14: 1091 | C14: Abate e produtos de carne, inclusive os produtos do laticínio e da pesca | D14: 8 | E14: 0.00015050569 | F14: 0.015550448 | G14: 0.0011158411 | H14: 0.0004836337 | I14: 3.9205602e-05 | J14: 6.6926352e-05 | K14: 0.0001543414 | L14: 0.090330565 | M14: 0.00022353641 | N14: 0.0097202197 | O14: 0.0004195652 | P14: 0.00045914105 | Q14: 0.000424517 | R14: 0.00039818303 | S14: 0.034402186 | T14: 0.0016847187 | U14: 0.00083361364 | V14: 0.00014299712 | W14: 5.4843472e-05 | X14: 0.017041084 | Y14: 0.00035516599 | Z14: 0.0009180452 | AA14: 0.038833011 | AB14: 0.00075283746 | AC14: 0.00053216191 | AD14: 0.00049638525 | AE14: 0.00041373903 | AF14: 0.00024202121 | AG14: 0.0011259227 | AH14: 0.00025108435 | AI14: 0.00047641782 | AJ14: 0.00072784845 | AK14: 4.1195879e-05 | AL14: 2.6826168e-05 | AM14: 0.00015146243 | AN14: 0.0011205451 | AO14: 4.9243071e-05 | AP14: 1.2109418e-05 | AQ14: 2.3488815e-05 | AR14: 0.00011451088 | AS14: 9.2937874e-06 | AT14: 0.00061509078 | AU14: 1.51004e-06 | AV14: 3.1359261e-06 | AW14: 1.2362582e-06 | AX14: 1.71253e-05 | AY14: 0.020428657 | AZ14: 0.081075113 | BA14: 0.00065185712 | BB14: 0.00042770568 | BC14: 0.00052993427 | BD14: 8.7420429e-05 | BE14: 5.8564524e-06 | BF14: 8.5287195e-06 | BG14: 6.7269017e-05 | BH14: 8.8837475e-05 | BI14: 8.2577076e-05 | BJ14: 9.4415413e-06 | BK14: 6.7544816e-05 | BL14: 4.4198325e-05 | BM14: 0.0031541484 | BN14: 0.0040463715 | BO14: 0.002107412 | BP14: 0.0083371719 | BQ14: 0.0024081374 | BR14: 0.00018576338 | BS14: 0.001658994 | BT14: 0
B15: 1092 | C15: Fabricação e refino de açúcar | D15: 9 | E15: 9.4236421e-05 | F15: 0.00056891789 | G15: 4.7195302e-05 | H15: 6.1710733e-05 | I15: 0.0012833741 | J15: 0.00011164289 | K15: 0.00016651256 | L15: 0.0014023934 | M15: 0.020005754 | N15: 0.012882932 | O15: 0.012160667 | P15: 0.00011866626 | Q15: 0.00010604391 | R15: 0.00010756393 | S15: 0.00018110554 | T15: 0.00063611354 | U15: 0.00020902022 | V15: 2.6631709e-05 | W15: 0.020021854 | X15: 0.011713937 | Y15: 0.00067409236 | Z15: 0.0051199607 | AA15: 0.010323044 | AB15: 0.0041534823 | AC15: 0.00012409885 | AD15: 0.00012651083 | AE15: 0.00010427549 | AF15: 6.2398304e-05 | AG15: 0.00025281908 | AH15: 6.7246531e-05 | AI15: 0.00014517158 | AJ15: 0.00049470636 | AK15: 5.9219379e-05 | AL15: 1.5523585e-05 | AM15: 6.3926001e-05 | AN15: 9.7229778e-05 | AO15: 0.00031122375 | AP15: 1.3464169e-05 | AQ15: 0.00019675931 | AR15: 0.00029754784 | AS15: 0.00095479415 | AT15: 0.00033392082 | AU15: 0.00089586365 | AV15: 0.0001677581 | AW15: 0.00035010288 | AX15: 0.00020189442 | AY15: 0.00038362024 | AZ15: 0.0037763355 | BA15: 0.00033487079 | BB15: 0.00024442517 | BC15: 0.00021719059 | BD15: 0.00016167621 | BE15: 9.0824408e-05 | BF15: 1.9223623e-05 | BG15: 0.00028952999 | BH15: 0.00098254558 | BI15: 0.0002129337 | BJ15: 0.0011392293 | BK15: 0.00032094969 | BL15: 0.00081348616 | BM15: 0.00041875402 | BN15: 0.00028536379 | BO15: 0.00010177097 | BP15: 0.00048428673 | BQ15: 0.00020011043 | BR15: 0.00038113883 | BS15: 0.00051200146 | BT15: 0
B16: 1093 | C16: Outros produtos alimentares | D16: 10 | E16: 0.0042879275 | F16: 0.087675923 | G16: 0.03064632 | H16: 0.0080696509 | I16: 0.0008110189 | J16: 0.00049927876 | K16: 0.0011872652 | L16: 0.085996241 | M16: 0.0012671493 | N16: 0.095395418 | O16: 0.02879141 | P16: 0.0018085987 | Q16: 0.0021405049 | R16: 0.001639522 | S16: 0.0034341893 | T16: 0.0038077922 | U16: 0.0099659802 | V16: 0.0011126795 | W16: 0.006664422 | X16: 0.075472257 | Y16: 0.0035901872 | Z16: 0.011188111 | AA16: 0.021815386 | AB16: 0.0053624363 | AC16: 0.0028265961 | AD16: 0.0023854375 | AE16: 0.0018673043 | AF16: 0.0010605745 | AG16: 0.0021644282 | AH16: 0.0010209538 | AI16: 0.0019527546 | AJ16: 0.0028170428 | AK16: 0.00014646462 | AL16: 9.3026239e-05 | AM16: 0.00055927636 | AN16: 0.0023045655 | AO16: 0.00034474868 | AP16: 3.0476444e-05 | AQ16: 0.00036982635 | AR16: 0.00028545206 | AS16: 0.00073110161 | AT16: 0.0042439145 | AU16: 0.00031582173 | AV16: 7.3546259e-05 | AW16: 0.00057243053 | AX16: 0.00029453552 | AY16: 0.0083095019 | AZ16: 0.04760511 | BA16: 0.0026536478 | BB16: 0.0016936925 | BC16: 0.0022007348 | BD16: 0.00044533981 | BE16: 0.00020999628 | BF16: 4.7903656e-05 | BG16: 0.00052344071 | BH16: 0.00061680968 | BI16: 0.00073110683 | BJ16: 0.00048060076 | BK16: 0.00043039666 | BL16: 0.00045804239 | BM16: 0.0020611544 | BN16: 0.0033912887 | BO16: 0.0014140819 | BP16: 0.01070574 | BQ16: 0.00171377 | BR16: 0.0014538489 | BS16: 0.0052751523 | BT16: 0
B17: 1100 | C17: Fabricação de bebidas | D17: 11 | E17: 3.7711496e-06 | F17: 1.1719615e-05 | G17: 3.7290251e-06 | H17: 0.00040104365 | I17: 0.00010909759 | J17: 0.00014442613 | K17: 0.00023780465 | L17: 0.0018625382 | M17: 0.00020046947 | N17: 0.00070839755 | O17: 0.091291049 | P17: 0.00039668458 | Q17: 0.00035549436 | R17: 0.00035072488 | S17: 0.00061906834 | T17: 0.00042152194 | U17: 0.00064779304 | V17: 0.00012500443 | W17: 0.00015222175 | X17: 0.00022919791 | Y17: 0.00022248181 | Z17: 0.00053254958 | AA17: 0.00021685381 | AB17: 0.00063225431 | AC17: 0.0004536889 | AD17: 0.00043448295 | AE17: 0.00037913575 | AF17: 0.00020422717 | AG17: 0.00055681823 | AH17: 0.00023294253 | AI17: 0.00046575218 | AJ17: 0.0009247799 | AK17: 7.4170162e-05 | AL17: 5.0666048e-05 | AM17: 0.00019026953 | AN17: 0.00032626222 | AO17: 0.00034319942 | AP17: 1.4137116e-05 | AQ17: 3.4232491e-05 | AR17: 8.8959124e-05 | AS17: 4.4234828e-05 | AT17: 0.00022993503 | AU17: 1.6475412e-05 | AV17: 2.3486018e-05 | AW17: 0.00015509786 | AX17: 3.5704796e-05 | AY17: 0.017557685 | AZ17: 0.10038943 | BA17: 0.00057586836 | BB17: 0.00035951552 | BC17: 0.00047014862 | BD17: 8.5649644e-05 | BE17: 0.00012423968 | BF17: 5.7524426e-06 | BG17: 8.7153948e-05 | BH17: 4.2814369e-05 | BI17: 7.4632399e-05 | BJ17: 3.2306437e-05 | BK17: 8.4795985e-05 | BL17: 5.2946742e-05 | BM17: 0.00014412009 | BN17: 0.00021563281 | BO17: 0.00011496657 | BP17: 0.00045578309 | BQ17: 0.00044666025 | BR17: 0.00080382905 | BS17: 9.9783103e-05 | BT17: 0
B18: 1200 | C18: Fabricação de produtos do fumo | D18: 12 | E18: 1.2546644e-05 | F18: 3.4961585e-06 | G18: 1.2373893e-06 | H18: 4.8509703e-06 | I18: 1.6869525e-05 | J18: 2.4723218e-05 | K18: 2.7976807e-05 | L18: 5.4240353e-05 | M18: 1.419691e-05 | N18: 3.2094615e-05 | O18: 7.312246e-06 | P18: 0.035063506 | Q18: 2.4883173e-05 | R18: 2.5098785e-05 | S18: 4.5034224e-05 | T18: 2.7837853e-05 | U18: 5.2015184e-05 | V18: 1.0784093e-05 | W18: 3.1494311e-06 | X18: 1.4659671e-05 | Y18: 1.5765698e-05 | Z18: 2.9445592e-05 | AA18: 8.4380625e-06 | AB18: 4.5935171e-05 | AC18: 3.0830152e-05 | AD18: 3.0885817e-05 | AE18: 2.4553093e-05 | AF18: 1.6674518e-05 | AG18: 3.0925714e-05 | AH18: 1.6745609e-05 | AI18: 3.3960996e-05 | AJ18: 0.00010701817 | AK18: 7.4951462e-06 | AL18: 3.6959984e-06 | AM18: 1.3956225e-05 | AN18: 2.1041327e-05 | AO18: 6.0828959e-05 | AP18: 4.8350937e-07 | AQ18: 1.2856257e-06 | AR18: 3.5858171e-06 | AS18: 1.8054294e-06 | AT18: 1.3652238e-05 | AU18: 1.7856461e-07 | AV18: 4.4418474e-06 | AW18: 1.0520143e-07 | AX18: 1.7544784e-06 | AY18: 1.8698797e-06 | AZ18: 1.0371697e-06 | BA18: 4.4167941e-05 | BB18: 2.4837497e-05 | BC18: 3.3088735e-05 | BD18: 6.7375407e-06 | BE18: 5.8645383e-07 | BF18: 1.2783159e-07 | BG18: 4.7861436e-06 | BH18: 2.1827872e-05 | BI18: 4.8844699e-06 | BJ18: 2.2100553e-06 | BK18: 7.6961326e-06 | BL18: 2.800228e-06 | BM18: 2.0980177e-07 | BN18: 2.232071e-07 | BO18: 1.6394977e-06 | BP18: 6.3361756e-07 | BQ18: 4.9181708e-07 | BR18: 3.7169914e-06 | BS18: 1.1342936e-06 | BT18: 0
... B74: 9700 | C74: Serviços domésticos | D74: 68 | E74: 0 | F74: 0 | G74: 0 | H74: 0 | I74: 0 | J74: 0 | K74: 0 | L74: 0 | M74: 0 | N74: 0 | O74: 0 | P74: 0 | Q74: 0 | R74: 0 | S74: 0 | T74: 0 | U74: 0 | V74: 0 | W74: 0 | X74: 0 | Y74: 0 | Z74: 0 | AA74: 0 | AB74: 0 | AC74: 0 | AD74: 0 | AE74: 0 | AF74: 0 | AG74: 0 | AH74: 0 | AI74: 0 | AJ74: 0 | AK74: 0 | AL74: 0 | AM74: 0 | AN74: 0 | AO74: 0 | AP74: 0 | AQ74: 0 | AR74: 0 | AS74: 0 | AT74: 0 | AU74: 0 | AV74: 0 | AW74: 0 | AX74: 0 | AY74: 0 | AZ74: 0 | BA74: 0 | BB74: 0 | BC74: 0 | BD74: 0 | BE74: 0 | BF74: 0 | BG74: 0 | BH74: 0 | BI74: 0 | BJ74: 0 | BK74: 0 | BL74: 0 | BM74: 0 | BN74: 0 | BO74: 0 | BP74: 0 | BQ74: 0 | BR74: 0 | BS74: 0 | BT74: 0

Sheet B_2020
B2: Matriz B — inversa de Leontief (2020)
B3: B = (I−A)⁻¹, colada como VALOR (inversão externa NumPy; confira com MINVERSE). Base das fórmulas das questões.
B6: Código | C6: Atividades | E6: 1 | F6: 2 | G6: 3 | H6: 4 | I6: 5 | J6: 6 | K6: 7 | L6: 8 | M6: 9 | N6: 10 | O6: 11 | P6: 12 | Q6: 13 | R6: 14 | S6: 15 | T6: 16 | U6: 17 | V6: 18 | W6: 19 | X6: 20 | Y6: 21 | Z6: 22 | AA6: 23 | AB6: 24 | AC6: 25 | AD6: 26 | AE6: 27 | AF6: 28 | AG6: 29 | AH6: 30 | AI6: 31 | AJ6: 32 | AK6: 33 | AL6: 34 | AM6: 35 | AN6: 36 | AO6: 37 | AP6: 38 | AQ6: 39 | AR6: 40 | AS6: 41 | AT6: 42 | AU6: 43 | AV6: 44 | AW6: 45 | AX6: 46 | AY6: 47 | AZ6: 48 | BA6: 49 | BB6: 50 | BC6: 51 | BD6: 52 | BE6: 53 | BF6: 54 | BG6: 55 | BH6: 56 | BI6: 57 | BJ6: 58 | BK6: 59 | BL6: 60 | BM6: 61 | BN6: 62 | BO6: 63 | BP6: 64 | BQ6: 65 | BR6: 66 | BS6: 67 | BT6: 68
B7: 0191 | C7: Agricultura, inclusive o apoio à agricultura e a pós-colheita | D7: 1 | E7: 1.0290601 | F7: 0.082310178 | G7: 0.018368722 | H7: 0.011268356 | I7: 0.0064471141 | J7: 0.0052550459 | K7: 0.0088716628 | L7: 0.10239577 | M7: 0.49959884 | N7: 0.33554431 | O7: 0.058543913 | P7: 0.30579937 | Q7: 0.16273854 | R7: 0.056311416 | S7: 0.026249736 | T7: 0.015507314 | U7: 0.021481248 | V7: 0.0054918768 | W7: 0.048477871 | X7: 0.43057732 | Y7: 0.01252328 | Z7: 0.019595367 | AA7: 0.034202154 | AB7: 0.01979246 | AC7: 0.013739223 | AD7: 0.012817275 | AE7: 0.011107391 | AF7: 0.0090161114 | AG7: 0.011983959 | AH7: 0.0055762092 | AI7: 0.011174503 | AJ7: 0.013481757 | AK7: 0.0055076575 | AL7: 0.0068413762 | AM7: 0.0047888093 | AN7: 0.011473935 | AO7: 0.004281973 | AP7: 0.0022646011 | AQ7: 0.0034841298 | AR7: 0.0061621544 | AS7: 0.0041078142 | AT7: 0.019203366 | AU7: 0.013515101 | AV7: 0.0057499135 | AW7: 0.010055383 | AX7: 0.0034763381 | AY7: 0.023296058 | AZ7: 0.054561058 | BA7: 0.011276158 | BB7: 0.0090286688 | BC7: 0.0095347619 | BD7: 0.0026448991 | BE7: 0.0014683486 | BF7: 0.00037785696 | BG7: 0.0029630335 | BH7: 0.0040447563 | BI7: 0.0051646239 | BJ7: 0.0040446007 | BK7: 0.0036658526 | BL7: 0.0032569054 | BM7: 0.0043654609 | BN7: 0.0038897329 | BO7: 0.0028456988 | BP7: 0.010129411 | BQ7: 0.0045753481 | BR7: 0.0032680341 | BS7: 0.011511374 | BT7: 0
B8: 0192 | C8: Pecuária, inclusive o apoio à pecuária | D8: 2 | E8: 0.0034732763 | F8: 1.0542163 | G8: 0.0079525576 | H8: 0.0011686014 | I8: 0.00068944227 | J8: 0.00062727145 | K8: 0.00096696063 | L8: 0.34538069 | M8: 0.0049478481 | N8: 0.023533872 | O8: 0.0027153405 | P8: 0.014845114 | Q8: 0.010006317 | R8: 0.008051497 | S8: 0.014831286 | T8: 0.0072869966 | U8: 0.005539634 | V8: 0.00084675041 | W8: 0.0015789822 | X8: 0.012959398 | Y8: 0.0013597981 | Z8: 0.0018317818 | AA8: 0.015437405 | AB8: 0.0017225793 | AC8: 0.0018655557 | AD8: 0.0020470987 | AE8: 0.0017355028 | AF8: 0.0017060805 | AG8: 0.0016874772 | AH8: 0.00062529682 | AI8: 0.0012609823 | AJ8: 0.0014586109 | AK8: 0.00075864954 | AL8: 0.00080605178 | AM8: 0.00060048377 | AN8: 0.001939987 | AO8: 0.00052938737 | AP8: 0.00028544296 | AQ8: 0.00046569132 | AR8: 0.0022503248 | AS8: 0.00043644438 | AT8: 0.0012428355 | AU8: 0.00060368609 | AV8: 0.00037812423 | AW8: 0.0010502917 | AX8: 0.00054650183 | AY8: 0.023057364 | AZ8: 0.038645486 | BA8: 0.0013113761 | BB8: 0.0016374335 | BC8: 0.0015416078 | BD8: 0.00040864288 | BE8: 0.00038563218 | BF8: 0.00012420114 | BG8: 0.00061672945 | BH8: 0.00067798735 | BI8: 0.00096115351 | BJ8: 0.0003943411 | BK8: 0.00073068971 | BL8: 0.00028684687 | BM8: 0.0021660904 | BN8: 0.002149311 | BO8: 0.0012889473 | BP8: 0.0050285175 | BQ8: 0.002146925 | BR8: 0.00063198019 | BS8: 0.0042860231 | BT8: 0
B9: 0280 | C9: Produção florestal; pesca e aquicultura | D9: 3 | E9: 0.0040943514 | F9: 0.010683339 | G9: 1.062448 | H9: 0.00062543019 | I9: 0.00089429409 | J9: 0.00050231304 | K9: 0.00070765038 | L9: 0.012853646 | M9: 0.002327702 | N9: 0.0038574872 | O9: 0.001570981 | P9: 0.0044836011 | Q9: 0.0027077296 | R9: 0.0015581588 | S9: 0.0022923495 | T9: 0.0650126 | U9: 0.042822479 | V9: 0.0030235644 | W9: 0.00067088062 | X9: 0.0024889746 | Y9: 0.00200803 | Z9: 0.0011382007 | AA9: 0.0027385761 | AB9: 0.0013477176 | AC9: 0.0072467723 | AD9: 0.0027652248 | AE9: 0.0080175151 | AF9: 0.00080769017 | AG9: 0.0031010025 | AH9: 0.00081317901 | AI9: 0.0015028058 | AJ9: 0.0017538555 | AK9: 0.0015315249 | AL9: 0.001837901 | AM9: 0.00093612198 | AN9: 0.0064428143 | AO9: 0.00077169515 | AP9: 0.00032998727 | AQ9: 0.00049497733 | AR9: 0.003313998 | AS9: 0.00061520751 | AT9: 0.0010229527 | AU9: 0.00051385245 | AV9: 0.00037579348 | AW9: 0.00049068836 | AX9: 0.00041814272 | AY9: 0.0026861997 | AZ9: 0.0040759878 | BA9: 0.0026909643 | BB9: 0.00096250905 | BC9: 0.00071795726 | BD9: 0.00041420175 | BE9: 0.00025543433 | BF9: 0.0001226738 | BG9: 0.00054208482 | BH9: 0.00058003884 | BI9: 0.00077236417 | BJ9: 0.00067993973 | BK9: 0.00066162206 | BL9: 0.00018769201 | BM9: 0.00043884158 | BN9: 0.00049473755 | BO9: 0.00048615377 | BP9: 0.0010353991 | BQ9: 0.00064774129 | BR9: 0.00039904323 | BS9: 0.00087930171 | BT9: 0
B10: 0580 | C10: Extração de carvão mineral e de minerais não-metálicos | D10: 4 | E10: 0.0038037746 | F10: 0.005021771 | G10: 0.0010695051 | H10: 1.0135053 | I10: 0.0047695505 | J10: 0.0010574976 | K10: 0.0018456546 | L10: 0.0030383287 | M10: 0.0025812063 | N10: 0.0033191674 | O10: 0.0031116901 | P10: 0.001629816 | Q10: 0.0033095272 | R10: 0.0012300667 | S10: 0.001854668 | T10: 0.00162793 | U10: 0.0026348997 | V10: 0.001034711 | W10: 0.0021829959 | X10: 0.0049664763 | Y10: 0.022460267 | Z10: 0.004847729 | AA10: 0.0036743888 | AB10: 0.0013052021 | AC10: 0.0052591891 | AD10: 0.062316279 | AE10: 0.012324522 | AF10: 0.0081959687 | AG10: 0.0039628067 | AH10: 0.00056421069 | AI10: 0.0038527121 | AJ10: 0.0022047127 | AK10: 0.0027894082 | AL10: 0.003105287 | AM10: 0.0015738861 | AN10: 0.0026696756 | AO10: 0.001378466 | AP10: 0.0017547596 | AQ10: 0.007215606 | AR10: 0.018134608 | AS10: 0.00088308593 | AT10: 0.00069146554 | AU10: 0.0009166521 | AV10: 0.00048648601 | AW10: 0.00066260879 | AX10: 0.00062073851 | AY10: 0.0015779241 | AZ10: 0.0013387851 | BA10: 0.00073252204 | BB10: 0.00063272527 | BC10: 0.00093730238 | BD10: 0.00033089144 | BE10: 0.00018337028 | BF10: 0.00084974691 | BG10: 0.0003195867 | BH10: 0.00049917298 | BI10: 0.00040252748 | BJ10: 0.00047408859 | BK10: 0.00071388295 | BL10: 0.00018239701 | BM10: 0.00065386257 | BN10: 0.00030438009 | BO10: 0.00036861847 | BP10: 0.00088612993 | BQ10: 0.00043663043 | BR10: 0.00061590597 | BS10: 0.00078933674 | BT10: 0
B11: 0680 | C11: Extração de petróleo e gás, inclusive as atividades de apoio | D11: 5 | E11: 0.01830561 | F11: 0.017344515 | G11: 0.010653425 | H11: 0.029074551 | I11: 1.0438635 | J11: 0.026579358 | K11: 0.037544798 | L11: 0.026022223 | M11: 0.022680766 | N11: 0.024209465 | O11: 0.016734598 | P11: 0.013258621 | Q11: 0.018975425 | R11: 0.010749812 | S11: 0.015881828 | T11: 0.018031143 | U11: 0.030478913 | V11: 0.0081569631 | W11: 0.32989449 | X11: 0.018739766 | Y11: 0.044614461 | Z11: 0.020533605 | AA11: 0.017587556 | AB11: 0.014791751 | AC11: 0.023685616 | AD11: 0.032502205 | AE11: 0.028648366 | AF11: 0.029599919 | AG11: 0.020184668 | AH11: 0.0067824537 | AI11: 0.018265663 | AJ11: 0.015129521 | AK11: 0.012567124 | AL11: 0.013142442 | AM11: 0.0081308304 | AN11: 0.012814619 | AO11: 0.0072406003 | AP11: 0.04611316 | AQ11: 0.02357057 | AR11: 0.014538615 | AS11: 0.005988935 | AT11: 0.013944832 | AU11: 0.072923316 | AV11: 0.029251462 | AW11: 0.050141391 | AX11: 0.012647697 | AY11: 0.0083748906 | AZ11: 0.010001246 | BA11: 0.011116317 | BB11: 0.0079109006 | BC11: 0.0087979843 | BD11: 0.0030254584 | BE11: 0.001938099 | BF11: 0.00059250543 | BG11: 0.0036633269 | BH11: 0.0062575192 | BI11: 0.0049145791 | BJ11: 0.0066782593 | BK11: 0.0048623952 | BL11: 0.0048492882 | BM11: 0.0058897192 | BN11: 0.0019226055 | BO11: 0.0041558061 | BP11: 0.0039996722 | BQ11: 0.0028200729 | BR11: 0.0053104289 | BS11: 0.0079139319 | BT11: 0
B12: 0791 | C12: Extração de minério de ferro, inclusive beneficiamentos e a aglomeração | D12: 6 | E12: 0.0010742968 | F12: 0.0018294365 | G12: 0.00078163201 | H12: 0.0034624649 | I12: 0.020083464 | J12: 1.028374 | K12: 0.010612695 | L12: 0.0033300427 | M12: 0.0015398912 | N12: 0.0024667248 | O12: 0.0057852312 | P12: 0.0012365436 | Q12: 0.0016241957 | R12: 0.0012488152 | S12: 0.0016983612 | T12: 0.003096029 | U12: 0.0031857072 | V12: 0.0018773807 | W12: 0.0067639673 | X12: 0.0013694785 | Y12: 0.002216244 | Z12: 0.0024482022 | AA12: 0.0030097738 | AB12: 0.0016136871 | AC12: 0.0043371536 | AD12: 0.0082982181 | AE12: 0.26774132 | AF12: 0.0095583836 | AG12: 0.058811862 | AH12: 0.0020458894 | AI12: 0.016552082 | AJ12: 0.02579542 | AK12: 0.019398384 | AL12: 0.029121304 | AM12: 0.0094759807 | AN12: 0.0078543456 | AO12: 0.011762525 | AP12: 0.0025108825 | AQ12: 0.0029354472 | AR12: 0.01244381 | AS12: 0.0040900514 | AT12: 0.0015674952 | AU12: 0.0033417132 | AV12: 0.0020384505 | AW12: 0.0017085979 | AX12: 0.0012785028 | AY12: 0.0015007875 | AZ12: 0.0019415972 | BA12: 0.001562162 | BB12: 0.0011384444 | BC12: 0.0015196579 | BD12: 0.0006363908 | BE12: 0.00028027923 | BF12: 0.00020887828 | BG12: 0.00056381317 | BH12: 0.00099882847 | BI12: 0.00072961235 | BJ12: 0.0023058038 | BK12: 0.00096952314 | BL12: 0.00055821361 | BM12: 0.00076457434 | BN12: 0.0003275317 | BO12: 0.00053988665 | BP12: 0.0010213121 | BQ12: 0.00061681008 | BR12: 0.0011037811 | BS12: 0.00096760912 | BT12: 0
B13: 0792 | C13: Extração de minerais metálicos não-ferrosos, inclusive beneficiamentos | D13: 7 | E13: 0.00040189565 | F13: 0.00042811984 | G13: 0.00017901127 | H13: 0.00069458838 | I13: 0.002077488 | J13: 0.0008007035 | K13: 1.0748199 | L13: 0.00097927939 | M13: 0.00047460773 | N13: 0.0009305941 | O13: 0.0011229712 | P13: 0.00039942075 | Q13: 0.00054049567 | R13: 0.00042734132 | S13: 0.00053706395 | T13: 0.00075268819 | U13: 0.0014163504 | V13: 0.0028183147 | W13: 0.00078878454 | X13: 0.00043761067 | Y13: 0.0012920297 | Z13: 0.0011668488 | AA13: 0.00083446868 | AB13: 0.00050811135 | AC13: 0.0009665519 | AD13: 0.0018563004 | AE13: 0.016708361 | AF13: 0.12874562 | AG13: 0.0086306871 | AH13: 0.0010236964 | AI13: 0.017597606 | AJ13: 0.0046873076 | AK13: 0.0043490216 | AL13: 0.0096929975 | AM13: 0.0050075383 | AN13: 0.0055693984 | AO13: 0.004233023 | AP13: 0.0007627433 | AQ13: 0.00082287669 | AR13: 0.0024778579 | AS13: 0.0017059368 | AT13: 0.00041342637 | AU13: 0.00086572184 | AV13: 0.0005470634 | AW13: 0.00033822073 | AX13: 0.00037303985 | AY13: 0.00043423732 | AZ13: 0.00046452223 | BA13: 0.00062499475 | BB13: 0.00038922656 | BC13: 0.00045943287 | BD13: 0.0002061369 | BE13: 0.00010003798 | BF13: 7.577186e-05 | BG13: 0.00024271485 | BH13: 0.00027463362 | BI13: 0.0003110749 | BJ13: 0.00046368932 | BK13: 0.00030442553 | BL13: 0.00015254745 | BM13: 0.00017119949 | BN13: 9.7723307e-05 | BO13: 0.00020222575 | BP13: 0.00031160431 | BQ13: 0.00032049224 | BR13: 0.00048625717 | BS13: 0.00039414068 | BT13: 0
B14: 1091 | C14: Abate e produtos de carne, inclusive os produtos do laticínio e da pesca | D14: 8 | E14: 0.00087781285 | F14: 0.019680511 | G14: 0.0020428113 | H14: 0.0015509775 | I14: 0.00082766376 | J14: 0.00064470082 | K14: 0.0010902344 | L14: 1.1081638 | M14: 0.0013072612 | N14: 0.013570526 | O14: 0.0019004336 | P14: 0.0017973335 | Q14: 0.0017814989 | R14: 0.0015400053 | S14: 0.043150622 | T14: 0.0033904 | U14: 0.0028082713 | V14: 0.0009521089 | W14: 0.0020857741 | X14: 0.020902558 | Y14: 0.0016328052 | Z14: 0.0029254533 | AA14: 0.045676217 | AB14: 0.0026585561 | AC14: 0.0019949444 | AD14: 0.0018104279 | AE14: 0.0015801084 | AF14: 0.0012618098 | AG14: 0.0027586599 | AH14: 0.00095338525 | AI14: 0.0017711248 | AJ14: 0.0022902021 | AK14: 0.00098363084 | AL14: 0.00076492585 | AM14: 0.00079331541 | AN14: 0.002372216 | AO14: 0.00078346657 | AP14: 0.00043378303 | AQ14: 0.0004238371 | AR14: 0.00089522461 | AS14: 0.00056190912 | AT14: 0.0014770423 | AU14: 0.0007960911 | AV14: 0.00049580443 | AW14: 0.0018587388 | AX14: 0.00052880815 | AY14: 0.02426511 | AZ14: 0.091087243 | BA14: 0.0018843452 | BB14: 0.0030731758 | BC14: 0.0017978112 | BD14: 0.00057162878 | BE14: 0.0006189815 | BF14: 8.9480882e-05 | BG14: 0.0010882739 | BH14: 0.00064055926 | BI14: 0.0015848739 | BJ14: 0.00051245668 | BK14: 0.0011292444 | BL14: 0.00040673041 | BM14: 0.004739395 | BN14: 0.0051058922 | BO14: 0.0029312075 | BP14: 0.01195905 | BQ14: 0.004639826 | BR14: 0.00095778156 | BS14: 0.0086177876 | BT14: 0
B15: 1092 | C15: Fabricação e refino de açúcar | D15: 9 | E15: 0.0023688857 | F15: 0.0038575587 | G15: 0.0015781392 | H15: 0.0035473639 | I15: 0.0028861983 | J15: 0.0022848963 | K15: 0.0036567607 | L15: 0.0066846089 | M15: 1.0231372 | N15: 0.017423192 | O15: 0.015945024 | P15: 0.0018930476 | Q15: 0.0022104643 | R15: 0.0014721948 | S15: 0.0023616393 | T15: 0.0029036988 | U15: 0.0035007154 | V15: 0.0012654227 | W15: 0.029702157 | X15: 0.015462648 | Y15: 0.0047271461 | Z15: 0.0085900521 | AA15: 0.013755301 | AB15: 0.0066172935 | AC15: 0.0029236692 | AD15: 0.0032159771 | AE15: 0.0028473489 | AF15: 0.0026464888 | AG15: 0.0024326863 | AH15: 0.00098211192 | AI15: 0.0022229408 | AJ15: 0.0025204737 | AK15: 0.0014603146 | AL15: 0.0013239337 | AM15: 0.0010362574 | AN15: 0.0017286207 | AO15: 0.0012725528 | AP15: 0.00090612825 | AQ15: 0.0011588254 | AR15: 0.0017333967 | AS15: 0.0017061937 | AT15: 0.0019089689 | AU15: 0.0078141884 | AV15: 0.0030199978 | AW15: 0.0051790888 | AX15: 0.0015348638 | AY15: 0.0015919622 | AZ15: 0.0073530408 | BA15: 0.0018898111 | BB15: 0.0015249347 | BC15: 0.0013739313 | BD15: 0.00060372926 | BE15: 0.00039439363 | BF15: 0.00010453602 | BG15: 0.00080649313 | BH15: 0.0017084909 | BI15: 0.0010604053 | BJ15: 0.0019826021 | BK15: 0.00092195325 | BL15: 0.0013887431 | BM15: 0.00089947405 | BN15: 0.0006211698 | BO15: 0.00059844538 | BP15: 0.00144976 | BQ15: 0.00087341369 | BR15: 0.00099909564 | BS15: 0.001886104 | BT15: 0
B16: 1093 | C16: Outros produtos alimentares | D16: 10 | E16: 0.0087191786 | F16: 0.10743137 | G16: 0.038096821 | H16: 0.01359028 | I16: 0.0036510168 | J16: 0.0030361488 | K16: 0.0054357594 | L16: 0.14661528 | M16: 0.0085340006 | N16: 1.1164785 | O16: 0.039338889 | P16: 0.0095749995 | Q16: 0.0092476301 | R16: 0.0070933612 | S16: 0.01532449 | T16: 0.012752789 | U16: 0.021800156 | V16: 0.0050437304 | W16: 0.018208812 | X16: 0.093223872 | Y16: 0.0097371716 | Z16: 0.020168193 | AA16: 0.037362896 | AB16: 0.012605611 | AC16: 0.010114289 | AD16: 0.0091867349 | AE16: 0.0073816878 | AF16: 0.0054725579 | AG16: 0.0083945523 | AH16: 0.0039082096 | AI16: 0.0076442104 | AJ16: 0.0092933146 | AK16: 0.0032929071 | AL16: 0.0031419387 | AM16: 0.0031044288 | AN16: 0.007436599 | AO16: 0.0030803895 | AP16: 0.0013176051 | AQ16: 0.001996907 | AR16: 0.0037702494 | AS16: 0.0024888111 | AT16: 0.0074807547 | AU16: 0.0054195132 | AV16: 0.0025430215 | AW16: 0.0052414853 | AX16: 0.0019690111 | AY16: 0.016470902 | AZ16: 0.070999152 | BA16: 0.0081525998 | BB16: 0.0068448631 | BC16: 0.0066308812 | BD16: 0.0018499495 | BE16: 0.0012335134 | BF16: 0.0003004289 | BG16: 0.0023129066 | BH16: 0.0022040815 | BI16: 0.0041545359 | BJ16: 0.0021076878 | BK16: 0.002393858 | BL16: 0.0015655268 | BM16: 0.0042524844 | BN16: 0.0052227316 | BO16: 0.0030307157 | BP16: 0.016172643 | BQ16: 0.0048046327 | BR16: 0.0031581209 | BS16: 0.012385204 | BT16: 0
B17: 1100 | C17: Fabricação de bebidas | D17: 11 | E17: 0.00026562968 | F17: 0.00037185635 | G17: 0.00014642971 | H17: 0.00087977042 | I17: 0.0006490805 | J17: 0.00049011844 | K17: 0.00081402685 | L17: 0.0030769085 | M17: 0.00061401523 | N17: 0.0014901938 | O17: 1.1010143 | P17: 0.00095823442 | Q17: 0.00093607635 | R17: 0.00089287816 | S17: 0.0014340691 | T17: 0.0010268619 | U17: 0.0015508668 | V17: 0.0006142919 | W17: 0.00059750231 | X17: 0.00073318565 | Y17: 0.0007773351 | Z17: 0.0014098747 | AA17: 0.00085918038 | AB17: 0.0017773656 | AC17: 0.0011663493 | AD17: 0.0011297198 | AE17: 0.0010751049 | AF17: 0.00083361763 | AG17: 0.0013714832 | AH17: 0.00066363479 | AI17: 0.0012140929 | AJ17: 0.0019352793 | AK17: 0.00078157596 | AL17: 0.00050992907 | AM17: 0.00059132345 | AN17: 0.00087514844 | AO17: 0.00090653378 | AP17: 0.00033868749 | AQ17: 0.00026744495 | AR17: 0.00051202414 | AS17: 0.0004124288 | AT17: 0.00069578903 | AU17: 0.0003343024 | AV17: 0.00032211073 | AW17: 0.0019772192 | AX17: 0.00037599617 | AY17: 0.020538704 | AZ17: 0.11096994 | BA17: 0.001267581 | BB17: 0.0029298292 | BC17: 0.0013058774 | BD17: 0.00043844709 | BE17: 0.00076280893 | BF17: 7.3327089e-05 | BG17: 0.0010351565 | BH17: 0.00033745524 | BI17: 0.001330148 | BJ17: 0.0003092142 | BK17: 0.00080958749 | BL17: 0.00024278689 | BM17: 0.0015124023 | BN17: 0.00084715452 | BO17: 0.00062092296 | BP17: 0.0034041085 | BQ17: 0.0021110055 | BR17: 0.0013631941 | BS17: 0.0075168177 | BT17: 0
B18: 1200 | C18: Fabricação de produtos do fumo | D18: 12 | E18: 2.3024995e-05 | F18: 1.7618721e-05 | G18: 6.0099877e-06 | H18: 2.0695945e-05 | I18: 3.2694973e-05 | J18: 3.9121078e-05 | K18: 5.156543e-05 | L18: 9.1791562e-05 | M18: 3.3486523e-05 | N18: 6.0239196e-05 | O18: 2.6250446e-05 | P18: 1.0363571 | Q18: 4.820476e-05 | R18: 4.6679827e-05 | S18: 7.465068e-05 | T18: 5.1671823e-05 | U18: 8.8820498e-05 | V18: 3.0956526e-05 | W18: 2.0796085e-05 | X18: 3.6646976e-05 | Y18: 3.2010841e-05 | Z18: 5.3379564e-05 | AA18: 3.0402424e-05 | AB18: 6.7683061e-05 | AC18: 5.706692e-05 | AD18: 5.6255744e-05 | AE18: 5.6656669e-05 | AF18: 4.0484531e-05 | AG18: 6.1448398e-05 | AH18: 3.0990311e-05 | AI18: 6.3797892e-05 | AJ18: 0.00015102028 | AK18: 2.6141702e-05 | AL18: 2.26244e-05 | AM18: 2.986574e-05 | AN18: 4.2459083e-05 | AO18: 8.9824307e-05 | AP18: 7.2849042e-06 | AQ18: 9.2332506e-06 | AR18: 2.1217299e-05 | AS18: 9.4450478e-06 | AT18: 2.2887809e-05 | AU18: 9.5662075e-06 | AV18: 1.6758575e-05 | AW18: 9.5040651e-06 | AX18: 9.2698563e-06 | AY18: 1.0751435e-05 | AZ18: 1.7509983e-05 | BA18: 6.6017132e-05 | BB18: 4.2074025e-05 | BC18: 5.1504173e-05 | BD18: 1.3276009e-05 | BE18: 4.0597575e-06 | BF18: 1.154446e-06 | BG18: 1.047464e-05 | BH18: 2.8463325e-05 | BI18: 2.2412188e-05 | BJ18: 8.850982e-06 | BK18: 1.4301257e-05 | BL18: 6.5588507e-06 | BM18: 3.8011382e-06 | BN18: 3.1562496e-06 | BO18: 6.2022573e-06 | BP18: 8.3422296e-06 | BQ18: 6.9596222e-06 | BR18: 1.0323086e-05 | BS18: 8.8380605e-06 | BT18: 0
... B74: 9700 | C74: Serviços domésticos | D74: 68 | E74: 0 | F74: 0 | G74: 0 | H74: 0 | I74: 0 | J74: 0 | K74: 0 | L74: 0 | M74: 0 | N74: 0 | O74: 0 | P74: 0 | Q74: 0 | R74: 0 | S74: 0 | T74: 0 | U74: 0 | V74: 0 | W74: 0 | X74: 0 | Y74: 0 | Z74: 0 | AA74: 0 | AB74: 0 | AC74: 0 | AD74: 0 | AE74: 0 | AF74: 0 | AG74: 0 | AH74: 0 | AI74: 0 | AJ74: 0 | AK74: 0 | AL74: 0 | AM74: 0 | AN74: 0 | AO74: 0 | AP74: 0 | AQ74: 0 | AR74: 0 | AS74: 0 | AT74: 0 | AU74: 0 | AV74: 0 | AW74: 0 | AX74: 0 | AY74: 0 | AZ74: 0 | BA74: 0 | BB74: 0 | BC74: 0 | BD74: 0 | BE74: 0 | BF74: 0 | BG74: 0 | BH74: 0 | BI74: 0 | BJ74: 0 | BK74: 0 | BL74: 0 | BM74: 0 | BN74: 0 | BO74: 0 | BP74: 0 | BQ74: 0 | BR74: 0 | BS74: 0 | BT74: 1

Sheet G_2020
B2: Matriz G — inversa de Ghosh (2020)
B3: G = (I−x̂⁻¹Z)⁻¹, colada como VALOR; usada na ligação para frente (Q4).
B6: Código | C6: Atividades | E6: 1 | F6: 2 | G6: 3 | H6: 4 | I6: 5 | J6: 6 | K6: 7 | L6: 8 | M6: 9 | N6: 10 | O6: 11 | P6: 12 | Q6: 13 | R6: 14 | S6: 15 | T6: 16 | U6: 17 | V6: 18 | W6: 19 | X6: 20 | Y6: 21 | Z6: 22 | AA6: 23 | AB6: 24 | AC6: 25 | AD6: 26 | AE6: 27 | AF6: 28 | AG6: 29 | AH6: 30 | AI6: 31 | AJ6: 32 | AK6: 33 | AL6: 34 | AM6: 35 | AN6: 36 | AO6: 37 | AP6: 38 | AQ6: 39 | AR6: 40 | AS6: 41 | AT6: 42 | AU6: 43 | AV6: 44 | AW6: 45 | AX6: 46 | AY6: 47 | AZ6: 48 | BA6: 49 | BB6: 50 | BC6: 51 | BD6: 52 | BE6: 53 | BF6: 54 | BG6: 55 | BH6: 56 | BI6: 57 | BJ6: 58 | BK6: 59 | BL6: 60 | BM6: 61 | BN6: 62 | BO6: 63 | BP6: 64 | BQ6: 65 | BR6: 66 | BS6: 67 | BT6: 68
B7: 0191 | C7: Agricultura, inclusive o apoio à agricultura e a pós-colheita | D7: 1 | E7: 1.0290601 | F7: 0.030602692 | G7: 0.0014225977 | H7: 0.00047678729 | I7: 0.0028028526 | J7: 0.0014973455 | K7: 0.00038180883 | L7: 0.074260602 | M7: 0.064872957 | N7: 0.24053859 | O7: 0.010368947 | P7: 0.0096186231 | Q7: 0.016792015 | R7: 0.0065601122 | S7: 0.0017608918 | T7: 0.0011125935 | U7: 0.0047163233 | V7: 0.00019034489 | W7: 0.039295286 | X7: 0.057147927 | Y7: 0.0048033651 | Z7: 0.0042518064 | AA7: 0.0037659388 | AB7: 0.0031444478 | AC7: 0.0034106909 | AD7: 0.0023713336 | AE7: 0.003123029 | AF7: 0.0014082774 | AG7: 0.0027420149 | AH7: 0.0011844063 | AI7: 0.0020283699 | AJ7: 0.0038353082 | AK7: 0.0016499992 | AL7: 0.0012537795 | AM7: 0.00036466804 | AN7: 0.001840345 | AO7: 0.00069168252 | AP7: 0.0014760715 | AQ7: 0.000614512 | AR7: 0.006873821 | AS7: 0.0013133197 | AT7: 0.042982181 | AU7: 0.010362003 | AV7: 0.00031432069 | AW7: 0.00047357194 | AX7: 0.00096259049 | AY7: 0.00087446077 | AZ7: 0.024051752 | BA7: 0.0003383749 | BB7: 0.0006383688 | BC7: 0.0029719607 | BD7: 0.0010076914 | BE7: 0.0018743294 | BF7: 0.00048971243 | BG7: 0.0013288476 | BH7: 0.0005390386 | BI7: 0.0010980094 | BJ7: 0.00045935407 | BK7: 0.0018502345 | BL7: 0.000272819 | BM7: 0.0072206481 | BN7: 0.0027190026 | BO7: 0.00072682351 | BP7: 0.0045214476 | BQ7: 0.0026453654 | BR7: 0.00023391012 | BS7: 0.0036104975 | BT7: 0
B8: 0192 | C8: Pecuária, inclusive o apoio à pecuária | D8: 2 | E8: 0.0093418574 | F8: 1.0542163 | G8: 0.0016565475 | H8: 0.00013299167 | I8: 0.00080617017 | J8: 0.00048072304 | K8: 0.00011192926 | L8: 0.67370289 | M8: 0.001728035 | N8: 0.04537558 | O8: 0.001293514 | P8: 0.0012558963 | Q8: 0.0027770301 | R8: 0.0025228148 | S8: 0.002675965 | T8: 0.0014061849 | U8: 0.00327129 | V8: 7.8935028e-05 | W8: 0.0034424532 | X8: 0.004626239 | Y8: 0.0014028003 | Z8: 0.0010690247 | AA8: 0.0045718082 | AB8: 0.0007360677 | AC8: 0.0012456107 | AD8: 0.001018661 | AE8: 0.0013124512 | AF8: 0.00071674118 | AG8: 0.0010384875 | AH8: 0.00035722496 | AI8: 0.00061563294 | AJ8: 0.001116059 | AK8: 0.00061129652 | AL8: 0.0003973146 | AM8: 0.00012298874 | AN8: 0.00083691155 | AO8: 0.00023000133 | AP8: 0.00050041339 | AQ8: 0.00022091647 | AR8: 0.0067515697 | AS8: 0.00037530339 | AT8: 0.0074820158 | AU8: 0.0012448858 | AV8: 5.5595555e-05 | AW8: 0.00013304274 | AX8: 0.00040701 | AY8: 0.0023278847 | AZ8: 0.04582016 | BA8: 0.00010584203 | BB8: 0.0003113906 | BC8: 0.0012924121 | BD8: 0.00041875141 | BE8: 0.0013239876 | BF8: 0.00043294544 | BG8: 0.00074392165 | BH8: 0.00024302055 | BI8: 0.00054960924 | BJ8: 0.00012045861 | BK8: 0.00099192464 | BL8: 6.4626924e-05 | BM8: 0.0096364384 | BN8: 0.0040409456 | BO8: 0.00088546034 | BP8: 0.0060370831 | BQ8: 0.0033386609 | BR8: 0.00012166336 | BS8: 0.0036156661 | BT8: 0
B9: 0280 | C9: Produção florestal; pesca e aquicultura | D9: 3 | E9: 0.05286667 | F9: 0.051287311 | G9: 1.062448 | H9: 0.00034169594 | I9: 0.005020097 | J9: 0.0018480631 | K9: 0.00039323894 | L9: 0.12036483 | M9: 0.0039027118 | N9: 0.035705591 | O9: 0.0035926978 | P9: 0.0018209588 | Q9: 0.0036075681 | R9: 0.0023438152 | S9: 0.0019855709 | T9: 0.060227428 | U9: 0.12139833 | V9: 0.0013531206 | W9: 0.0070216472 | X9: 0.0042654674 | Y9: 0.0099447657 | Z9: 0.0031888624 | AA9: 0.0038935114 | AB9: 0.0027646513 | AC9: 0.023228525 | AD9: 0.0066057824 | AE9: 0.029107209 | AF9: 0.0016289606 | AG9: 0.009161539 | AH9: 0.0022302044 | AI9: 0.0035222374 | AJ9: 0.0064423515 | AK9: 0.0059243092 | AL9: 0.0043490723 | AM9: 0.0009204484 | AN9: 0.013343178 | AO9: 0.0016095538 | AP9: 0.0027772163 | AQ9: 0.0011272447 | AR9: 0.047732559 | AS9: 0.002539675 | AT9: 0.029564017 | AU9: 0.0050869761 | AV9: 0.00026525143 | AW9: 0.00029839391 | AX9: 0.0014949991 | AY9: 0.0013019462 | AZ9: 0.023200302 | BA9: 0.0010426577 | BB9: 0.00087871814 | BC9: 0.0028895395 | BD9: 0.0020376388 | BE9: 0.0042101043 | BF9: 0.0020528743 | BG9: 0.0031390822 | BH9: 0.00099811693 | BI9: 0.0021202463 | BJ9: 0.00099710103 | BK9: 0.0043117999 | BL9: 0.0002030075 | BM9: 0.0093723972 | BN9: 0.0044654121 | BO9: 0.0016032843 | BP9: 0.0059675754 | BQ9: 0.0048357067 | BR9: 0.00036879007 | BS9: 0.003561022 | BT9: 0
B10: 0580 | C10: Extração de carvão mineral e de minerais não-metálicos | D10: 4 | E10: 0.089898127 | F10: 0.044126438 | G10: 0.0019575907 | H10: 1.0135053 | I10: 0.049005884 | J10: 0.0071213242 | K10: 0.0018772722 | L10: 0.052077134 | M10: 0.0079213802 | N10: 0.056234122 | O10: 0.013025221 | P10: 0.0012115763 | Q10: 0.0080707562 | R10: 0.0033867205 | S10: 0.0029404227 | T10: 0.0027603969 | U10: 0.013672377 | V10: 0.00084756965 | W10: 0.041820162 | X10: 0.015578784 | Y10: 0.20360025 | Z10: 0.024859608 | AA10: 0.0095618248 | AB10: 0.0049007016 | AC10: 0.03085566 | AD10: 0.27247983 | AE10: 0.081897359 | AF10: 0.030255553 | AG10: 0.021429312 | AH10: 0.0028322973 | AI10: 0.01652804 | AJ10: 0.014823189 | AK10: 0.019749894 | AL10: 0.013449784 | AM10: 0.0028325614 | AN10: 0.010120016 | AO10: 0.0052625327 | AP10: 0.02703144 | AQ10: 0.030077707 | AR10: 0.47809003 | AS10: 0.0066726524 | AT10: 0.036577792 | AU10: 0.016609817 | AV10: 0.00062851824 | AW10: 0.00073753124 | AX10: 0.0040622263 | AY10: 0.0013998447 | AZ10: 0.013947959 | BA10: 0.00051950957 | BB10: 0.0010573018 | BC10: 0.0069047633 | BD10: 0.0029794757 | BE10: 0.0055319923 | BF10: 0.026027902 | BG10: 0.0033873742 | BH10: 0.0015722241 | BI10: 0.0020225477 | BJ10: 0.0012725278 | BK10: 0.0085155884 | BL10: 0.00036109631 | BM10: 0.025560446 | BN10: 0.0050285403 | BO10: 0.0022251177 | BP10: 0.0093481692 | BQ10: 0.0059663867 | BR10: 0.0010418681 | BS10: 0.0058511076 | BT10: 0
B11: 0680 | C11: Extração de petróleo e gás, inclusive as atividades de apoio | D11: 5 | E11: 0.042106516 | F11: 0.014833149 | G11: 0.0018978308 | H11: 0.002829712 | I11: 1.0438635 | J11: 0.017420278 | K11: 0.0037166854 | L11: 0.043409615 | M11: 0.0067743104 | N11: 0.039919507 | O11: 0.0068176279 | P11: 0.0009592676 | Q11: 0.0045036955 | R11: 0.0028805855 | S11: 0.002450605 | T11: 0.0029756941 | U11: 0.015392481 | V11: 0.00065030043 | W11: 0.61508775 | X11: 0.0057210874 | Y11: 0.039361194 | Z11: 0.010248265 | AA11: 0.0044544119 | AB11: 0.0054054183 | AC11: 0.013524772 | AD11: 0.013831679 | AE11: 0.018528015 | AF11: 0.010634683 | AG11: 0.01062322 | AH11: 0.0033137031 | AI11: 0.007626398 | AJ11: 0.0099002016 | AK11: 0.0086599985 | AL11: 0.005540116 | AM11: 0.0014241973 | AN11: 0.0047277838 | AO11: 0.0026903113 | AP11: 0.069136224 | AQ11: 0.0095624949 | AR11: 0.037303861 | AS11: 0.0044042743 | AT11: 0.071794214 | AU11: 0.12860443 | AV11: 0.0036781067 | AW11: 0.0054318633 | AX11: 0.008055567 | AY11: 0.00072310628 | AZ11: 0.010141055 | BA11: 0.00076729609 | BB11: 0.0012865864 | BC11: 0.0063078518 | BD11: 0.0026513968 | BE11: 0.0056905968 | BF11: 0.0017663271 | BG11: 0.0037790216 | BH11: 0.001918204 | BI11: 0.0024033598 | BJ11: 0.0017446177 | BK11: 0.0056450414 | BL11: 0.00093435637 | BM11: 0.022408137 | BN11: 0.0030913282 | BO11: 0.0024415206 | BP11: 0.0041066036 | BQ11: 0.0037504809 | BR11: 0.00087429325 | BS11: 0.0057094898 | BT11: 0
B12: 0791 | C12: Extração de minério de ferro, inclusive beneficiamentos e a aglomeração | D12: 6 | E12: 0.003770325 | F12: 0.0023871402 | G12: 0.00021245159 | H12: 0.00051416677 | I12: 0.030642771 | J12: 1.028374 | K12: 0.0016029542 | L12: 0.0084758009 | M12: 0.0007017571 | N12: 0.0062059757 | O12: 0.0035960699 | P12: 0.00013650239 | Q12: 0.00058817322 | R12: 0.00051058433 | S12: 0.00039984556 | T12: 0.00077957779 | U12: 0.0024547339 | V12: 0.00022836381 | W12: 0.019242119 | X12: 0.00063790943 | Y12: 0.0029833183 | Z12: 0.001864326 | AA12: 0.0011630761 | AB12: 0.00089974292 | AC12: 0.0037786745 | AD12: 0.0053881082 | AE12: 0.26420062 | AF12: 0.0052397175 | AG12: 0.047226841 | AH12: 0.0015251 | AI12: 0.010544502 | AJ12: 0.025754366 | AK12: 0.020395617 | AL12: 0.018730225 | AM12: 0.0025324963 | AN12: 0.0044213137 | AO12: 0.0066683431 | AP12: 0.0057437638 | AQ12: 0.0018170413 | AR12: 0.04871621 | AS12: 0.0045892628 | AT12: 0.012313224 | AU12: 0.0089918301 | AV12: 0.00039108063 | AW12: 0.00028241107 | AX12: 0.0012424409 | AY12: 0.00019771134 | AZ12: 0.0030038452 | BA12: 0.00016451956 | BB12: 0.00028249726 | BC12: 0.0016623923 | BD12: 0.00085093586 | BE12: 0.0012556314 | BF12: 0.00095008284 | BG12: 0.00088741816 | BH12: 0.00046716781 | BI12: 0.00054439488 | BJ12: 0.00091907033 | BK12: 0.0017173723 | BL12: 0.00016410597 | BM12: 0.0044383371 | BN12: 0.0008035218 | BO12: 0.00048394623 | BP12: 0.0015999494 | BQ12: 0.0012516056 | BR12: 0.00027726808 | BS12: 0.0010651097 | BT12: 0
B13: 0792 | C13: Extração de minerais metálicos não-ferrosos, inclusive beneficiamentos | D13: 7 | E13: 0.0093383978 | F13: 0.0036985416 | G13: 0.00032213848 | H13: 0.00068288992 | I13: 0.020986137 | J13: 0.0053012257 | K13: 1.0748199 | L13: 0.016502211 | M13: 0.0014319773 | N13: 0.015500805 | O13: 0.0046214749 | P13: 0.00029192145 | Q13: 0.0012958767 | R13: 0.0011567747 | S13: 0.00083712976 | T13: 0.0012547988 | U13: 0.0072255989 | V13: 0.0022697028 | W13: 0.014856427 | X13: 0.0013495727 | Y13: 0.011514871 | Z13: 0.0058829306 | AA13: 0.0021349559 | AB13: 0.0018756966 | AC13: 0.005575251 | AD13: 0.0079800257 | AE13: 0.10915833 | AF13: 0.467262 | AG13: 0.045885336 | AH13: 0.0050523322 | AI13: 0.074221817 | AJ13: 0.030983915 | AK13: 0.030273836 | AL13: 0.041275738 | AM13: 0.0088604036 | AN13: 0.020756503 | AO13: 0.015888122 | AP13: 0.011551893 | AQ13: 0.0033723284 | AR13: 0.064224554 | AS13: 0.012673065 | AT13: 0.021501478 | AU13: 0.015422752 | AV13: 0.0006948777 | AW13: 0.00037012348 | AX13: 0.0024001249 | AY13: 0.00037874256 | AZ13: 0.0047580553 | BA13: 0.00043578513 | BB13: 0.00063945423 | BC13: 0.0033274714 | BD13: 0.0018248755 | BE13: 0.0029671583 | BF13: 0.0022818165 | BG13: 0.0025292631 | BH13: 0.00085043333 | BI13: 0.0015367082 | BJ13: 0.0012236524 | BK13: 0.0035701948 | BL13: 0.00029691591 | BM13: 0.006579723 | BN13: 0.0015872563 | BO13: 0.0012001501 | BP13: 0.0032318844 | BQ13: 0.004305644 | BR13: 0.00080870014 | BS13: 0.0028724351 | BT13: 0
B14: 1091 | C14: Abate e produtos de carne, inclusive os produtos do laticínio e da pesca | D14: 8 | E14: 0.0012103904 | F14: 0.010089415 | G14: 0.00021814987 | H14: 9.0488457e-05 | I14: 0.00049614931 | J14: 0.00025329538 | K14: 6.469703e-05 | L14: 1.1081638 | M14: 0.00023406054 | N14: 0.013413902 | O14: 0.00046411879 | P14: 7.7952229e-05 | Q14: 0.00025346706 | R14: 0.00024737772 | S14: 0.0039913364 | T14: 0.00033540878 | U14: 0.00085017176 | V14: 4.5502014e-05 | W14: 0.002331244 | X14: 0.0038253601 | Y14: 0.00086354591 | Z14: 0.00087525943 | AA14: 0.0069347926 | AB14: 0.00058239013 | AC14: 0.00068286448 | AD14: 0.00046185085 | AE14: 0.00061259631 | AF14: 0.00027176053 | AG14: 0.0008703445 | AH14: 0.00027922458 | AI14: 0.0004432938 | AJ14: 0.00089836149 | AK14: 0.00040632403 | AL14: 0.00019329498 | AM14: 8.3298965e-05 | AN14: 0.00052464388 | AO14: 0.0001745046 | AP14: 0.00038986279 | AQ14: 0.00010307624 | AR14: 0.0013769596 | AS14: 0.00024771328 | AT14: 0.0045585587 | AU14: 0.00084160972 | AV14: 3.7371937e-05 | AW14: 0.00012070612 | AX14: 0.00020190229 | AY14: 0.001255925 | AZ14: 0.05536624 | BA14: 7.7968825e-05 | BB14: 0.00029961178 | BC14: 0.00077268206 | BD14: 0.00030030052 | BE14: 0.0010894768 | BF14: 0.00015990701 | BG14: 0.00067297725 | BH14: 0.00011770919 | BI14: 0.00046460686 | BJ14: 8.0251399e-05 | BK14: 0.00078589276 | BL14: 4.6978555e-05 | BM14: 0.010809174 | BN14: 0.0049213587 | BO14: 0.00103231 | BP14: 0.0073606052 | BQ14: 0.0036990208 | BR14: 9.4526256e-05 | BS14: 0.0037269987 | BT14: 0
B15: 1092 | C15: Fabricação e refino de açúcar | D15: 9 | E15: 0.018243234 | F15: 0.011045271 | G15: 0.00094125261 | H15: 0.0011559195 | I15: 0.0096631518 | J15: 0.0050138314 | K15: 0.0012119793 | L15: 0.037334486 | M15: 1.0231372 | N15: 0.096187877 | O15: 0.021748826 | P15: 0.00045855937 | Q15: 0.0017565222 | R15: 0.0013208023 | S15: 0.0012200539 | T15: 0.0016043873 | U15: 0.0059191398 | V15: 0.00033776434 | W15: 0.18541404 | X15: 0.01580487 | Y15: 0.013963178 | Z15: 0.014354022 | AA15: 0.011664003 | AB15: 0.0080962283 | AC15: 0.0055894122 | AD15: 0.0045821325 | AE15: 0.0061654156 | AF15: 0.0031834403 | AG15: 0.0042866036 | AH15: 0.0016064987 | AI15: 0.0031074529 | AJ15: 0.0055219652 | AK15: 0.0033691548 | AL15: 0.0018685367 | AM15: 0.00060770879 | AN15: 0.002135228 | AO15: 0.0015830565 | AP15: 0.0045484463 | AQ15: 0.0015740256 | AR15: 0.014890913 | AS15: 0.0042009327 | AT15: 0.032905435 | AU15: 0.046138772 | AV15: 0.0012713819 | AW15: 0.0018784448 | AX15: 0.0032730084 | AY15: 0.00046020186 | AZ15: 0.024962532 | BA15: 0.00043673008 | BB15: 0.00083034182 | BC15: 0.0032980403 | BD15: 0.0017714071 | BE15: 0.0038770766 | BF15: 0.0010433677 | BG15: 0.0027854605 | BH15: 0.0017534683 | BI15: 0.0017361889 | BJ15: 0.0017340643 | BK15: 0.0035835907 | BL15: 0.0008958785 | BM15: 0.011457568 | BN15: 0.0033439355 | BO15: 0.0011771242 | BP15: 0.0049836454 | BQ15: 0.0038890117 | BR15: 0.00055071541 | BS15: 0.0045557855 | BT15: 0
B16: 1093 | C16: Outros produtos alimentares | D16: 10 | E16: 0.012162999 | F16: 0.055718871 | G16: 0.004115826 | H16: 0.00080215377 | I16: 0.0022141847 | J16: 0.0012067955 | K16: 0.00032633697 | L16: 0.1483272 | M16: 0.001545824 | N16: 1.1164785 | O16: 0.0097194148 | P16: 0.00042012661 | Q16: 0.0013310917 | R16: 0.0011527417 | S16: 0.001434032 | T16: 0.0012763513 | U16: 0.0066768064 | V16: 0.00024385823 | W16: 0.020589398 | X16: 0.017260031 | Y16: 0.0052098528 | Z16: 0.0061045293 | AA16: 0.0057388574 | AB16: 0.0027936606 | AC16: 0.0035025203 | AD16: 0.0023709548 | AE16: 0.002895241 | AF16: 0.0011924067 | AG16: 0.0026793665 | AH16: 0.0011579895 | AI16: 0.0019356047 | AJ16: 0.0036879881 | AK16: 0.0013761361 | AL16: 0.00080323106 | AM16: 0.00032977443 | AN16: 0.0016638965 | AO16: 0.00069411849 | AP16: 0.0011980255 | AQ16: 0.00049131384 | AR16: 0.0058667938 | AS16: 0.001109984 | AT16: 0.023357244 | AU16: 0.0057962862 | AV16: 0.00019392187 | AW16: 0.00034435535 | AX16: 0.00076055888 | AY16: 0.00086246286 | AZ16: 0.043659845 | BA16: 0.00034127008 | BB16: 0.00067511508 | BC16: 0.0028831654 | BD16: 0.00098320354 | BE16: 0.0021964723 | BF16: 0.00054315092 | BG16: 0.0014469776 | BH16: 0.00040975122 | BI16: 0.0012321256 | BJ16: 0.00033392066 | BK16: 0.0016854477 | BL16: 0.00018293427 | BM16: 0.009811918 | BN16: 0.0050927534 | BO16: 0.0010798175 | BP16: 0.01007023 | BQ16: 0.0038751349 | BR16: 0.00031532347 | BS16: 0.0054188631 | BT16: 0
B17: 1100 | C17: Fabricação de bebidas | D17: 11 | E17: 0.0014997666 | F17: 0.0007805997 | G17: 6.4029404e-05 | H17: 0.00021017477 | I17: 0.0015932376 | J17: 0.00078848536 | K17: 0.00019780021 | L17: 0.012599059 | M17: 0.00045016166 | N17: 0.0060314915 | O17: 1.1010143 | P17: 0.00017017477 | Q17: 0.00054534429 | R17: 0.00058729203 | S17: 0.00054315639 | T17: 0.00041596719 | U17: 0.0019224969 | V17: 0.00012021048 | W17: 0.0027345357 | X17: 0.00054942747 | Y17: 0.0016833828 | Z17: 0.0017272201 | AA17: 0.00053413524 | AB17: 0.0015942943 | AC17: 0.0016347672 | AD17: 0.0011800891 | AE17: 0.0017067184 | AF17: 0.00073516176 | AG17: 0.0017717689 | AH17: 0.00079586223 | AI17: 0.0012442795 | AJ17: 0.0031084544 | AK17: 0.0013220111 | AL17: 0.00052763614 | AM17: 0.00025423911 | AN17: 0.00079252987 | AO17: 0.00082678759 | AP17: 0.0012464129 | AQ17: 0.00026632843 | AR17: 0.0032248028 | AS17: 0.00074448465 | AT17: 0.0087929729 | AU17: 0.0014471416 | AV17: 9.9417751e-05 | AW17: 0.00052576208 | AX17: 0.00058782772 | AY17: 0.0043528933 | AZ17: 0.27619535 | BA17: 0.00021476316 | BB17: 0.0011695999 | BC17: 0.0022981729 | BD17: 0.00094315425 | BE17: 0.005497682 | BF17: 0.00053656857 | BG17: 0.002621149 | BH17: 0.00025391641 | BI17: 0.0015966672 | BJ17: 0.00019827978 | BK17: 0.00230708 | BL17: 0.00011482641 | BM17: 0.014124091 | BN17: 0.0033434863 | BO17: 0.00089541598 | BP17: 0.0085791403 | BQ17: 0.0068912497 | BR17: 0.00055089298 | BS17: 0.013311316 | BT17: 0
B18: 1200 | C18: Fabricação de produtos do fumo | D18: 12 | E18: 0.00073202046 | F18: 0.00020825918 | G18: 1.4797911e-05 | H18: 2.7840246e-05 | I18: 0.00045189712 | J18: 0.00035438881 | K18: 7.0554264e-05 | L18: 0.002116425 | M18: 0.00013824073 | N18: 0.0013728963 | O18: 0.00014781322 | P18: 1.0363571 | Q18: 0.00015813428 | R18: 0.00017288915 | S18: 0.0001592081 | T18: 0.00011786298 | U18: 0.00061998466 | V18: 3.4111149e-05 | W18: 0.00053592274 | X18: 0.00015463619 | Y18: 0.00039034469 | Z18: 0.00036822967 | AA18: 0.00010642697 | AB18: 0.00034186 | AC18: 0.00045038954 | AD18: 0.00033089296 | AE18: 0.00050645243 | AF18: 0.00020103965 | AG18: 0.00044699609 | AH18: 0.00020927207 | AI18: 0.00036817046 | AJ18: 0.0013658805 | AK18: 0.00024898568 | AL18: 0.00013181913 | AM18: 7.23048e-05 | AN18: 0.00021651158 | AO18: 0.00046129678 | AP18: 0.00015096046 | AQ18: 5.1774313e-05 | AR18: 0.00075245308 | AS18: 9.6003598e-05 | AT18: 0.001628692 | AU18: 0.00023317818 | AV18: 2.9125434e-05 | AW18: 1.4230509e-05 | AX18: 8.1604899e-05 | AY18: 1.2830631e-05 | AZ18: 0.0002453993 | BA18: 6.2982126e-05 | BB18: 9.4577029e-05 | BC18: 0.00051038665 | BD18: 0.00016080874 | BE18: 0.00016475573 | BF18: 4.7567572e-05 | BG18: 0.00014934868 | BH18: 0.00012059708 | BI18: 0.00015148698 | BJ18: 3.1958548e-05 | BK18: 0.00022948255 | BL18: 1.7467103e-05 | BM18: 0.00019988648 | BN18: 7.0143082e-05 | BO18: 5.036322e-05 | BP18: 0.00011838566 | BQ18: 0.00012792955 | BR18: 2.3490684e-05 | BS18: 8.8129346e-05 | BT18: 0
... B74: 9700 | C74: Serviços domésticos | D74: 68 | E74: 0 | F74: 0 | G74: 0 | H74: 0 | I74: 0 | J74: 0 | K74: 0 | L74: 0 | M74: 0 | N74: 0 | O74: 0 | P74: 0 | Q74: 0 | R74: 0 | S74: 0 | T74: 0 | U74: 0 | V74: 0 | W74: 0 | X74: 0 | Y74: 0 | Z74: 0 | AA74: 0 | AB74: 0 | AC74: 0 | AD74: 0 | AE74: 0 | AF74: 0 | AG74: 0 | AH74: 0 | AI74: 0 | AJ74: 0 | AK74: 0 | AL74: 0 | AM74: 0 | AN74: 0 | AO74: 0 | AP74: 0 | AQ74: 0 | AR74: 0 | AS74: 0 | AT74: 0 | AU74: 0 | AV74: 0 | AW74: 0 | AX74: 0 | AY74: 0 | AZ74: 0 | BA74: 0 | BB74: 0 | BC74: 0 | BD74: 0 | BE74: 0 | BF74: 0 | BG74: 0 | BH74: 0 | BI74: 0 | BJ74: 0 | BK74: 0 | BL74: 0 | BM74: 0 | BN74: 0 | BO74: 0 | BP74: 0 | BQ74: 0 | BR74: 0 | BS74: 0 | BT74: 1

Sheet B2_2020
B2: Matriz B2 — modelo fechado para as famílias (2020)
B3: Inversa do sistema com famílias endógenas (tipo II, fechamento por VALOR ADICIONADO — convenção das abas 20/22/23 da MIP); última linha/coluna = famílias.
B6: Código | C6: Atividades | E6: 1 | F6: 2 | G6: 3 | H6: 4 | I6: 5 | J6: 6 | K6: 7 | L6: 8 | M6: 9 | N6: 10 | O6: 11 | P6: 12 | Q6: 13 | R6: 14 | S6: 15 | T6: 16 | U6: 17 | V6: 18 | W6: 19 | X6: 20 | Y6: 21 | Z6: 22 | AA6: 23 | AB6: 24 | AC6: 25 | AD6: 26 | AE6: 27 | AF6: 28 | AG6: 29 | AH6: 30 | AI6: 31 | AJ6: 32 | AK6: 33 | AL6: 34 | AM6: 35 | AN6: 36 | AO6: 37 | AP6: 38 | AQ6: 39 | AR6: 40 | AS6: 41 | AT6: 42 | AU6: 43 | AV6: 44 | AW6: 45 | AX6: 46 | AY6: 47 | AZ6: 48 | BA6: 49 | BB6: 50 | BC6: 51 | BD6: 52 | BE6: 53 | BF6: 54 | BG6: 55 | BH6: 56 | BI6: 57 | BJ6: 58 | BK6: 59 | BL6: 60 | BM6: 61 | BN6: 62 | BO6: 63 | BP6: 64 | BQ6: 65 | BR6: 66 | BS6: 67 | BT6: 68 | BU6: FAM
B7: 0191 | C7: Agricultura, inclusive o apoio à agricultura e a pós-colheita | D7: 1 | E7: 1.094026 | F7: 0.14950081 | G7: 0.093170726 | H7: 0.078887581 | I7: 0.068871743 | J7: 0.076594309 | K7: 0.075630762 | L7: 0.20884122 | M7: 0.57552788 | N7: 0.42108971 | O7: 0.12549548 | P7: 0.38302297 | Q7: 0.2347565 | R7: 0.13311777 | S7: 0.11967189 | T7: 0.099343841 | U7: 0.1190866 | V7: 0.073616279 | W7: 0.10111505 | X7: 0.50881681 | Y7: 0.067165149 | Z7: 0.090878955 | AA7: 0.093721677 | AB7: 0.11684879 | AC7: 0.089380582 | AD7: 0.096453592 | AE7: 0.088602577 | AF7: 0.076756647 | AG7: 0.097050151 | AH7: 0.050665817 | AI7: 0.086371472 | AJ7: 0.10433956 | AK7: 0.053292142 | AL7: 0.062449176 | AM7: 0.051807434 | AN7: 0.091151696 | AO7: 0.061182803 | AP7: 0.068195421 | AQ7: 0.075132887 | AR7: 0.072932329 | AS7: 0.071401281 | AT7: 0.10292018 | AU7: 0.081300993 | AV7: 0.071375416 | AW7: 0.061988811 | AX7: 0.077063846 | AY7: 0.093551158 | AZ7: 0.12175942 | BA7: 0.10988153 | BB7: 0.099269113 | BC7: 0.10729934 | BD7: 0.078766436 | BE7: 0.07735652 | BF7: 0.080099287 | BG7: 0.082026898 | BH7: 0.076132548 | BI7: 0.082524108 | BJ7: 0.077700063 | BK7: 0.079724815 | BL7: 0.082147065 | BM7: 0.080673987 | BN7: 0.081670273 | BO7: 0.078444919 | BP7: 0.081307957 | BQ7: 0.073017937 | BR7: 0.076862809 | BS7: 0.080093941 | BT7: 0.0811191 | BU7: 0.0811191
B8: 0192 | C8: Pecuária, inclusive o apoio à pecuária | D8: 2 | E8: 0.037817188 | F8: 1.0897363 | G8: 0.047496272 | H8: 0.036915175 | I8: 0.033689918 | J8: 0.038340425 | K8: 0.036258833 | L8: 0.40165256 | M8: 0.045087365 | N8: 0.068757034 | O8: 0.038108958 | P8: 0.055668993 | Q8: 0.048078263 | R8: 0.048654799 | S8: 0.064218454 | T8: 0.051606767 | U8: 0.057138229 | V8: 0.036860383 | W8: 0.029405371 | X8: 0.054320324 | Y8: 0.030245956 | Z8: 0.039515503 | AA8: 0.046902111 | AB8: 0.053030932 | AC8: 0.041852991 | AD8: 0.04626103 | AE8: 0.042702954 | AF8: 0.037516784 | AG8: 0.046657304 | AH8: 0.024461698 | AI8: 0.041013493 | AJ8: 0.049490147 | AK8: 0.026019684 | AL8: 0.030202844 | AM8: 0.025456651 | AN8: 0.044061247 | AO8: 0.030609733 | AP8: 0.035139449 | AQ8: 0.038342457 | AR8: 0.037548052 | AS8: 0.036010807 | AT8: 0.045499322 | AU8: 0.036438367 | AV8: 0.035070726 | AW8: 0.028504645 | AX8: 0.039448179 | AY8: 0.06019738 | AZ8: 0.074169574 | BA8: 0.053438623 | BB8: 0.049342604 | BC8: 0.053224375 | BD8: 0.040649922 | BE8: 0.040503544 | BF8: 0.042268546 | BG8: 0.042413456 | BH8: 0.038786847 | BI8: 0.041856867 | BJ8: 0.039331942 | BK8: 0.040938889 | BL8: 0.041991745 | BM8: 0.04250622 | BN8: 0.043267614 | BO8: 0.041254106 | BP8: 0.042656708 | BQ8: 0.038328766 | BR8: 0.039537499 | BS8: 0.040541863 | BT8: 0.042883217 | BU8: 0.042883217
B9: 0280 | C9: Produção florestal; pesca e aquicultura | D9: 3 | E9: 0.011562443 | F9: 0.018407171 | G9: 1.0710468 | H9: 0.0083985307 | I9: 0.008070255 | J9: 0.0087030469 | K9: 0.008381876 | L9: 0.025089976 | M9: 0.011056049 | N9: 0.013691274 | O9: 0.0092673313 | P9: 0.013360763 | Q9: 0.010986483 | R9: 0.010387356 | S9: 0.0130316 | T9: 0.074649944 | U9: 0.054042605 | V9: 0.010854737 | W9: 0.0067217351 | X9: 0.011482917 | Y9: 0.0082893316 | Z9: 0.0093325345 | AA9: 0.0095805835 | AB9: 0.012504731 | AC9: 0.015942049 | AD9: 0.012379554 | AE9: 0.016925897 | AF9: 0.0085947358 | AG9: 0.012879702 | AH9: 0.0059964099 | AI9: 0.010146998 | AJ9: 0.012198324 | AK9: 0.0070245426 | AL9: 0.0082302402 | AM9: 0.0063411011 | AN9: 0.015602092 | AO9: 0.0073126732 | AP9: 0.0079089989 | AQ9: 0.0087312887 | AR9: 0.010989497 | AS9: 0.0083508609 | AT9: 0.010646536 | AU9: 0.008306112 | AV9: 0.0079197076 | AW9: 0.0064606438 | AX9: 0.0088773212 | AY9: 0.010762305 | AZ9: 0.011800709 | BA9: 0.014026046 | BB9: 0.011336009 | BC9: 0.011956387 | BD9: 0.0091646771 | BE9: 0.0089790833 | BF9: 0.0092869712 | BG9: 0.0096307924 | BH9: 0.008866819 | BI9: 0.0096651465 | BJ9: 0.0091469299 | BK9: 0.0094049042 | BL9: 0.0092564316 | BM9: 0.009210812 | BN9: 0.0094359219 | BO9: 0.0091765867 | BP9: 0.0092176578 | BQ9: 0.0085154908 | BR9: 0.0088590572 | BS9: 0.0087631423 | BT9: 0.0093249652 | BU9: 0.0093249652
B10: 0580 | C10: Extração de carvão mineral e de minerais não-metálicos | D10: 4 | E10: 0.0053494112 | F10: 0.0066203371 | G10: 0.0028491572 | H10: 1.0151141 | I10: 0.0062547262 | J10: 0.0027547658 | K10: 0.0034339539 | L10: 0.0055708258 | M10: 0.0043876722 | N10: 0.0053544211 | O10: 0.0047045684 | P10: 0.0034670814 | Q10: 0.0050229428 | R10: 0.0030574052 | S10: 0.0040773215 | T10: 0.0036225269 | U10: 0.0049570778 | V10: 0.0026554929 | W10: 0.0034353135 | X10: 0.0068279113 | Y10: 0.023760279 | Z10: 0.0065436726 | AA10: 0.0050904477 | AB10: 0.0036143179 | AC10: 0.0070588107 | AD10: 0.064306113 | AE10: 0.014168249 | AF10: 0.0098076178 | AG10: 0.0059866592 | AH10: 0.0016369602 | AI10: 0.0056417609 | AJ10: 0.0043663565 | AK10: 0.0039262729 | AL10: 0.0044282801 | AM10: 0.0026925298 | AN10: 0.0045653293 | AO10: 0.0027322223 | AP10: 0.0033233528 | AQ10: 0.0089202376 | AR10: 0.019723171 | AS10: 0.0024840986 | AT10: 0.0026832144 | AU10: 0.0025293803 | AV10: 0.0020478153 | AW10: 0.0018981831 | AX10: 0.0023714959 | AY10: 0.0032493985 | AZ10: 0.0029375352 | BA10: 0.0030784919 | BB10: 0.002779681 | BC10: 0.0032632686 | BD10: 0.0021419372 | BE10: 0.0019888639 | BF10: 0.0027464395 | BG10: 0.0022006348 | BH10: 0.0022142499 | BI10: 0.0022430258 | BJ10: 0.0022264627 | BK10: 0.00252344 | BL10: 0.0020593124 | BM10: 0.0024693571 | BN10: 0.002154896 | BO10: 0.0021672375 | BP10: 0.0025795745 | BQ10: 0.0020649824 | BR10: 0.0023668362 | BS10: 0.0024210191 | BT10: 0.0019299453 | BU10: 0.0019299453
B11: 0680 | C11: Extração de petróleo e gás, inclusive as atividades de apoio | D11: 5 | E11: 0.038176106 | F11: 0.037895466 | G11: 0.033532392 | H11: 0.049756591 | I11: 1.0629567 | J11: 0.04839921 | K11: 0.05796376 | L11: 0.058579665 | M11: 0.045904449 | N11: 0.050374413 | O11: 0.037212427 | P11: 0.036878258 | Q11: 0.041002865 | R11: 0.034241829 | S11: 0.044455962 | T11: 0.043673412 | U11: 0.060332521 | V11: 0.028993517 | W11: 0.34599412 | X11: 0.042670124 | Y11: 0.061327243 | Z11: 0.042336428 | AA11: 0.035792218 | AB11: 0.044477433 | AC11: 0.046821309 | AD11: 0.058083238 | AE11: 0.05235107 | AF11: 0.050319062 | AG11: 0.046203043 | AH11: 0.020573577 | AI11: 0.041265434 | AJ11: 0.042919321 | AK11: 0.027182503 | AL11: 0.030150664 | AM11: 0.022511964 | AN11: 0.037184886 | AO11: 0.024644308 | AP11: 0.066278783 | AQ11: 0.045485084 | AR11: 0.034960964 | AS11: 0.026571338 | AT11: 0.039550486 | AU11: 0.093656332 | AV11: 0.049323701 | AW11: 0.066025768 | AX11: 0.035155198 | AY11: 0.02986314 | AZ11: 0.030554562 | BA11: 0.041275789 | BB11: 0.035511875 | BC11: 0.038700292 | BD11: 0.026308018 | BE11: 0.025149282 | BF11: 0.02497613 | BG11: 0.027845828 | BH11: 0.028306316 | BI11: 0.028575778 | BJ11: 0.029206545 | BK11: 0.028125816 | BL11: 0.02897866 | BM11: 0.029229472 | BN11: 0.025712589 | BO11: 0.02727861 | BP11: 0.025770367 | BQ11: 0.023753947 | BR11: 0.027820152 | BS11: 0.02889062 | BT11: 0.024811116 | BU11: 0.024811116
B12: 0791 | C12: Extração de minério de ferro, inclusive beneficiamentos e a aglomeração | D12: 6 | E12: 0.003437448 | F12: 0.0042735126 | G12: 0.0035025735 | H12: 0.0059221311 | I12: 0.022354176 | J12: 1.030969 | K12: 0.013041074 | L12: 0.0072020223 | M12: 0.004301829 | N12: 0.0055784602 | O12: 0.008220611 | P12: 0.0040455712 | Q12: 0.0042438671 | R12: 0.0040426653 | S12: 0.0050966154 | T12: 0.0061456036 | U12: 0.0067361263 | V12: 0.0043554228 | W12: 0.0086786578 | X12: 0.0042154594 | Y12: 0.0042038556 | Z12: 0.0050411605 | AA12: 0.0051748112 | AB12: 0.0051441351 | AC12: 0.0070886269 | AD12: 0.01134051 | AE12: 0.27056023 | AF12: 0.012022462 | AG12: 0.061906166 | AH12: 0.0036860351 | AI12: 0.019287391 | AJ12: 0.029100396 | AK12: 0.021136556 | AL12: 0.031144052 | AM12: 0.011186295 | AN12: 0.010752644 | AO12: 0.013832307 | AP12: 0.0049091325 | AQ12: 0.0055416886 | AR12: 0.014872591 | AS12: 0.006537868 | AT12: 0.0046127152 | AU12: 0.0058074419 | AV12: 0.0044255944 | AW12: 0.0035976893 | AX12: 0.0039552667 | AY12: 0.0040563342 | AZ12: 0.0043859545 | BA12: 0.0051489568 | BB12: 0.004420963 | BC12: 0.0050758687 | BD12: 0.0034053307 | BE12: 0.0030407304 | BF12: 0.0031087651 | BG12: 0.0034397809 | BH12: 0.0036210398 | BI12: 0.0035435828 | BJ12: 0.0049850396 | BK12: 0.0037361868 | BL12: 0.0034278628 | BM12: 0.003540316 | BN12: 0.0031568182 | BO12: 0.0032898271 | BP12: 0.0036104494 | BQ12: 0.0031064263 | BR12: 0.0037808093 | BS12: 0.0034623171 | BT12: 0.0029507275 | BU12: 0.0029507275
B13: 0792 | C13: Extração de minerais metálicos não-ferrosos, inclusive beneficiamentos | D13: 7 | E13: 0.0011804958 | F13: 0.0012333828 | G13: 0.0010754946 | H13: 0.0015049879 | I13: 0.0028256316 | J13: 0.0016556867 | K13: 1.07562 | L13: 0.0022550014 | M13: 0.0013845983 | N13: 0.0019558344 | O13: 0.0019253689 | P13: 0.0013249262 | Q13: 0.001403613 | R13: 0.0013478462 | S13: 0.0016567051 | T13: 0.001757448 | U13: 0.0025861262 | V13: 0.0036347686 | W13: 0.001419628 | X13: 0.0013752914 | Y13: 0.0019468988 | Z13: 0.0020211648 | AA13: 0.0015477953 | AB13: 0.0016713071 | AC13: 0.0018730947 | AD13: 0.0028586607 | AE13: 0.017637122 | AF13: 0.12955748 | AG13: 0.0096501841 | AH13: 0.0015640841 | AI13: 0.018498822 | AJ13: 0.0057762157 | AK13: 0.0049217067 | AL13: 0.010359443 | AM13: 0.0055710447 | AN13: 0.0065243164 | AO13: 0.0049149652 | AP13: 0.0015529077 | AQ13: 0.0016815691 | AR13: 0.0032780817 | AS13: 0.0025124322 | AT13: 0.0014167514 | AU13: 0.0016781188 | AV13: 0.0013335686 | AW13: 0.00096062986 | AX13: 0.0012549677 | AY13: 0.0012762271 | AZ13: 0.0012698778 | BA13: 0.0018067554 | BB13: 0.0014707357 | BC13: 0.0016311169 | BD13: 0.0011184345 | BE13: 0.0010095387 | BF13: 0.0010312132 | BG13: 0.0011902755 | BH13: 0.0011385878 | BI13: 0.0012382089 | BJ13: 0.0013464316 | BK13: 0.0012159732 | BL13: 0.0010980263 | BM13: 0.0010857381 | BN13: 0.0010299036 | BO13: 0.0011082635 | BP13: 0.0011646614 | BQ13: 0.0011407595 | BR13: 0.0013682721 | BS13: 0.0012160856 | BT13: 0.00097219211 | BU13: 0.00097219211
B14: 1091 | C14: Abate e produtos de carne, inclusive os produtos do laticínio e da pesca | D14: 8 | E14: 0.075296959 | F14: 0.096648102 | G14: 0.087729308 | H14: 0.079009525 | I14: 0.072335745 | J14: 0.082364592 | K14: 0.077563498 | L14: 1.2300982 | M14: 0.08828479 | N14: 0.11156371 | O14: 0.078594168 | P14: 0.090257794 | Q14: 0.08427885 | R14: 0.089522502 | S14: 0.1501667 | T14: 0.099426039 | U14: 0.11461625 | V14: 0.078989342 | W14: 0.062382228 | X14: 0.11052673 | Y14: 0.064225652 | Z14: 0.084581568 | AA14: 0.11385647 | AB14: 0.11383762 | AC14: 0.088642932 | AD14: 0.097616726 | AE14: 0.090351673 | AF14: 0.078859319 | AG14: 0.10020289 | AH14: 0.052604015 | AI14: 0.087910058 | AJ14: 0.10636879 | AK14: 0.05572127 | AL14: 0.064464257 | AM14: 0.054653654 | AN14: 0.093643945 | AO14: 0.065963977 | AP14: 0.075958244 | AQ14: 0.082498256 | AR14: 0.077381175 | AS14: 0.077647297 | AT14: 0.097375552 | AU14: 0.078445556 | AV14: 0.07567052 | AW14: 0.061349037 | AX14: 0.084824086 | AY14: 0.10474308 | AZ14: 0.16806369 | BA14: 0.11483785 | BB14: 0.10644457 | BC14: 0.11378818 | BD14: 0.087769665 | BE14: 0.087549695 | BF14: 0.091411233 | BG14: 0.091656778 | BH14: 0.083217897 | BI14: 0.090200992 | BJ14: 0.084885578 | BK14: 0.088255601 | BL14: 0.090776254 | BM14: 0.092151629 | BN14: 0.094204334 | BO14: 0.089530925 | BP14: 0.093494837 | BQ14: 0.083041545 | BR14: 0.085261385 | BS14: 0.087179854 | BT14: 0.092922799 | BU14: 0.092922799
B15: 1092 | C15: Fabricação e refino de açúcar | D15: 9 | E15: 0.010354719 | F15: 0.012116863 | G15: 0.010773059 | H15: 0.011859352 | I15: 0.010559649 | J15: 0.011054164 | K15: 0.011863019 | L15: 0.01976925 | M15: 1.0324706 | N15: 0.027938728 | O15: 0.024174941 | P15: 0.011385638 | Q15: 0.011063161 | R15: 0.010913496 | S15: 0.013845413 | T15: 0.013209173 | U15: 0.015498702 | V15: 0.0096395089 | W15: 0.0361725 | X15: 0.025080116 | Y15: 0.011443913 | Z15: 0.017352476 | AA15: 0.021071645 | AB15: 0.018547791 | AC15: 0.012221766 | AD15: 0.013496841 | AE15: 0.012373324 | AF15: 0.010973389 | AG15: 0.012889316 | AH15: 0.0065246819 | AI15: 0.011466411 | AJ15: 0.013689028 | AK15: 0.007334148 | AL15: 0.0081594361 | AM15: 0.0068159487 | AN15: 0.011522886 | AO15: 0.0082669988 | AP15: 0.0090105717 | AQ15: 0.0099661374 | AR15: 0.0099410165 | AS15: 0.0099781385 | AT15: 0.012199728 | AU15: 0.016146664 | AV15: 0.011086911 | AW15: 0.011562925 | AX15: 0.010580494 | AY15: 0.010227961 | AZ15: 0.015613295 | BA15: 0.014010723 | BB15: 0.012617601 | BC15: 0.01339149 | BD15: 0.0099608508 | BE15: 0.0097228291 | BF15: 0.0099041688 | BG15: 0.010525296 | BH15: 0.010569771 | BI15: 0.0105697 | BJ15: 0.011036585 | BK15: 0.010271383 | BL15: 0.011086193 | BM15: 0.010279581 | BN15: 0.010182222 | BO15: 0.009891362 | BP15: 0.010199272 | BQ15: 0.0092866125 | BR15: 0.010045619 | BS15: 0.010316509 | BT15: 0.0099714392 | BU15: 0.0099714392
B16: 1093 | C16: Outros produtos alimentares | D16: 10 | E16: 0.083211188 | F16: 0.18447432 | G16: 0.12386721 | H16: 0.091124666 | I16: 0.075229112 | J16: 0.084836052 | K16: 0.081983898 | L16: 0.26866907 | M16: 0.095596689 | N16: 1.2145676 | O16: 0.11610771 | P16: 0.098122071 | Q16: 0.091825754 | R16: 0.095162002 | S16: 0.12244535 | T16: 0.10888246 | U16: 0.13371761 | V16: 0.08315737 | W16: 0.078564302 | X16: 0.1829358 | Y16: 0.072391303 | Z16: 0.10190426 | AA16: 0.1056099 | AB16: 0.12389353 | AC16: 0.096847114 | AD16: 0.10508684 | AE16: 0.096240169 | AF16: 0.083146043 | AG16: 0.10593419 | AH16: 0.05560941 | AI16: 0.093867482 | AJ16: 0.11347381 | AK16: 0.05808414 | AL16: 0.066903638 | AM16: 0.057017503 | AN16: 0.098797692 | AO16: 0.068324718 | AP16: 0.076916012 | AQ16: 0.084151685 | AR16: 0.080331087 | AS16: 0.079649673 | AT16: 0.10347316 | AU16: 0.083145005 | AV16: 0.077791341 | AW16: 0.064790031 | AX16: 0.086346823 | AY16: 0.097027669 | AZ16: 0.14805097 | BA16: 0.1212167 | BB16: 0.11031747 | BC16: 0.1187309 | BD16: 0.089133362 | BE16: 0.088249341 | BF16: 0.091711594 | BG16: 0.092970086 | BH16: 0.084862271 | BI16: 0.092857418 | BJ16: 0.086563419 | BK16: 0.08960552 | BL16: 0.092023531 | BM16: 0.091750304 | BN16: 0.09440841 | BO16: 0.089715223 | BP16: 0.097788262 | BQ16: 0.083283115 | BR16: 0.087544266 | BS16: 0.09102419 | BT16: 0.093013779 | BU16: 0.093013779
B17: 1100 | C17: Fabricação de bebidas | D17: 11 | E17: 0.021588907 | F17: 0.022425338 | G17: 0.024698135 | H17: 0.023073925 | I17: 0.021138252 | J17: 0.023905274 | K17: 0.022725869 | L17: 0.038014705 | M17: 0.025535639 | N17: 0.029568126 | O17: 1.1229893 | P17: 0.026304761 | Q17: 0.024573997 | R17: 0.026102455 | S17: 0.032097328 | T17: 0.028543901 | U17: 0.033587146 | V17: 0.022974257 | W17: 0.017874212 | X17: 0.026413151 | Y17: 0.018712029 | Z17: 0.024806756 | AA17: 0.02039483 | AB17: 0.033633441 | AC17: 0.02599355 | AD17: 0.028581046 | AE17: 0.026510773 | AF17: 0.023067589 | AG17: 0.029292126 | AH17: 0.015463061 | AI17: 0.025895434 | AJ17: 0.031756861 | AK17: 0.016465522 | AL17: 0.018761663 | AM17: 0.016023897 | AN17: 0.027027187 | AO17: 0.019582669 | AP17: 0.02197867 | AQ17: 0.023784183 | AR17: 0.022427501 | AS17: 0.022499663 | AT17: 0.028173536 | AU17: 0.022583161 | AV17: 0.021861881 | AW17: 0.019022942 | AX17: 0.024529076 | AY17: 0.043598013 | AZ17: 0.13302596 | BA17: 0.033632087 | BB17: 0.032548779 | BC17: 0.033394417 | BD17: 0.025423253 | BE17: 0.025671018 | BF17: 0.026239699 | BG17: 0.0269857 | BH17: 0.023998295 | BI17: 0.026721276 | BJ17: 0.024484598 | BK17: 0.025773855 | BL17: 0.026136317 | BM17: 0.026558582 | BN17: 0.026376482 | BO17: 0.025434292 | BP17: 0.026766513 | BQ17: 0.024575407 | BR17: 0.025518659 | BS17: 0.030027163 | BT17: 0.026625118 | BU17: 0.026625118
B18: 1200 | C18: Fabricação de produtos do fumo | D18: 12 | E18: 0.0035089582 | F18: 0.0036229259 | G18: 0.0040197272 | H18: 0.0036490005 | I18: 0.0033822685 | J18: 0.003867035 | K18: 0.0036337174 | L18: 0.005803429 | M18: 0.0041076781 | N18: 0.0046504247 | O18: 0.0036187297 | P18: 1.0405008 | Q18: 0.0039125364 | R18: 0.004167946 | S18: 0.0050874859 | T18: 0.0045501624 | U18: 0.0053261173 | V18: 0.0036863678 | W18: 0.0028451958 | X18: 0.0042348125 | Y18: 0.0029639779 | Z18: 0.0038783061 | AA18: 0.0032240941 | AB18: 0.0052755201 | AC18: 0.0041158222 | AD18: 0.0045440036 | AE18: 0.0042148843 | AF18: 0.0036752983 | AG18: 0.0046259202 | AH18: 0.0024504033 | AI18: 0.0040987081 | AJ18: 0.0050262579 | AK18: 0.002590156 | AL18: 0.0030064213 | AM18: 0.0025527857 | AN18: 0.0043177991 | AO18: 0.0031430024 | AP18: 0.0035449932 | AQ18: 0.0038537539 | AR18: 0.0036039636 | AS18: 0.0036202701 | AT18: 0.004514955 | AU18: 0.0036468137 | AV18: 0.0035380841 | AW18: 0.0027961419 | AX18: 0.0039578198 | AY18: 0.0037804915 | AZ18: 0.0036232321 | BA18: 0.0053569725 | BB18: 0.0048841853 | BC18: 0.0052973445 | BD18: 0.0040977966 | BE18: 0.0040760584 | BF18: 0.0042788377 | BG18: 0.0042528743 | BH18: 0.0038965417 | BI18: 0.0041733584 | BJ18: 0.0039610472 | BK18: 0.0040954642 | BL18: 0.0042396379 | BM18: 0.0040983551 | BN18: 0.0041766954 | BO18: 0.0040626964 | BP18: 0.0038276324 | BQ18: 0.0036794441 | BR18: 0.003959263 | BS18: 0.0036888335 | BT18: 0.0043526792 | BU18: 0.0043526792
... B75: FAM | C75: Famílias (VA ↔ consumo) | D75: 69 | E75: 1.62516 | F75: 1.6808127 | G75: 1.8712156 | H75: 1.6915342 | I75: 1.5615884 | J75: 1.7845931 | K75: 1.6700176 | L75: 2.6627947 | M75: 1.899409 | N75: 2.139968 | O75: 1.6748323 | P75: 1.9317932 | Q75: 1.8015712 | R75: 1.9213555 | S75: 2.3370095 | T75: 2.0972194 | U75: 2.4416546 | V75: 1.7041715 | W75: 1.3167496 | X75: 1.9572063 | Y75: 1.3668981 | Z75: 1.7832004 | AA75: 1.4889154 | AB75: 2.4279204 | AC75: 1.8922125 | AD75: 2.0922111 | AE75: 1.9385871 | AF75: 1.6945688 | AG75: 2.1279802 | AH75: 1.1279427 | AI75: 1.8810959 | AJ75: 2.2728608 | AK75: 1.1953566 | AL75: 1.3910614 | AM75: 1.1761982 | AN75: 1.9931855 | AO75: 1.4234073 | AP75: 1.6492978 | AQ75: 1.7923353 | AR75: 1.6702947 | AS75: 1.6833852 | AT75: 2.0942248 | AU75: 1.6957035 | AV75: 1.6416601 | AW75: 1.2991449 | AX75: 1.8408342 | AY75: 1.7574722 | AZ75: 1.6810062 | BA75: 2.4666705 | BB75: 2.2574171 | BC75: 2.4456377 | BD75: 1.9042245 | BE75: 1.8983867 | BF75: 1.9942779 | BG75: 1.9778285 | BH75: 1.803318 | BI75: 1.9351924 | BJ75: 1.8425342 | BK75: 1.9026591 | BL75: 1.9734832 | BM75: 1.9089021 | BN75: 1.9457254 | BO75: 1.8911584 | BP75: 1.7805727 | BQ75: 1.7121311 | BR75: 1.841016 | BS75: 1.7156328 | BT75: 2.0292414 | BU75: 2.0292414

Sheet A_2010
B2: Matriz A — coeficientes técnicos nacionais (2010)
B3: a(i,j) = Z(i,j)/x(j); reproduz a aba 13 do arquivo-fonte (desvio < 1e-15).
B6: Código | C6: Atividades | E6: 1 | F6: 2 | G6: 3 | H6: 4 | I6: 5 | J6: 6 | K6: 7 | L6: 8 | M6: 9 | N6: 10 | O6: 11 | P6: 12 | Q6: 13 | R6: 14 | S6: 15 | T6: 16 | U6: 17 | V6: 18 | W6: 19 | X6: 20 | Y6: 21 | Z6: 22 | AA6: 23 | AB6: 24 | AC6: 25 | AD6: 26 | AE6: 27 | AF6: 28 | AG6: 29 | AH6: 30 | AI6: 31 | AJ6: 32 | AK6: 33 | AL6: 34 | AM6: 35 | AN6: 36 | AO6: 37 | AP6: 38 | AQ6: 39 | AR6: 40 | AS6: 41 | AT6: 42 | AU6: 43 | AV6: 44 | AW6: 45 | AX6: 46 | AY6: 47 | AZ6: 48 | BA6: 49 | BB6: 50 | BC6: 51 | BD6: 52 | BE6: 53 | BF6: 54 | BG6: 55 | BH6: 56 | BI6: 57 | BJ6: 58 | BK6: 59 | BL6: 60 | BM6: 61 | BN6: 62 | BO6: 63 | BP6: 64 | BQ6: 65 | BR6: 66 | BS6: 67 | BT6: 68
B7: 0191 | C7: Agricultura, inclusive o apoio à agricultura e a pós-colheita | D7: 1 | E7: 0.024570859 | F7: 0.033961348 | G7: 0.0057704602 | H7: 0.00012676835 | I7: 2.7100113e-05 | J7: 8.0184254e-06 | K7: 7.6648443e-05 | L7: 0.028804084 | M7: 0.45667347 | N7: 0.24274831 | O7: 0.027428915 | P7: 0.24436894 | Q7: 0.084501803 | R7: 0.0040430194 | S7: 0.00013993391 | T7: 0.003332532 | U7: 0.0014744713 | V7: 8.5232735e-06 | W7: 2.1427904e-05 | X7: 0.40972387 | Y7: 0.00012386382 | Z7: 0.0003306672 | AA7: 3.9275191e-05 | AB7: 0.00011758757 | AC7: 0.0004332364 | AD7: 0.000217617 | AE7: 0.00015720516 | AF7: 0.00023638522 | AG7: 1.6608474e-05 | AH7: 2.2127395e-06 | AI7: 4.7778186e-06 | AJ7: 7.3657668e-06 | AK7: 3.6983938e-06 | AL7: 3.6959175e-06 | AM7: 1.4135374e-05 | AN7: 0.00015236232 | AO7: 7.2811989e-07 | AP7: 2.4933863e-06 | AQ7: 0.00034769288 | AR7: 0.00047372839 | AS7: 1.125361e-05 | AT7: 0.0086435384 | AU7: 1.7985945e-06 | AV7: 9.5783023e-07 | AW7: 9.5707771e-06 | AX7: 6.1697155e-05 | AY7: 0.010356 | AZ7: 0.017333785 | BA7: 4.7246386e-06 | BB7: 1.6384554e-05 | BC7: 0.00018679376 | BD7: 1.2780437e-05 | BE7: 2.4939531e-05 | BF7: 2.7034191e-05 | BG7: 2.3422065e-05 | BH7: 0.00018074124 | BI7: 7.4611092e-06 | BJ7: 9.5165112e-06 | BK7: 0.00041057178 | BL7: 4.2650032e-06 | BM7: 0.0019661034 | BN7: 0.0016703111 | BO7: 0.00049102803 | BP7: 0.0012986331 | BQ7: 0.00090915279 | BR7: 5.5263415e-05 | BS7: 0.0010318598 | BT7: 0
B8: 0192 | C8: Pecuária, inclusive o apoio à pecuária | D8: 2 | E8: 0.003114173 | F8: 0.035589676 | G8: 0.0053246203 | H8: 0.00032286712 | I8: 7.8530247e-05 | J8: 1.3345066e-05 | K8: 0.00016335753 | L8: 0.34113716 | M8: 0.00230067 | N8: 0.015170439 | O8: 0.00093532144 | P8: 0.012473371 | Q8: 0.0020039237 | R8: 0.0009888661 | S8: 0.00024804856 | T8: 0.0056569756 | U8: 0.0020362903 | V8: 1.8553172e-05 | W8: 1.2821154e-06 | X8: 0.0029487198 | Y8: 0.00047696705 | Z8: 0.00015997422 | AA8: 9.0255958e-05 | AB8: 3.6581516e-05 | AC8: 0.000704299 | AD8: 0.00096789339 | AE8: 0.00031606671 | AF8: 0.00055104074 | AG8: 1.6953675e-05 | AH8: 5.9138037e-06 | AI8: 1.6551172e-05 | AJ8: 1.3346755e-05 | AK8: 6.2195106e-06 | AL8: 1.0068467e-05 | AM8: 2.099116e-05 | AN8: 8.1342252e-05 | AO8: 2.2140551e-06 | AP8: 3.1735124e-06 | AQ8: 0.0001092539 | AR8: 0.0010612955 | AS8: 1.877436e-05 | AT8: 0.00037848225 | AU8: 2.6890284e-06 | AV8: 2.2153358e-06 | AW8: 1.1114613e-05 | AX8: 0.0001306732 | AY8: 0.0095765671 | AZ8: 0.0056850635 | BA8: 1.3354546e-05 | BB8: 2.9444853e-05 | BC8: 0.00039724352 | BD8: 2.9176743e-05 | BE8: 5.0128162e-05 | BF8: 6.0291711e-05 | BG8: 2.4159196e-05 | BH8: 0.00018441704 | BI8: 7.5676569e-05 | BJ8: 2.1799853e-05 | BK8: 0.00011030826 | BL8: 8.5457415e-06 | BM8: 0.00037855344 | BN8: 0.0005249346 | BO8: 0.00017381342 | BP8: 0.00044834728 | BQ8: 0.00061647406 | BR8: 5.4168099e-05 | BS8: 0.00032537629 | BT8: 0
B9: 0280 | C9: Produção florestal; pesca e aquicultura | D9: 3 | E9: 0.004195637 | F9: 0.010248428 | G9: 0.074501456 | H9: 0.00012604737 | I9: 5.5467945e-06 | J9: 1.046738e-06 | K9: 7.7244739e-06 | L9: 0.0067016745 | M9: 4.6207153e-05 | N9: 0.0018187635 | O9: 0.00018175801 | P9: 0.00153773 | Q9: 0.0014487918 | R9: 0.00036194869 | S9: 0.00049006769 | T9: 0.10676495 | U9: 0.035931412 | V9: 9.7733174e-07 | W9: 7.7720968e-08 | X9: 0.00010736505 | Y9: 0.0012091664 | Z9: 4.3905632e-05 | AA9: 1.9827993e-06 | AB9: 4.8845736e-06 | AC9: 0.013256822 | AD9: 0.00076866567 | AE9: 0.0046818878 | AF9: 2.9166342e-05 | AG9: 9.0612506e-05 | AH9: 6.0415366e-07 | AI9: 1.5028484e-06 | AJ9: 1.6236601e-06 | AK9: 6.8425456e-07 | AL9: 9.9835006e-07 | AM9: 1.9894784e-06 | AN9: 6.0947827e-05 | AO9: 2.7155892e-07 | AP9: 6.0535069e-07 | AQ9: 9.4518126e-06 | AR9: 0.00076532763 | AS9: 1.369754e-06 | AT9: 0.00034015211 | AU9: 2.7891931e-07 | AV9: 1.8979545e-07 | AW9: 1.0244241e-06 | AX9: 6.5388993e-06 | AY9: 0.0020135456 | AZ9: 0.0022335876 | BA9: 1.5343452e-06 | BB9: 3.0147131e-06 | BC9: 1.8426652e-05 | BD9: 2.1483703e-06 | BE9: 2.6817656e-06 | BF9: 3.2911382e-06 | BG9: 1.4570423e-06 | BH9: 5.3038369e-05 | BI9: 8.2023085e-07 | BJ9: 1.7105798e-06 | BK9: 6.1000341e-06 | BL9: 6.8081881e-07 | BM9: 0.00017429716 | BN9: 0.00031179856 | BO9: 8.9692859e-05 | BP9: 0.00023897843 | BQ9: 0.00012799706 | BR9: 3.2795236e-06 | BS9: 2.8706589e-05 | BT9: 0
B10: 0580 | C10: Extração de carvão mineral e de minerais não-metálicos | D10: 4 | E10: 0.00063717446 | F10: 0.0026468607 | G10: 0.00035521895 | H10: 0.01624849 | I10: 0.002425982 | J10: 2.3529884e-05 | K10: 0.0003208784 | L10: 0.00027175714 | M10: 0.00033907615 | N10: 0.0011673969 | O10: 0.00033592545 | P10: 8.5164353e-06 | Q10: 0.00014296382 | R10: 8.7443508e-06 | S10: 0.00013473525 | T10: 1.7001386e-05 | U10: 0.00066994581 | V10: 1.7184723e-05 | W10: 6.1096669e-05 | X10: 0.0050537592 | Y10: 0.02629436 | Z10: 0.0028191465 | AA10: 0.00071513844 | AB10: 8.7668761e-05 | AC10: 0.00025285512 | AD10: 0.052692419 | AE10: 0.011979938 | AF10: 0.0069070298 | AG10: 0.00011326106 | AH10: 7.9935545e-06 | AI10: 0.00064777981 | AJ10: 0.00014432652 | AK10: 0.00013819673 | AL10: 0.00038482373 | AM10: 0.00013902861 | AN10: 0.00051698408 | AO10: 0.00021507217 | AP10: 0.00071793268 | AQ10: 0.0054148921 | AR10: 0.01042156 | AS10: 2.6977155e-05 | AT10: 9.7182987e-05 | AU10: 2.5010332e-06 | AV10: 1.0998676e-05 | AW10: 1.8566776e-06 | AX10: 5.6801021e-05 | AY10: 0.00016818671 | AZ10: 0.00015051732 | BA10: 1.8499664e-05 | BB10: 1.3586751e-05 | BC10: 1.8553076e-05 | BD10: 7.1143664e-06 | BE10: 5.9371978e-06 | BF10: 0.000487276 | BG10: 1.3625721e-05 | BH10: 3.3620801e-05 | BI10: 7.4472142e-06 | BJ10: 1.3599208e-05 | BK10: 1.7160435e-05 | BL10: 4.0626279e-06 | BM10: 0.00010097688 | BN10: 0.00010282299 | BO10: 2.872614e-05 | BP10: 0.00012113067 | BQ10: 0.00015594535 | BR10: 4.6209218e-05 | BS10: 5.8270552e-05 | BT10: 0
B11: 0680 | C11: Extração de petróleo e gás, inclusive as atividades de apoio | D11: 5 | E11: 7.8080356e-05 | F11: 0.00010172796 | G11: 3.2984104e-05 | H11: 0.00015888387 | I11: 0.045998201 | J11: 0.0030560604 | K11: 0.0015217612 | L11: 0.00030798971 | M11: 3.6945387e-05 | N11: 0.0020199968 | O11: 0.0017621463 | P11: 1.0268737e-05 | Q11: 0.0029665118 | R11: 3.2367874e-05 | S11: 5.636512e-05 | T11: 0.0010740073 | U11: 0.0063340296 | V11: 0.00012522836 | W11: 0.29353087 | X11: 4.6139623e-05 | Y11: 0.0098058071 | Z11: 0.001570129 | AA11: 0.00074994189 | AB11: 0.0005736504 | AC11: 0.00098590347 | AD11: 0.00350488 | AE11: 0.0032139638 | AF11: 0.0049269183 | AG11: 0.0024844742 | AH11: 3.6999962e-05 | AI11: 0.00037014818 | AJ11: 0.00021314012 | AK11: 0.00044098907 | AL11: 0.0016284972 | AM11: 4.9862409e-05 | AN11: 4.846137e-05 | AO11: 0.00010647989 | AP11: 0.037257484 | AQ11: 0.0042443453 | AR11: 0.0010334885 | AS11: 7.1993975e-05 | AT11: 0.00016604129 | AU11: 0.00021147333 | AV11: 0.0001828282 | AW11: 4.3492883e-05 | AX11: 0.00027660698 | AY11: 0.00012481802 | AZ11: 0.00014611806 | BA11: 9.4427908e-05 | BB11: 4.1299854e-05 | BC11: 0.00032899687 | BD11: 6.7024373e-05 | BE11: 3.3164331e-05 | BF11: 1.1883307e-05 | BG11: 7.3521532e-05 | BH11: 0.00067186867 | BI11: 3.1453767e-05 | BJ11: 0.00016425112 | BK11: 5.0936337e-05 | BL11: 3.3007162e-05 | BM11: 0.00059158542 | BN11: 2.6902959e-05 | BO11: 0.00014197853 | BP11: 3.3699429e-05 | BQ11: 4.5520361e-05 | BR11: 0.00026124841 | BS11: 0.00011146528 | BT11: 0
B12: 0791 | C12: Extração de minério de ferro, inclusive beneficiamentos e a aglomeração | D12: 6 | E12: 4.3399601e-09 | F12: 4.3910579e-09 | G12: 3.0036806e-08 | H12: 1.5640192e-07 | I12: 3.0481921e-06 | J12: 0.013074684 | K12: 0.0023915501 | L12: 4.2532518e-07 | M12: 5.4524132e-07 | N12: 1.5848555e-06 | O12: 1.3947505e-06 | P12: 1.9243856e-06 | Q12: 1.7949531e-06 | R12: 1.2422481e-06 | S12: 7.076576e-07 | T12: 1.33666e-07 | U12: 9.4292859e-07 | V12: 3.2433855e-07 | W12: 5.5973233e-08 | X12: 5.4733768e-07 | Y12: 1.9381343e-06 | Z12: 6.8090178e-06 | AA12: 1.3709856e-05 | AB12: 2.0895025e-05 | AC12: 2.8046146e-06 | AD12: 0.0017112372 | AE12: 0.11996141 | AF12: 0.0015944308 | AG12: 1.3036586e-06 | AH12: 8.7061744e-06 | AI12: 3.178368e-06 | AJ12: 2.0565569e-06 | AK12: 1.0692129e-05 | AL12: 6.5730761e-06 | AM12: 2.7589193e-06 | AN12: 7.3594541e-07 | AO12: 1.0694405e-07 | AP12: 1.7159359e-06 | AQ12: 1.035634e-06 | AR12: 3.5926445e-07 | AS12: 3.1312539e-06 | AT12: 5.1939439e-06 | AU12: 4.7914276e-07 | AV12: 5.8276967e-07 | AW12: 5.0912759e-07 | AX12: 2.8221724e-06 | AY12: 5.7386887e-06 | AZ12: 2.7843239e-06 | BA12: 1.673613e-06 | BB12: 1.6776868e-06 | BC12: 3.4865173e-06 | BD12: 6.5830198e-06 | BE12: 1.6491006e-06 | BF12: 5.5214359e-07 | BG12: 3.2127889e-06 | BH12: 0.00015987912 | BI12: 1.2870078e-06 | BJ12: 7.7871243e-06 | BK12: 2.1213092e-06 | BL12: 9.2455724e-07 | BM12: 5.1768086e-07 | BN12: 3.2305911e-07 | BO12: 1.9113257e-05 | BP12: 3.4390457e-07 | BQ12: 1.421037e-06 | BR12: 1.198927e-05 | BS12: 2.3496215e-06 | BT12: 0
B13: 0792 | C13: Extração de minerais metálicos não-ferrosos, inclusive beneficiamentos | D13: 7 | E13: 7.5636154e-06 | F13: 1.5004717e-05 | G13: 1.9268365e-06 | H13: 4.8876057e-05 | I13: 0.00025623915 | J13: 8.0458171e-05 | K13: 0.054328576 | L13: 8.6407987e-06 | M13: 3.1098211e-06 | N13: 1.511641e-05 | O13: 1.1160572e-05 | P13: 1.4233042e-06 | Q13: 2.0594853e-06 | R13: 1.2920166e-06 | S13: 2.7493063e-06 | T13: 8.0171624e-07 | U13: 1.9171792e-05 | V13: 5.6593207e-05 | W13: 1.4438121e-07 | X13: 1.592697e-05 | Y13: 8.4367746e-05 | Z13: 2.6658646e-05 | AA13: 7.1743249e-06 | AB13: 3.3944812e-06 | AC13: 7.4870775e-06 | AD13: 0.0005089064 | AE13: 0.011918471 | AF13: 0.14421092 | AG13: 7.8286233e-05 | AH13: 1.0238401e-05 | AI13: 0.00038051556 | AJ13: 4.3835441e-05 | AK13: 2.069129e-05 | AL13: 0.0002293365 | AM13: 8.7267841e-05 | AN13: 0.00013044578 | AO13: 2.5853013e-05 | AP13: 7.6510253e-07 | AQ13: 2.7417172e-05 | AR13: 7.2604549e-05 | AS13: 1.6926045e-06 | AT13: 2.6103006e-06 | AU13: 3.8691377e-07 | AV13: 2.0813203e-07 | AW13: 1.8183128e-07 | AX13: 1.1357478e-06 | AY13: 5.920129e-06 | AZ13: 2.3058347e-06 | BA13: 2.9361109e-06 | BB13: 2.0406243e-06 | BC13: 2.8148576e-06 | BD13: 8.2642043e-07 | BE13: 5.812282e-07 | BF13: 2.8912075e-06 | BG13: 1.3599749e-06 | BH13: 1.4562655e-05 | BI13: 6.3333648e-07 | BJ13: 1.2621794e-06 | BK13: 1.0772464e-06 | BL13: 4.5163131e-07 | BM13: 7.6746243e-07 | BN13: 6.7387252e-07 | BO13: 2.0576286e-06 | BP13: 7.6961694e-07 | BQ13: 1.2216329e-06 | BR13: 4.3381641e-06 | BS13: 1.2279994e-06 | BT13: 0
B14: 1091 | C14: Abate e produtos de carne, inclusive os produtos do laticínio e da pesca | D14: 8 | E14: 0.00064085254 | F14: 0.019922325 | G14: 0.00288528 | H14: 0.00017364065 | I14: 1.2817617e-05 | J14: 2.1664606e-05 | K14: 5.4832626e-05 | L14: 0.075034463 | M14: 7.945599e-05 | N14: 0.007107459 | O14: 0.0007269989 | P14: 0.00014855265 | Q14: 0.00018279953 | R14: 0.00014112597 | S14: 0.055565291 | T14: 0.0001013154 | U14: 0.00026521962 | V14: 6.8155524e-05 | W14: 1.512647e-05 | X14: 0.012511319 | Y14: 0.00016911761 | Z14: 0.00051328563 | AA14: 0.023596048 | AB14: 0.00029666865 | AC14: 0.00021017624 | AD14: 0.00014049548 | AE14: 0.0001542478 | AF14: 0.00010699153 | AG14: 0.00041595746 | AH14: 0.00010297772 | AI14: 0.00015267575 | AJ14: 0.00022748713 | AK14: 1.8923649e-05 | AL14: 1.5632391e-05 | AM14: 5.1798832e-05 | AN14: 0.00012621112 | AO14: 3.6510632e-05 | AP14: 3.7404756e-06 | AQ14: 1.3703345e-05 | AR14: 1.488292e-05 | AS14: 1.0097741e-05 | AT14: 0.00036219396 | AU14: 2.1261881e-06 | AV14: 8.7007912e-06 | AW14: 2.983131e-06 | AX14: 1.0602658e-05 | AY14: 0.0145751 | AZ14: 0.050162992 | BA14: 0.00026088604 | BB14: 0.00016440416 | BC14: 0.00024041653 | BD14: 3.4615772e-05 | BE14: 6.4208347e-06 | BF14: 1.8175755e-06 | BG14: 3.4595053e-05 | BH14: 4.7698173e-05 | BI14: 4.4785064e-05 | BJ14: 1.9756006e-05 | BK14: 2.8297492e-05 | BL14: 1.8925345e-05 | BM14: 0.0028133796 | BN14: 0.006000425 | BO14: 0.0017812866 | BP14: 0.0046444709 | BQ14: 0.0029444155 | BR14: 0.00026957543 | BS14: 0.0018967261 | BT14: 0
B15: 1092 | C15: Fabricação e refino de açúcar | D15: 9 | E15: 0.00035115753 | F15: 0.0011755803 | G15: 0.00015859377 | H15: 0.0002257851 | I15: 0.00083764583 | J15: 0.0002025763 | K15: 0.00028406071 | L15: 0.0020569777 | M15: 0.036795601 | N15: 0.020767412 | O15: 0.015945069 | P15: 2.6749598e-05 | Q15: 0.00016557398 | R15: 2.3837366e-05 | S15: 4.5898484e-05 | T15: 0.00012760172 | U15: 0.00015396278 | V15: 3.4906399e-05 | W15: 0.017347368 | X15: 0.022655688 | Y15: 0.00083227328 | Z15: 0.010677875 | AA15: 0.0089590812 | AB15: 0.0035457581 | AC15: 0.00010767902 | AD15: 0.00019628215 | AE15: 0.00016933183 | AF15: 0.00022301625 | AG15: 0.00014928257 | AH15: 1.8753922e-05 | AI15: 9.8730365e-05 | AJ15: 0.00070852475 | AK15: 8.1627757e-05 | AL15: 6.9156401e-05 | AM15: 9.4218188e-05 | AN15: 4.0242862e-05 | AO15: 0.00068397226 | AP15: 0.001233695 | AQ15: 0.00031582739 | AR15: 0.00021837789 | AS15: 0.0002807854 | AT15: 0.0001789731 | AU15: 0.00057431705 | AV15: 7.5700386e-05 | AW15: 7.9444278e-06 | AX15: 0.00020508812 | AY15: 0.00039784303 | AZ15: 0.0044790765 | BA15: 5.4525528e-05 | BB15: 7.061334e-05 | BC15: 7.2037319e-05 | BD15: 2.6187904e-05 | BE15: 3.0227451e-05 | BF15: 6.3051052e-06 | BG15: 3.846696e-05 | BH15: 0.00031916444 | BI15: 6.9378043e-05 | BJ15: 2.9918566e-05 | BK15: 0.0001664281 | BL15: 0.00059778212 | BM15: 0.00065664045 | BN15: 0.00055686074 | BO15: 0.00023619123 | BP15: 0.0004420344 | BQ15: 0.00029350277 | BR15: 0.00014703927 | BS15: 0.00035149627 | BT15: 0
B16: 1093 | C16: Outros produtos alimentares | D16: 10 | E16: 0.006951138 | F16: 0.060740772 | G16: 0.01486792 | H16: 0.0060449753 | I16: 0.00029732881 | J16: 0.00039519999 | K16: 0.0010025316 | L16: 0.061412676 | M16: 0.0012020746 | N16: 0.095623039 | O16: 0.027948575 | P16: 0.0021129427 | Q16: 0.0025447876 | R16: 0.0015987269 | S16: 0.0040904924 | T16: 0.0016469302 | U16: 0.0095716085 | V16: 0.0010931555 | W16: 0.0012924721 | X16: 0.049539836 | Y16: 0.0034885367 | Z16: 0.012920451 | AA16: 0.018616036 | AB16: 0.0044290723 | AC16: 0.0029188384 | AD16: 0.0019875204 | AE16: 0.0022557315 | AF16: 0.0015201879 | AG16: 0.0021320965 | AH16: 0.0013708244 | AI16: 0.0020946544 | AJ16: 0.0029969694 | AK16: 0.00022330888 | AL16: 0.00018562343 | AM16: 0.00076298102 | AN16: 0.0015625765 | AO16: 0.00044734893 | AP16: 5.2622027e-05 | AQ16: 0.00029132175 | AR16: 0.00021976194 | AS16: 0.00055856554 | AT16: 0.003674659 | AU16: 8.7128287e-05 | AV16: 3.1908128e-05 | AW16: 0.00083214095 | AX16: 0.00019880777 | AY16: 0.0087981301 | AZ16: 0.04014763 | BA16: 0.003591364 | BB16: 0.0022335441 | BC16: 0.0033435671 | BD16: 0.00046622369 | BE16: 0.00034397028 | BF16: 4.4356141e-05 | BG16: 0.00055229171 | BH16: 0.00038518179 | BI16: 0.00047893792 | BJ16: 0.00013304274 | BK16: 0.00039041727 | BL16: 0.0002614291 | BM16: 0.0018342845 | BN16: 0.0051152979 | BO16: 0.0017086121 | BP16: 0.0074072516 | BQ16: 0.0028935565 | BR16: 0.0010230059 | BS16: 0.0036792892 | BT16: 0
B17: 1100 | C17: Fabricação de bebidas | D17: 11 | E17: 5.1811614e-06 | F17: 1.3558433e-05 | G17: 5.1161819e-06 | H17: 4.0502561e-05 | I17: 5.3666363e-05 | J17: 8.6443968e-05 | K17: 0.00013425682 | L17: 0.0018050063 | M17: 8.9965134e-05 | N17: 0.00033495493 | O17: 0.090795871 | P17: 0.00016385057 | Q17: 0.00017344423 | R17: 0.00012944512 | S17: 0.00026355265 | T17: 0.00012292204 | U17: 0.00025765588 | V17: 6.2271635e-05 | W17: 0.00013445828 | X17: 0.00014363484 | Y17: 9.8355366e-05 | Z17: 0.000264264 | AA17: 0.00016017415 | AB17: 0.00028107416 | AC17: 0.00022286092 | AD17: 0.00015109489 | AE17: 0.00019867468 | AF17: 0.00011927329 | AG17: 0.00029675328 | AH17: 0.00013844717 | AI17: 0.00024053672 | AJ17: 0.00057452628 | AK17: 8.2213043e-05 | AL17: 7.5843034e-05 | AM17: 0.0001771728 | AN17: 0.00014437564 | AO17: 0.00037080424 | AP17: 2.2854468e-05 | AQ17: 3.9974737e-05 | AR17: 0.00010840101 | AS17: 4.0549531e-05 | AT17: 0.00012385217 | AU17: 2.6984695e-05 | AV17: 2.7314841e-05 | AW17: 0.00024724881 | AX17: 2.7099071e-05 | AY17: 0.018339997 | AZ17: 0.11830187 | BA17: 0.00028938136 | BB17: 0.00018382709 | BC17: 0.00026832006 | BD17: 4.5009978e-05 | BE17: 0.00024454129 | BF17: 6.1536247e-06 | BG17: 6.0233678e-05 | BH17: 4.5473198e-05 | BI17: 3.0351236e-05 | BJ17: 2.7869545e-05 | BK17: 5.6715897e-05 | BL17: 3.0659165e-05 | BM17: 0.00013284953 | BN17: 0.00029497533 | BO17: 0.00013072012 | BP17: 0.00022736327 | BQ17: 0.00082341544 | BR17: 0.00078301188 | BS17: 0.00012845595 | BT17: 0
B18: 1200 | C18: Fabricação de produtos do fumo | D18: 12 | E18: 5.7795049e-07 | F18: 4.4150496e-07 | G18: 2.0204039e-07 | H18: 4.3447057e-06 | I18: 8.6147926e-07 | J18: 3.5080541e-06 | K18: 8.3002099e-06 | L18: 6.8360982e-05 | M18: 1.8088597e-05 | N18: 4.8716301e-05 | O18: 7.5981883e-06 | P18: 0.068344149 | Q18: 4.2346949e-05 | R18: 3.0957526e-05 | S18: 6.4247415e-05 | T18: 2.6942947e-05 | U18: 9.1698768e-05 | V18: 3.0301037e-05 | W18: 3.5325341e-06 | X18: 2.7909048e-05 | Y18: 1.8462501e-05 | Z18: 4.9928094e-05 | AA18: 2.1440173e-05 | AB18: 6.4408436e-05 | AC18: 4.5253305e-05 | AD18: 3.800416e-05 | AE18: 3.6249991e-05 | AF18: 2.6206361e-05 | AG18: 3.5633908e-05 | AH18: 3.0723477e-05 | AI18: 3.6922864e-05 | AJ18: 4.9147114e-05 | AK18: 4.6195433e-06 | AL18: 4.5975403e-06 | AM18: 1.0992488e-05 | AN18: 2.5527975e-05 | AO18: 4.2058196e-07 | AP18: 3.7153175e-07 | AQ18: 1.0122331e-06 | AR18: 2.5782336e-07 | AS18: 1.685167e-06 | AT18: 1.7792284e-05 | AU18: 2.235983e-07 | AV18: 1.4730751e-06 | AW18: 2.5675539e-07 | AX18: 1.0331896e-06 | AY18: 3.1387391e-06 | AZ18: 1.9558698e-06 | BA18: 8.3858151e-05 | BB18: 4.0308616e-05 | BC18: 5.8851096e-05 | BD18: 9.2437924e-06 | BE18: 1.4656885e-06 | BF18: 2.1297059e-07 | BG18: 8.7286012e-06 | BH18: 2.132909e-05 | BI18: 6.5248482e-06 | BJ18: 4.5472909e-06 | BK18: 8.5377202e-06 | BL18: 3.8232022e-06 | BM18: 4.9697752e-07 | BN18: 1.0759753e-06 | BO18: 5.1169033e-06 | BP18: 3.1602837e-07 | BQ18: 1.6627594e-06 | BR18: 2.2927603e-06 | BS18: 1.667178e-06 | BT18: 0
... B74: 9700 | C74: Serviços domésticos | D74: 68 | E74: 0 | F74: 0 | G74: 0 | H74: 0 | I74: 0 | J74: 0 | K74: 0 | L74: 0 | M74: 0 | N74: 0 | O74: 0 | P74: 0 | Q74: 0 | R74: 0 | S74: 0 | T74: 0 | U74: 0 | V74: 0 | W74: 0 | X74: 0 | Y74: 0 | Z74: 0 | AA74: 0 | AB74: 0 | AC74: 0 | AD74: 0 | AE74: 0 | AF74: 0 | AG74: 0 | AH74: 0 | AI74: 0 | AJ74: 0 | AK74: 0 | AL74: 0 | AM74: 0 | AN74: 0 | AO74: 0 | AP74: 0 | AQ74: 0 | AR74: 0 | AS74: 0 | AT74: 0 | AU74: 0 | AV74: 0 | AW74: 0 | AX74: 0 | AY74: 0 | AZ74: 0 | BA74: 0 | BB74: 0 | BC74: 0 | BD74: 0 | BE74: 0 | BF74: 0 | BG74: 0 | BH74: 0 | BI74: 0 | BJ74: 0 | BK74: 0 | BL74: 0 | BM74: 0 | BN74: 0 | BO74: 0 | BP74: 0 | BQ74: 0 | BR74: 0 | BS74: 0 | BT74: 0

Sheet B_2010
B2: Matriz B — inversa de Leontief (2010)
B3: B = (I−A)⁻¹, colada como VALOR; usada em Q4 e Q7.
B6: Código | C6: Atividades | E6: 1 | F6: 2 | G6: 3 | H6: 4 | I6: 5 | J6: 6 | K6: 7 | L6: 8 | M6: 9 | N6: 10 | O6: 11 | P6: 12 | Q6: 13 | R6: 14 | S6: 15 | T6: 16 | U6: 17 | V6: 18 | W6: 19 | X6: 20 | Y6: 21 | Z6: 22 | AA6: 23 | AB6: 24 | AC6: 25 | AD6: 26 | AE6: 27 | AF6: 28 | AG6: 29 | AH6: 30 | AI6: 31 | AJ6: 32 | AK6: 33 | AL6: 34 | AM6: 35 | AN6: 36 | AO6: 37 | AP6: 38 | AQ6: 39 | AR6: 40 | AS6: 41 | AT6: 42 | AU6: 43 | AV6: 44 | AW6: 45 | AX6: 46 | AY6: 47 | AZ6: 48 | BA6: 49 | BB6: 50 | BC6: 51 | BD6: 52 | BE6: 53 | BF6: 54 | BG6: 55 | BH6: 56 | BI6: 57 | BJ6: 58 | BK6: 59 | BL6: 60 | BM6: 61 | BN6: 62 | BO6: 63 | BP6: 64 | BQ6: 65 | BR6: 66 | BS6: 67 | BT6: 68
B7: 0191 | C7: Agricultura, inclusive o apoio à agricultura e a pós-colheita | D7: 1 | E7: 1.0315712 | F7: 0.059981228 | G7: 0.013164719 | H7: 0.0082220785 | I7: 0.0030632176 | J7: 0.0026133374 | K7: 0.0059433118 | L7: 0.082937994 | M7: 0.49584901 | N7: 0.29845766 | O7: 0.053493745 | P7: 0.27674795 | Q7: 0.11380761 | R7: 0.032079707 | S7: 0.021508932 | T7: 0.010515716 | U7: 0.015043665 | V7: 0.0049176911 | W7: 0.029622156 | X7: 0.45679394 | Y7: 0.009178796 | Z7: 0.020398909 | AA7: 0.022969594 | AB7: 0.013037065 | AC7: 0.010142746 | AD7: 0.0079309865 | AE7: 0.0076861422 | AF7: 0.0070577656 | AG7: 0.0069178795 | AH7: 0.0046171111 | AI7: 0.0072730266 | AJ7: 0.008612807 | AK7: 0.0037947054 | AL7: 0.0051708391 | AM7: 0.0039609218 | AN7: 0.0074434414 | AO7: 0.0034969875 | AP7: 0.0029192821 | AQ7: 0.0027511412 | AR7: 0.0040280296 | AS7: 0.0022397893 | AT7: 0.013291098 | AU7: 0.0081522818 | AV7: 0.0046127384 | AW7: 0.0062341881 | AX7: 0.0023014495 | AY7: 0.01901832 | AZ7: 0.044137208 | BA7: 0.0090439799 | BB7: 0.0064847315 | BC7: 0.0085842721 | BD7: 0.001808246 | BE7: 0.0014528544 | BF7: 0.00028782657 | BG7: 0.0020650169 | BH7: 0.0021979937 | BI7: 0.0042455877 | BJ7: 0.0018062701 | BK7: 0.0025916713 | BL7: 0.0019989645 | BM7: 0.0048797022 | BN7: 0.0053002401 | BO7: 0.0028037125 | BP7: 0.0066456735 | BQ7: 0.0048042892 | BR7: 0.0019968831 | BS7: 0.0080503997 | BT7: 0
B8: 0192 | C8: Pecuária, inclusive o apoio à pecuária | D8: 2 | E8: 0.0041396389 | F8: 1.0467924 | G8: 0.0077168308 | H8: 0.0010345601 | I8: 0.00040580068 | J8: 0.00028238723 | K8: 0.00069745995 | L8: 0.38846301 | M8: 0.0048772669 | N8: 0.022577842 | O8: 0.0027652801 | P8: 0.01584526 | Q8: 0.0038385978 | R8: 0.0023433066 | S8: 0.025767067 | T8: 0.0082325543 | U8: 0.0042036578 | V8: 0.00078394751 | W8: 0.0008003662 | X8: 0.011279557 | Y8: 0.0013397708 | Z8: 0.0017649836 | AA8: 0.010740048 | AB8: 0.0011874868 | AC8: 0.0019719007 | AD8: 0.0019329787 | AE8: 0.0011848065 | AF8: 0.0013823017 | AG8: 0.0010238509 | AH8: 0.00061875553 | AI8: 0.00093862311 | AJ8: 0.0010287289 | AK8: 0.00057291156 | AL8: 0.0006258263 | AM8: 0.00057167603 | AN8: 0.0014952429 | AO8: 0.00044453844 | AP8: 0.0002705356 | AQ8: 0.00049800766 | AR8: 0.0018078856 | AS8: 0.00033310346 | AT8: 0.0010484719 | AU8: 0.00037326488 | AV8: 0.00035419773 | AW8: 0.0010340327 | AX8: 0.00044700016 | AY8: 0.016457327 | AZ8: 0.026898981 | BA8: 0.0011870094 | BB8: 0.0010864028 | BC8: 0.0015263989 | BD8: 0.00034980434 | BE8: 0.00042100176 | BF8: 0.0001234496 | BG8: 0.0004804157 | BH8: 0.00052882323 | BI8: 0.0008168818 | BJ8: 0.00033017759 | BK8: 0.00059162839 | BL8: 0.00022477203 | BM8: 0.0020717659 | BN8: 0.003322682 | BO8: 0.0012503553 | BP8: 0.0033553297 | BQ8: 0.0027559228 | BR8: 0.00050447411 | BS8: 0.0036635871 | BT8: 0
B9: 0280 | C9: Produção florestal; pesca e aquicultura | D9: 3 | E9: 0.005577223 | F9: 0.013058999 | G9: 1.0810001 | H9: 0.0010470512 | I9: 0.00056461758 | J9: 0.00056346409 | K9: 0.00093941407 | L9: 0.014951818 | M9: 0.0032299707 | N9: 0.0062448486 | O9: 0.0023320543 | P9: 0.0065559085 | Q9: 0.0044576739 | R9: 0.0025085762 | S9: 0.0040783019 | T9: 0.13343129 | U9: 0.049316572 | V9: 0.0045181013 | W9: 0.00060235689 | X9: 0.0035703665 | Y9: 0.0025491004 | Z9: 0.0019728123 | AA9: 0.0038323918 | AB9: 0.0018856077 | AC9: 0.018548339 | AD9: 0.0032648444 | AE9: 0.0069437291 | AF9: 0.0011936191 | AG9: 0.0032195582 | AH9: 0.0018503898 | AI9: 0.0021689931 | AJ9: 0.0025711325 | AK9: 0.0023353413 | AL9: 0.0025946626 | AM9: 0.0021131379 | AN9: 0.014230164 | AO9: 0.0012196224 | AP9: 0.00066102235 | AQ9: 0.00086522209 | AR9: 0.003653765 | AS9: 0.00086998268 | AT9: 0.0016076775 | AU9: 0.00076529831 | AV9: 0.00071781234 | AW9: 0.00090772933 | AX9: 0.00063832159 | AY9: 0.0034875935 | AZ9: 0.0043033538 | BA9: 0.0042423058 | BB9: 0.0018593558 | BC9: 0.0012655381 | BD9: 0.00052590231 | BE9: 0.0004835999 | BF9: 0.00022523589 | BG9: 0.00080329941 | BH9: 0.00075161762 | BI9: 0.001513784 | BJ9: 0.0010726515 | BK9: 0.0010032416 | BL9: 0.00026584901 | BM9: 0.00066092273 | BN9: 0.00091624205 | BO9: 0.00076688563 | BP9: 0.001056673 | BQ9: 0.0013690838 | BR9: 0.00058091609 | BS9: 0.0012329145 | BT9: 0
B10: 0580 | C10: Extração de carvão mineral e de minerais não-metálicos | D10: 4 | E10: 0.0054570016 | F10: 0.0055251997 | G10: 0.0012604943 | H10: 1.0187929 | I10: 0.0040525866 | J10: 0.00094838283 | K10: 0.0022235046 | L10: 0.003667951 | M10: 0.0036895503 | N10: 0.0044175332 | O10: 0.0029789466 | P10: 0.0021354177 | Q10: 0.0048145735 | R10: 0.0015578196 | S10: 0.0028240403 | T10: 0.0016058318 | U10: 0.0040603832 | V10: 0.001882848 | W10: 0.0023595361 | X10: 0.0085608744 | Y10: 0.034707599 | Z10: 0.01047025 | AA10: 0.005893771 | AB10: 0.0018558815 | AC10: 0.006947051 | AD10: 0.061706853 | AE10: 0.016078035 | AF10: 0.011043826 | AG10: 0.004977394 | AH10: 0.00095739895 | AI10: 0.0050759302 | AJ10: 0.0031378039 | AK10: 0.0032379809 | AL10: 0.004301 | AM10: 0.0025445993 | AN10: 0.0032135333 | AO10: 0.0022385497 | AP10: 0.0020559488 | AQ10: 0.0088665177 | AR10: 0.018850855 | AS10: 0.0010496352 | AT10: 0.00077554553 | AU10: 0.0010739179 | AV10: 0.00074254896 | AW10: 0.00074106841 | AX10: 0.00074466677 | AY10: 0.0016445512 | AZ10: 0.0014324003 | BA10: 0.001207652 | BB10: 0.00082347488 | BC10: 0.0012877186 | BD10: 0.00044908154 | BE10: 0.00030707883 | BF10: 0.00087804161 | BG10: 0.00039735025 | BH10: 0.00058937548 | BI10: 0.00061890331 | BJ10: 0.00066817806 | BK10: 0.00086705033 | BL10: 0.00021273502 | BM10: 0.00084150756 | BN10: 0.00053848888 | BO10: 0.00051263772 | BP10: 0.0010860268 | BQ10: 0.00088389721 | BR10: 0.00062308645 | BS10: 0.00092615063 | BT10: 0
B11: 0680 | C11: Extração de petróleo e gás, inclusive as atividades de apoio | D11: 5 | E11: 0.028285835 | F11: 0.023664792 | G11: 0.014247342 | H11: 0.03427045 | I11: 1.0605513 | J11: 0.022642263 | K11: 0.048726996 | L11: 0.03119329 | M11: 0.032252204 | N11: 0.033508233 | O11: 0.020611912 | P11: 0.017406335 | Q11: 0.028258647 | R11: 0.012618965 | S11: 0.021254322 | T11: 0.01813433 | U11: 0.038763713 | V11: 0.012484261 | W11: 0.4239678 | X11: 0.029991784 | Y11: 0.066713006 | Z11: 0.035704342 | AA11: 0.025761442 | AB11: 0.01871439 | AC11: 0.032110877 | AD11: 0.039365099 | AE11: 0.035759728 | AF11: 0.043165892 | AG11: 0.022610167 | AH11: 0.010481164 | AI11: 0.023604287 | AJ11: 0.018119694 | AK11: 0.016320486 | AL11: 0.018976784 | AM11: 0.012842612 | AN11: 0.014927584 | AO11: 0.010445699 | AP11: 0.067151322 | AQ11: 0.020265899 | AR11: 0.01741404 | AS11: 0.008372822 | AT11: 0.016079827 | AU11: 0.094829628 | AV11: 0.05027815 | AW11: 0.056511199 | AX11: 0.015475154 | AY11: 0.0095643381 | AZ11: 0.011182434 | BA11: 0.016154875 | BB11: 0.010581664 | BC11: 0.012040077 | BD11: 0.004261566 | BE11: 0.0036900918 | BF11: 0.00082161432 | BG11: 0.005332465 | BH11: 0.0080978418 | BI11: 0.007785713 | BJ11: 0.011368919 | BK11: 0.0066043538 | BL11: 0.0062936878 | BM11: 0.0052318293 | BN11: 0.0036593035 | BO11: 0.0067660281 | BP11: 0.0050101938 | BQ11: 0.0048988135 | BR11: 0.006449619 | BS11: 0.011793107 | BT11: 0
B12: 0791 | C12: Extração de minério de ferro, inclusive beneficiamentos e a aglomeração | D12: 6 | E12: 0.0005136168 | F12: 0.00089052531 | G12: 0.0003038187 | H12: 0.0018738314 | I12: 0.0030764641 | J12: 1.0145821 | K12: 0.0058498899 | L12: 0.001473699 | M12: 0.00069529721 | N12: 0.0011575932 | O12: 0.0022545839 | P12: 0.00057597267 | Q12: 0.00076414604 | R12: 0.00057902738 | S12: 0.00084160546 | T12: 0.001012708 | U12: 0.0014558373 | V12: 0.0010623004 | W12: 0.0014342933 | X12: 0.00076639374 | Y12: 0.00095667631 | Z12: 0.0015033689 | AA12: 0.0015069936 | AB12: 0.00080504514 | AC12: 0.0023392011 | AD12: 0.0041927457 | AE12: 0.14181794 | AF12: 0.0085277471 | AG12: 0.032385566 | AH12: 0.0013133617 | AI12: 0.010211218 | AJ12: 0.015405463 | AK12: 0.011439697 | AL12: 0.017594127 | AM12: 0.0074160422 | AN12: 0.0044878527 | AO12: 0.0065912989 | AP12: 0.0011662448 | AQ12: 0.0017385069 | AR12: 0.0070651474 | AS12: 0.0020823007 | AT12: 0.00068984791 | AU12: 0.001402319 | AV12: 0.00099126672 | AW12: 0.00055923349 | AX12: 0.00062252811 | AY12: 0.00070089595 | AZ12: 0.00084410574 | BA12: 0.00088544827 | BB12: 0.00060215757 | BC12: 0.00085687723 | BD12: 0.00034137344 | BE12: 0.00019652377 | BF12: 0.00011290969 | BG12: 0.00030500405 | BH12: 0.00064458195 | BI12: 0.0004404119 | BJ12: 0.0013775601 | BK12: 0.00050629806 | BL12: 0.0002602523 | BM12: 0.00041885346 | BN12: 0.00024925802 | BO12: 0.00034512664 | BP12: 0.00050200036 | BQ12: 0.00042147883 | BR12: 0.0005090078 | BS12: 0.00048410936 | BT12: 0
B13: 0792 | C13: Extração de minerais metálicos não-ferrosos, inclusive beneficiamentos | D13: 7 | E13: 0.00048992048 | F13: 0.00045360149 | G13: 0.00019445943 | H13: 0.0010222981 | I13: 0.0011475315 | J13: 0.00077627562 | K13: 1.0599397 | L13: 0.00097687527 | M13: 0.00055466822 | N13: 0.0010199371 | O13: 0.00087984121 | P13: 0.00044509732 | Q13: 0.00067260531 | R13: 0.00048785751 | S13: 0.00065058855 | T13: 0.00058174905 | U13: 0.0016468255 | V13: 0.0030456669 | W13: 0.0005837282 | X13: 0.00062438944 | Y13: 0.0016942812 | Z13: 0.0018293003 | AA13: 0.0010002425 | AB13: 0.00059399392 | AC13: 0.0011344033 | AD13: 0.0017678393 | AE13: 0.017951517 | AF13: 0.1763226 | AG13: 0.0075067864 | AH13: 0.001360338 | AI13: 0.020099655 | AJ13: 0.0062184726 | AK13: 0.0050154525 | AL13: 0.013707205 | AM13: 0.0057562008 | AN13: 0.0057860614 | AO13: 0.0068512173 | AP13: 0.00085049949 | AQ13: 0.0013029021 | AR13: 0.0028822807 | AS13: 0.0021283467 | AT13: 0.00044202861 | AU13: 0.0010088481 | AV13: 0.00077309858 | AW13: 0.00035667281 | AX13: 0.00048727101 | AY13: 0.00043950031 | AZ13: 0.00041604306 | BA13: 0.00090850478 | BB13: 0.00048452168 | BC13: 0.00061765512 | BD13: 0.00026576935 | BE13: 0.00017051142 | BF13: 9.5907983e-05 | BG13: 0.00030580366 | BH13: 0.000352133 | BI13: 0.00045726159 | BJ13: 0.00065772333 | BK13: 0.00038844226 | BL13: 0.00017597095 | BM13: 0.00023945987 | BN13: 0.00018040459 | BO13: 0.00028166958 | BP13: 0.00037621351 | BQ13: 0.00050170387 | BR13: 0.00053149362 | BS13: 0.00043678983 | BT13: 0
B14: 1091 | C14: Abate e produtos de carne, inclusive os produtos do laticínio e da pesca | D14: 8 | E14: 0.0011688577 | F14: 0.023431067 | G14: 0.003793338 | H14: 0.00076004776 | I14: 0.00034721617 | J14: 0.0002733661 | K14: 0.00054219851 | L14: 1.0911304 | M14: 0.0010816537 | N14: 0.0099969336 | O14: 0.0017039225 | P14: 0.0013127152 | Q14: 0.0010450683 | R14: 0.00074743371 | S14: 0.069203988 | T14: 0.0011383462 | U14: 0.0015383328 | V14: 0.00059516538 | W14: 0.00080979853 | X14: 0.015142109 | Y14: 0.00083755159 | Z14: 0.0017663813 | AA14: 0.027208059 | AB14: 0.0013670315 | AC14: 0.0010741704 | AD14: 0.00080720222 | AE14: 0.00085052481 | AF14: 0.00073927574 | AG14: 0.0011958243 | AH14: 0.00063717746 | AI14: 0.00087039759 | AJ14: 0.0010671269 | AK14: 0.00052030728 | AL14: 0.00045047701 | AM14: 0.00048055893 | AN14: 0.00069949603 | AO14: 0.00045173538 | AP14: 0.00029804609 | AQ14: 0.00026408644 | AR14: 0.00040593008 | AS14: 0.00032156276 | AT14: 0.00085252397 | AU14: 0.00037243196 | AV14: 0.00037083369 | AW14: 0.0017142854 | AX14: 0.00034015057 | AY14: 0.016892975 | AZ14: 0.055614538 | BA14: 0.0011409438 | BB14: 0.0014005433 | BC14: 0.0012353304 | BD14: 0.00035873698 | BE14: 0.00051886685 | BF14: 5.2467527e-05 | BG14: 0.00066064164 | BH14: 0.00040237301 | BI14: 0.00094398075 | BJ14: 0.00033246465 | BK14: 0.00068414458 | BL14: 0.00030212413 | BM14: 0.0039711876 | BN14: 0.0071085333 | BO14: 0.002391827 | BP14: 0.0067685512 | BQ14: 0.0047815278 | BR14: 0.00071740155 | BS14: 0.0063407633 | BT14: 0
B15: 1092 | C15: Fabricação e refino de açúcar | D15: 9 | E15: 0.003020807 | F15: 0.0046915924 | G15: 0.0015684899 | H15: 0.0039024386 | I15: 0.0019343014 | J15: 0.0016385988 | K15: 0.0036512311 | L15: 0.0075442445 | M15: 1.0411903 | N15: 0.026831908 | O15: 0.020519908 | P15: 0.0017966481 | Q15: 0.0024231585 | R15: 0.0011800585 | S15: 0.0023531579 | T15: 0.0018159878 | U15: 0.0032090958 | V15: 0.0018298419 | W15: 0.02632262 | X15: 0.027645842 | Y15: 0.0050369048 | Z15: 0.015268222 | AA15: 0.012789473 | AB15: 0.0058482397 | AC15: 0.0030556946 | AD15: 0.0030464395 | AE15: 0.0026835449 | AF15: 0.0029726337 | AG15: 0.0019075093 | AH15: 0.0010527749 | AI15: 0.0020399588 | AJ15: 0.0024823897 | AK15: 0.0013989626 | AL15: 0.0014371917 | AM15: 0.0012411286 | AN15: 0.0014274245 | AO15: 0.0018284314 | AP15: 0.0028374603 | AQ15: 0.001487241 | AR15: 0.0016446022 | AS15: 0.0010606221 | AT15: 0.001494938 | AU15: 0.0067149875 | AV15: 0.0034201812 | AW15: 0.0038905102 | AX15: 0.0013706652 | AY15: 0.001818905 | AZ15: 0.0089946239 | BA15: 0.0017577765 | BB15: 0.0012170553 | BC15: 0.0013113186 | BD15: 0.00043417948 | BE15: 0.00041847442 | BF15: 0.00010123401 | BG15: 0.00055555967 | BH15: 0.00096460358 | BI15: 0.00094199562 | BJ15: 0.00089944735 | BK15: 0.00083617035 | BL15: 0.0011069346 | BM15: 0.0012392255 | BN15: 0.0011196884 | BO15: 0.00084387922 | BP15: 0.001437568 | BQ15: 0.0011517401 | BR15: 0.00073600026 | BS15: 0.0018898276 | BT15: 0
B16: 1093 | C16: Outros produtos alimentares | D16: 10 | E16: 0.01058141 | F16: 0.074077114 | G16: 0.019197472 | H16: 0.010254596 | I16: 0.0016642882 | J16: 0.0016359222 | K16: 0.0035952694 | L16: 0.10540289 | M16: 0.0083506667 | N16: 1.1144947 | O16: 0.03706268 | P16: 0.009207507 | Q16: 0.0083315059 | R16: 0.0054150674 | S16: 0.016177985 | T16: 0.0073482248 | U16: 0.018457964 | V16: 0.0052434741 | W16: 0.0054278199 | X16: 0.063432476 | Y16: 0.0078421909 | Z16: 0.020775142 | AA16: 0.028211245 | AB16: 0.0095125356 | AC16: 0.0087785333 | AD16: 0.0064458592 | AE16: 0.0062890998 | AF16: 0.0050361883 | AG16: 0.006362263 | AH16: 0.0043698873 | AI16: 0.006450735 | AJ16: 0.0078650905 | AK16: 0.0027110401 | AL16: 0.0029100316 | AM16: 0.0033115327 | AN16: 0.0050630817 | AO16: 0.0030112555 | AP16: 0.0010900808 | AQ16: 0.0016291038 | AR16: 0.0026340201 | AS16: 0.0018871264 | AT16: 0.0058749134 | AU16: 0.0020889483 | AV16: 0.0016047265 | AW16: 0.0038051021 | AX16: 0.0013058672 | AY16: 0.014240201 | AZ16: 0.055601658 | BA16: 0.0089346066 | BB16: 0.0062279894 | BC16: 0.008189869 | BD16: 0.0016526178 | BE16: 0.0015576506 | BF16: 0.00026668988 | BG16: 0.0020944773 | BH16: 0.0015010656 | BI16: 0.0042011489 | BJ16: 0.0012836379 | BK16: 0.0020067198 | BL16: 0.00098981235 | BM16: 0.0037239545 | BN16: 0.0073318334 | BO16: 0.0033077488 | BP16: 0.011112635 | BQ16: 0.0060599546 | BR16: 0.002291586 | BS16: 0.0092811854 | BT16: 0
B17: 1100 | C17: Fabricação de bebidas | D17: 11 | E17: 0.00021930027 | F17: 0.00029006245 | G17: 0.00013388028 | H17: 0.00047465416 | I17: 0.00050066736 | J17: 0.00036906955 | K17: 0.00067336735 | L17: 0.0028607084 | M17: 0.00048823961 | N17: 0.0010645998 | O17: 1.1003176 | P17: 0.00070917983 | Q17: 0.00075484663 | R17: 0.00057582589 | S17: 0.0010987341 | T17: 0.00049775759 | U17: 0.0010451402 | V17: 0.00056101959 | W17: 0.00052506792 | X17: 0.00064591848 | Y17: 0.00063028513 | Z17: 0.0011910135 | AA17: 0.00071416819 | AB17: 0.0013749539 | AC17: 0.00085848964 | AD17: 0.00069557132 | AE17: 0.00086500981 | AF17: 0.00077748292 | AG17: 0.00093108201 | AH17: 0.00065166649 | AI17: 0.00091967884 | AJ17: 0.0014420524 | AK17: 0.0007173136 | AL17: 0.00051600308 | AM17: 0.0006383398 | AN17: 0.00057534857 | AO17: 0.00089993428 | AP17: 0.00038156772 | AQ17: 0.00030801121 | AR17: 0.0004626063 | AS17: 0.00042935367 | AT17: 0.00057452978 | AU17: 0.00035433384 | AV17: 0.00045751454 | AW17: 0.0038587638 | AX17: 0.00043765348 | AY17: 0.02133422 | AZ17: 0.13046887 | BA17: 0.0010822293 | BB17: 0.0019987647 | BC17: 0.0012942129 | BD17: 0.00044021793 | BE17: 0.0012287341 | BF17: 8.5754337e-05 | BG17: 0.0011090004 | BH17: 0.00037655314 | BI17: 0.0012448046 | BJ17: 0.00037495622 | BK17: 0.00095191404 | BL17: 0.00024352664 | BM17: 0.0020065157 | BN17: 0.0012950109 | BO17: 0.00077849805 | BP17: 0.0037360614 | BQ17: 0.0032522454 | BR17: 0.0013635819 | BS17: 0.0088441753 | BT17: 0
B18: 1200 | C18: Fabricação de produtos do fumo | D18: 12 | E18: 1.1939779e-05 | F18: 1.520388e-05 | G18: 4.4775063e-06 | H18: 2.203213e-05 | I18: 1.0003194e-05 | J18: 1.2183002e-05 | K18: 2.5059671e-05 | L18: 0.000110015 | M18: 3.3797953e-05 | N18: 8.2368242e-05 | O18: 2.9008074e-05 | P18: 1.0733793 | Q18: 7.6181569e-05 | R18: 6.0744623e-05 | S18: 0.00011163242 | T18: 4.7628206e-05 | U18: 0.00014381316 | V18: 6.1304105e-05 | W18: 1.4429489e-05 | X18: 5.0328628e-05 | Y18: 3.8389993e-05 | Z18: 8.504788e-05 | AA18: 5.1292931e-05 | AB18: 9.469387e-05 | AC18: 8.0738733e-05 | AD18: 6.5734204e-05 | AE18: 6.3525499e-05 | AF18: 5.0156177e-05 | AG18: 6.8676265e-05 | AH18: 5.6335676e-05 | AI18: 7.1545643e-05 | AJ18: 8.8222668e-05 | AK18: 2.6876217e-05 | AL18: 2.9665823e-05 | AM18: 3.2684477e-05 | AN18: 5.0670303e-05 | AO18: 2.4268151e-05 | AP18: 7.7529199e-06 | AQ18: 1.0183051e-05 | AR18: 1.9047522e-05 | AS18: 1.1295245e-05 | AT18: 2.9318586e-05 | AU18: 9.3220514e-06 | AV18: 1.0364001e-05 | AW18: 9.1300238e-06 | AX18: 8.7002823e-06 | AY18: 1.4356835e-05 | AZ18: 1.8166614e-05 | BA18: 0.00012300348 | BB18: 6.7209784e-05 | BC18: 9.5602293e-05 | BD18: 1.8452467e-05 | BE18: 9.3074252e-06 | BF18: 1.729191e-06 | BG18: 1.8359347e-05 | BH18: 3.1082062e-05 | BI18: 4.3818213e-05 | BJ18: 1.2843657e-05 | BK18: 1.783135e-05 | BL18: 8.6763321e-06 | BM18: 5.8730164e-06 | BN18: 7.31917e-06 | BO18: 1.5085778e-05 | BP18: 8.8484282e-06 | BQ18: 1.2085511e-05 | BR18: 1.0055243e-05 | BS18: 1.2018275e-05 | BT18: 0
... B74: 9700 | C74: Serviços domésticos | D74: 68 | E74: 0 | F74: 0 | G74: 0 | H74: 0 | I74: 0 | J74: 0 | K74: 0 | L74: 0 | M74: 0 | N74: 0 | O74: 0 | P74: 0 | Q74: 0 | R74: 0 | S74: 0 | T74: 0 | U74: 0 | V74: 0 | W74: 0 | X74: 0 | Y74: 0 | Z74: 0 | AA74: 0 | AB74: 0 | AC74: 0 | AD74: 0 | AE74: 0 | AF74: 0 | AG74: 0 | AH74: 0 | AI74: 0 | AJ74: 0 | AK74: 0 | AL74: 0 | AM74: 0 | AN74: 0 | AO74: 0 | AP74: 0 | AQ74: 0 | AR74: 0 | AS74: 0 | AT74: 0 | AU74: 0 | AV74: 0 | AW74: 0 | AX74: 0 | AY74: 0 | AZ74: 0 | BA74: 0 | BB74: 0 | BC74: 0 | BD74: 0 | BE74: 0 | BF74: 0 | BG74: 0 | BH74: 0 | BI74: 0 | BJ74: 0 | BK74: 0 | BL74: 0 | BM74: 0 | BN74: 0 | BO74: 0 | BP74: 0 | BQ74: 0 | BR74: 0 | BS74: 0 | BT74: 1

Sheet G_2010
B2: Matriz G — inversa de Ghosh (2010)
B3: G = (I−x̂⁻¹Z)⁻¹, colada como VALOR; usada na ligação para frente (Q4).
B6: Código | C6: Atividades | E6: 1 | F6: 2 | G6: 3 | H6: 4 | I6: 5 | J6: 6 | K6: 7 | L6: 8 | M6: 9 | N6: 10 | O6: 11 | P6: 12 | Q6: 13 | R6: 14 | S6: 15 | T6: 16 | U6: 17 | V6: 18 | W6: 19 | X6: 20 | Y6: 21 | Z6: 22 | AA6: 23 | AB6: 24 | AC6: 25 | AD6: 26 | AE6: 27 | AF6: 28 | AG6: 29 | AH6: 30 | AI6: 31 | AJ6: 32 | AK6: 33 | AL6: 34 | AM6: 35 | AN6: 36 | AO6: 37 | AP6: 38 | AQ6: 39 | AR6: 40 | AS6: 41 | AT6: 42 | AU6: 43 | AV6: 44 | AW6: 45 | AX6: 46 | AY6: 47 | AZ6: 48 | BA6: 49 | BB6: 50 | BC6: 51 | BD6: 52 | BE6: 53 | BF6: 54 | BG6: 55 | BH6: 56 | BI6: 57 | BJ6: 58 | BK6: 59 | BL6: 60 | BM6: 61 | BN6: 62 | BO6: 63 | BP6: 64 | BQ6: 65 | BR6: 66 | BS6: 67 | BT6: 68
B7: 0191 | C7: Agricultura, inclusive o apoio à agricultura e a pós-colheita | D7: 1 | E7: 1.0315712 | F7: 0.029641619 | G7: 0.0015851207 | H7: 0.000722483 | I7: 0.0021284211 | J7: 0.00087479583 | K7: 0.00034717802 | L7: 0.067547945 | M7: 0.13044223 | N7: 0.27217353 | O7: 0.016800725 | P7: 0.021969586 | Q7: 0.027292503 | R7: 0.0092125549 | S7: 0.0037286939 | T7: 0.0013088209 | U7: 0.005009566 | V7: 0.00050449283 | W7: 0.039811093 | X7: 0.065800013 | Y7: 0.0048349019 | Z7: 0.0056872826 | AA7: 0.0036169483 | AB7: 0.003147916 | AC7: 0.004363289 | AD7: 0.0030118877 | AE7: 0.0041662231 | AF7: 0.0015791479 | AG7: 0.0031098318 | AH7: 0.001761415 | AI7: 0.0025246547 | AJ7: 0.0050031615 | AK7: 0.0035249921 | AL7: 0.0024763598 | AM7: 0.00077210072 | AN7: 0.0022305948 | AO7: 0.00087513219 | AP7: 0.0026394746 | AQ7: 0.00070115725 | AR7: 0.010666081 | AS7: 0.0014233574 | AT7: 0.042453731 | AU7: 0.010239342 | AV7: 0.00029198904 | AW7: 0.00092113036 | AX7: 0.00092077881 | AY7: 0.0016971773 | AZ7: 0.032827736 | BA7: 0.001223442 | BB7: 0.0010819983 | BC7: 0.0067427772 | BD7: 0.00072361539 | BE7: 0.0031205469 | BF7: 0.00050488667 | BG7: 0.0013947525 | BH7: 0.00060999627 | BI7: 0.0014603015 | BJ7: 0.00027024362 | BK7: 0.0019122633 | BL7: 0.00024553048 | BM7: 0.013997634 | BN7: 0.0049960886 | BO7: 0.00094682434 | BP7: 0.0040675091 | BQ7: 0.0032553803 | BR7: 0.00027552472 | BS7: 0.0049714714 | BT7: 0
B8: 0192 | C8: Pecuária, inclusive o apoio à pecuária | D8: 2 | E8: 0.0083767563 | F8: 1.0467924 | G8: 0.0018801961 | H8: 0.00018395651 | I8: 0.00057056603 | J8: 0.00019128006 | K8: 8.2443497e-05 | L8: 0.6402089 | M8: 0.0025963229 | N8: 0.041663813 | O8: 0.0017574282 | P8: 0.0025453661 | Q8: 0.0018627651 | R8: 0.0013617339 | S8: 0.0090389147 | T8: 0.0020734301 | U8: 0.0028326129 | V8: 0.00016273994 | W8: 0.002176655 | X8: 0.0032878432 | Y8: 0.0014280581 | Z8: 0.00099575378 | AA8: 0.0034222255 | AB8: 0.0005802104 | AC8: 0.0017165517 | AD8: 0.0014854296 | AE8: 0.0012995559 | AF8: 0.00062585229 | AG8: 0.00093135246 | AH8: 0.00047766551 | AI8: 0.00065931277 | AJ8: 0.0012092447 | AK8: 0.0010769142 | AL8: 0.00060648484 | AM8: 0.00022549717 | AN8: 0.00090671767 | AO8: 0.00022511391 | AP8: 0.00049497045 | AQ8: 0.00025683369 | AR8: 0.0096871627 | AS8: 0.00042835057 | AT8: 0.0067768088 | AU8: 0.00094868806 | AV8: 4.5369805e-05 | AW8: 0.00030916398 | AX8: 0.00036188865 | AY8: 0.0029718562 | AZ8: 0.040484178 | BA8: 0.00032493117 | BB8: 0.00036680806 | BC8: 0.0024261452 | BD8: 0.00028326237 | BE8: 0.0018298098 | BF8: 0.00043819371 | BG8: 0.00065660496 | BH8: 0.00029697828 | BI8: 0.0005685614 | BJ8: 9.9961732e-05 | BK8: 0.00088334469 | BL8: 5.5867086e-05 | BM8: 0.01202584 | BN8: 0.0063377747 | BO8: 0.0008544424 | BP8: 0.0041556423 | BQ8: 0.0037787926 | BR8: 0.0001408511 | BS8: 0.0045781229 | BT8: 0
B9: 0280 | C9: Produção florestal; pesca e aquicultura | D9: 3 | E9: 0.046319863 | F9: 0.053597648 | G9: 1.0810001 | H9: 0.00076412285 | I9: 0.0032582422 | J9: 0.0015664867 | K9: 0.00045575351 | L9: 0.10113509 | M9: 0.0070569427 | N9: 0.04729708 | O9: 0.0060829316 | P9: 0.0043223467 | Q9: 0.0088782955 | R9: 0.0059830999 | S9: 0.0058717357 | T9: 0.13792668 | U9: 0.1363919 | V9: 0.0038494525 | W9: 0.0067234251 | X9: 0.004271375 | Y9: 0.011151625 | Z9: 0.0045680716 | AA9: 0.0050119662 | AB9: 0.0037813242 | AC9: 0.066269351 | AD9: 0.010297299 | AE9: 0.031259076 | AF9: 0.0022180462 | AG9: 0.012020138 | AH9: 0.0058627833 | AI9: 0.0062530839 | AJ9: 0.012404336 | AK9: 0.018016885 | AL9: 0.010320075 | AM9: 0.0034210136 | AN9: 0.035416536 | AO9: 0.0025348615 | AP9: 0.0049637148 | AQ9: 0.0018313839 | AR9: 0.080353 | AS9: 0.0045916276 | AT9: 0.042648444 | AU9: 0.0079831244 | AV9: 0.00037737046 | AW9: 0.0011139016 | AX9: 0.0021210097 | AY9: 0.0025848193 | AZ9: 0.02658229 | BA9: 0.0047662301 | BB9: 0.002576596 | BC9: 0.0082558125 | BD9: 0.0017478518 | BE9: 0.0086266878 | BF9: 0.0032813298 | BG9: 0.0045060941 | BH9: 0.0017323951 | BI9: 0.0043243206 | BJ9: 0.0013328481 | BK9: 0.0061478403 | BL9: 0.00027119685 | BM9: 0.015745675 | BN9: 0.0071728882 | BO9: 0.0021508781 | BP9: 0.0053712999 | BQ9: 0.0077046316 | BR9: 0.00066568778 | BS9: 0.0063233862 | BT9: 0
B10: 0580 | C10: Extração de carvão mineral e de minerais não-metálicos | D10: 4 | E10: 0.062102355 | F10: 0.031073383 | G10: 0.001727212 | H10: 1.0187929 | I10: 0.032045423 | J10: 0.0036128413 | K10: 0.0014781406 | L10: 0.03399665 | M10: 0.011045775 | N10: 0.045845528 | O10: 0.010647355 | P10: 0.0019291869 | Q10: 0.013139652 | R10: 0.0050912081 | S10: 0.0055713797 | T10: 0.0022745496 | U10: 0.015387479 | V10: 0.0021981787 | W10: 0.036088435 | X10: 0.01403388 | Y10: 0.20805612 | Z10: 0.03322071 | AA10: 0.010561758 | AB10: 0.0050997343 | AC10: 0.034010492 | AD10: 0.26668522 | AE10: 0.099179307 | AF10: 0.028120895 | AG10: 0.025463607 | AH10: 0.0041566007 | AI10: 0.020051942 | AJ10: 0.020743383 | AK10: 0.034230115 | AL10: 0.023441001 | AM10: 0.005644833 | AN10: 0.010959322 | AO10: 0.0063752955 | AP10: 0.021154741 | AQ10: 0.025716367 | AR10: 0.56806401 | AS10: 0.0075910029 | AT10: 0.028191378 | AU10: 0.015350339 | AV10: 0.0005349175 | AW10: 0.0012461017 | AX10: 0.0033905474 | AY10: 0.0016701538 | AZ10: 0.012124239 | BA10: 0.001859172 | BB10: 0.0015636477 | BC10: 0.011510927 | BD10: 0.0020451702 | BE10: 0.0075060679 | BF10: 0.01752799 | BG10: 0.003054225 | BH10: 0.0018614303 | BI10: 0.0024225989 | BJ10: 0.001137677 | BK10: 0.0072805816 | BL10: 0.00029736738 | BM10: 0.027470929 | BN10: 0.0057765072 | BO10: 0.0019701554 | BP10: 0.0075645665 | BQ10: 0.0068159805 | BR10: 0.00097838598 | BS10: 0.0065088328 | BT10: 0
B11: 0680 | C11: Extração de petróleo e gás, inclusive as atividades de apoio | D11: 5 | E11: 0.040708893 | F11: 0.016830986 | G11: 0.0024689079 | H11: 0.004333972 | I11: 1.0605513 | J11: 0.010908156 | K11: 0.0040965063 | L11: 0.036562854 | M11: 0.012210922 | N11: 0.043977949 | O11: 0.0093167317 | P11: 0.0019886808 | Q11: 0.009753123 | R11: 0.0052154732 | S11: 0.0053028021 | T11: 0.0032483525 | U11: 0.018577707 | V11: 0.0018432188 | W11: 0.82005049 | X11: 0.006217678 | Y11: 0.050574633 | Z11: 0.01432647 | AA11: 0.0058382063 | AB11: 0.006503382 | AC11: 0.019880664 | AD11: 0.021515092 | AE11: 0.027896428 | AF11: 0.013900057 | AG11: 0.014628102 | AH11: 0.0057546796 | AI11: 0.011792286 | AJ11: 0.015148546 | AK11: 0.021818931 | AL11: 0.013079635 | AM11: 0.0036028927 | AN11: 0.0064380852 | AO11: 0.0037621608 | AP11: 0.087380851 | AQ11: 0.0074334204 | AR11: 0.066363923 | AS11: 0.0076577103 | AT11: 0.073919099 | AU11: 0.17141831 | AV11: 0.004580441 | AW11: 0.012016998 | AX11: 0.0089106445 | AY11: 0.0012283731 | AZ11: 0.01196996 | BA11: 0.0031451957 | BB11: 0.0025410243 | BC11: 0.013610839 | BD11: 0.0024543686 | BE11: 0.011406859 | BF11: 0.0020742033 | BG11: 0.005183485 | BH11: 0.0032343745 | BI11: 0.0038541038 | BJ11: 0.0024480045 | BK11: 0.007013235 | BL11: 0.0011125661 | BM11: 0.021599076 | BN11: 0.0049642461 | BO11: 0.0032884408 | BP11: 0.0044133091 | BQ11: 0.0047773139 | BR11: 0.0012807438 | BS11: 0.010481321 | BT11: 0
B12: 0791 | C12: Extração de minério de ferro, inclusive beneficiamentos e a aglomeração | D12: 6 | E12: 0.0015343626 | F12: 0.0013146848 | G12: 0.00010928336 | H12: 0.00049188696 | I12: 0.0063858742 | J12: 1.0145821 | K12: 0.0010208459 | L12: 0.0035855534 | M12: 0.0005464218 | N12: 0.0031536096 | O12: 0.0021153402 | P12: 0.0001365929 | Q12: 0.00054744085 | R12: 0.00049674966 | S12: 0.00043584815 | T12: 0.00037654284 | U12: 0.0014482651 | V12: 0.00032555913 | W12: 0.0057585641 | X12: 0.00032979675 | Y12: 0.0015054133 | Z12: 0.0012521381 | AA12: 0.00070890684 | AB12: 0.00058070067 | AC12: 0.0030061786 | AD12: 0.0047566246 | AE12: 0.22964345 | AF12: 0.0057000503 | AG12: 0.043491481 | AH12: 0.0014968025 | AI12: 0.010588957 | AJ12: 0.026733964 | AK12: 0.031745589 | AL12: 0.025171507 | AM12: 0.0043185572 | AN12: 0.0040176703 | AO12: 0.0049276446 | AP12: 0.003150068 | AQ12: 0.0013236335 | AR12: 0.055888472 | AS12: 0.0039531111 | AT12: 0.0065825952 | AU12: 0.0052617293 | AV12: 0.00018745069 | AW12: 0.00024684433 | AX12: 0.00074404912 | AY12: 0.00018685186 | AZ12: 0.0018755201 | BA12: 0.00035782919 | BB12: 0.00030014665 | BC12: 0.0020106789 | BD12: 0.00040810205 | BE12: 0.0012609925 | BF12: 0.00059167477 | BG12: 0.0006154148 | BH12: 0.00053440149 | BI12: 0.0004525354 | BJ12: 0.00061570418 | BK12: 0.0011159965 | BL12: 9.5495674e-05 | BM12: 0.0035893204 | BN12: 0.0007018956 | BO12: 0.00034817951 | BP12: 0.00091787247 | BQ12: 0.00085317307 | BR12: 0.00020980757 | BS12: 0.00089309934 | BT12: 0
B13: 0792 | C13: Extração de minerais metálicos não-ferrosos, inclusive beneficiamentos | D13: 7 | E13: 0.0083869082 | F13: 0.0038374024 | G13: 0.00040082615 | H13: 0.0015378 | I13: 0.013649622 | J13: 0.0044483961 | K13: 1.0599397 | L13: 0.013619903 | M13: 0.0024979189 | N13: 0.015922558 | O13: 0.0047304844 | P13: 0.00060487931 | Q13: 0.0027612684 | R13: 0.0023983855 | S13: 0.0019307257 | T13: 0.0012395194 | U13: 0.0093879407 | V13: 0.0053487517 | W13: 0.01342995 | X13: 0.0015397049 | Y13: 0.015277902 | Z13: 0.0087309031 | AA13: 0.0026963148 | AB13: 0.0024552833 | AC13: 0.0083541486 | AD13: 0.011492927 | AE13: 0.16657566 | AF13: 0.67536704 | AG13: 0.057768922 | AH13: 0.0088841214 | AI13: 0.11944053 | AJ13: 0.061838625 | AK13: 0.079756576 | AL13: 0.11237713 | AM13: 0.019208344 | AN13: 0.029682894 | AO13: 0.029351048 | AP13: 0.013164118 | AQ13: 0.0056844782 | AR13: 0.13065463 | AS13: 0.023153969 | AT13: 0.02417028 | AU13: 0.021691769 | AV13: 0.00083775859 | AW13: 0.00090216815 | AX13: 0.003337342 | AY13: 0.00067141425 | AZ13: 0.0052972523 | BA13: 0.0021039106 | BB13: 0.0013839617 | BC13: 0.0083053449 | BD13: 0.001820671 | BE13: 0.0062695791 | BF13: 0.0028800106 | BG13: 0.0035358393 | BH13: 0.001672953 | BI13: 0.0026924382 | BJ13: 0.0016845825 | BK13: 0.0049064857 | BL13: 0.00037001352 | BM13: 0.011758999 | BN13: 0.002911109 | BO13: 0.0016283666 | BP13: 0.003941851 | BQ13: 0.0058196429 | BR13: 0.0012554004 | BS13: 0.0046176 | BT13: 0
B14: 1091 | C14: Abate e produtos de carne, inclusive os produtos do laticínio e da pesca | D14: 8 | E14: 0.0014351689 | F14: 0.014217395 | G14: 0.00056080731 | H14: 8.2002724e-05 | I14: 0.00029622455 | J14: 0.00011235626 | K14: 3.8888699e-05 | L14: 1.0911304 | M14: 0.00034938026 | N14: 0.011193641 | O14: 0.000657077 | P14: 0.00012795267 | Q14: 0.00030772169 | R14: 0.00026355045 | S14: 0.014730259 | T14: 0.0001739631 | U14: 0.00062898189 | V14: 7.4967461e-05 | W14: 0.0013363057 | X14: 0.0026781407 | Y14: 0.00054169509 | Z14: 0.00060467738 | AA14: 0.0052605109 | AB14: 0.0004052875 | AC14: 0.00056737868 | AD14: 0.00037638759 | AE14: 0.00056606001 | AF14: 0.00020309696 | AG14: 0.00066004367 | AH14: 0.00029846483 | AI14: 0.00037097606 | AJ14: 0.00076112726 | AK14: 0.00059344623 | AL14: 0.00026489071 | AM14: 0.00011501798 | AN14: 0.00025737926 | AO14: 0.00013880499 | AP14: 0.00033087673 | AQ14: 8.2639947e-05 | AR14: 0.00131979 | AS14: 0.00025090766 | AT14: 0.0033435129 | AU14: 0.00057435606 | AV14: 2.8822277e-05 | AW14: 0.00031100382 | AX14: 0.00016709615 | AY14: 0.0018509837 | AZ14: 0.050788548 | BA14: 0.00018950882 | BB14: 0.00028692771 | BC14: 0.0011914062 | BD14: 0.0001762657 | BE14: 0.0013683775 | BF14: 0.00011300431 | BG14: 0.00054787424 | BH14: 0.00013711058 | BI14: 0.00039866605 | BJ14: 6.1074457e-05 | BK14: 0.00061980782 | BL14: 4.5564555e-05 | BM14: 0.013986953 | BN14: 0.0082272743 | BO14: 0.00099176115 | BP14: 0.0050865889 | BQ14: 0.0039781454 | BR14: 0.00012153787 | BS14: 0.0048078447 | BT14: 0
B15: 1092 | C15: Fabricação e refino de açúcar | D15: 9 | E15: 0.01148297 | F15: 0.0088132907 | G15: 0.00071789963 | H15: 0.0013035069 | I15: 0.0051089907 | J15: 0.0020850434 | K15: 0.00081076367 | L15: 0.023356385 | M15: 1.0411903 | N15: 0.093013496 | O15: 0.02449806 | P15: 0.00054216532 | Q15: 0.0022089461 | R15: 0.0012882035 | S15: 0.0015506729 | T15: 0.00085918274 | U15: 0.0040621914 | V15: 0.00071357326 | W15: 0.13447694 | X15: 0.015137937 | Y15: 0.010085489 | Z15: 0.016181455 | AA15: 0.0076554877 | AB15: 0.005367842 | AC15: 0.0049968882 | AD15: 0.004397799 | AE15: 0.0055293518 | AF15: 0.0025282978 | AG15: 0.0032595813 | AH15: 0.0015267156 | AI15: 0.0026917794 | AJ15: 0.0054815201 | AK15: 0.004939892 | AL15: 0.0026163671 | AM15: 0.00091965666 | AN15: 0.0016260403 | AO15: 0.0017393601 | AP15: 0.0097521968 | AQ15: 0.001440838 | AR15: 0.016554053 | AS15: 0.0025621156 | AT15: 0.018151371 | AU15: 0.03206043 | AV15: 0.00082297773 | AW15: 0.0021851387 | AX15: 0.0020845701 | AY15: 0.00061701587 | AZ15: 0.025430233 | BA15: 0.00090389645 | BB15: 0.00077192683 | BC15: 0.0039153879 | BD15: 0.00066046653 | BE15: 0.0034167153 | BF15: 0.00067502633 | BG15: 0.0014263809 | BH15: 0.0010176088 | BI15: 0.001231643 | BJ15: 0.00051154018 | BK15: 0.0023452751 | BL15: 0.00051683695 | BM15: 0.013512725 | BN15: 0.0040120192 | BO15: 0.0010832968 | BP15: 0.0033446384 | BQ15: 0.0029665954 | BR15: 0.00038602652 | BS15: 0.0044363003 | BT15: 0
B16: 1093 | C16: Outros produtos alimentares | D16: 10 | E16: 0.01160327 | F16: 0.040142782 | G16: 0.0025347295 | H16: 0.00098810111 | I16: 0.0012680754 | J16: 0.00060049681 | K16: 0.00023029897 | L16: 0.094134316 | M16: 0.0024089442 | N16: 1.1144947 | O16: 0.012764349 | P16: 0.00080152368 | Q16: 0.0021909496 | R16: 0.0017052592 | S16: 0.0030753824 | T16: 0.0010029069 | U16: 0.0067401114 | V16: 0.00058986105 | W16: 0.007999258 | X16: 0.010019687 | Y16: 0.0045297705 | Z16: 0.0063515352 | AA16: 0.0048713359 | AB16: 0.0025187 | AC16: 0.0041411144 | AD16: 0.0026842887 | AE16: 0.0037381733 | AF16: 0.0012356469 | AG16: 0.0031362622 | AH16: 0.0018280937 | AI16: 0.00245546 | AJ16: 0.0050100305 | AK16: 0.0027615497 | AL16: 0.0015282248 | AM16: 0.00070785383 | AN16: 0.0016637907 | AO16: 0.00082635 | AP16: 0.0010807791 | AQ16: 0.00045529003 | AR16: 0.0076483569 | AS16: 0.0013150571 | AT16: 0.020577534 | AU16: 0.0028771162 | AV16: 0.00011138984 | AW16: 0.00061651599 | AX16: 0.00057291435 | AY16: 0.0013935034 | AZ16: 0.045348263 | BA16: 0.0013253667 | BB16: 0.001139513 | BC16: 0.007054222 | BD16: 0.00072520291 | BE16: 0.003668728 | BF16: 0.00051298705 | BG16: 0.0015512652 | BH16: 0.00045681173 | BI16: 0.0015845635 | BJ16: 0.00021059697 | BK16: 0.001623646 | BL16: 0.00013331838 | BM16: 0.011713928 | BN16: 0.0075785133 | BO16: 0.0012249131 | BP16: 0.0074583614 | BQ16: 0.0045027599 | BR16: 0.00034672162 | BS16: 0.0062850363 | BT16: 0
B17: 1100 | C17: Fabricação de bebidas | D17: 11 | E17: 0.00069825513 | F17: 0.00045640781 | G17: 5.132658e-05 | H17: 0.00013280006 | I17: 0.0011076536 | J17: 0.00039336381 | K17: 0.00012524221 | L17: 0.0074183475 | M17: 0.00040895614 | N17: 0.0030911817 | O17: 1.1003176 | P17: 0.00017925398 | Q17: 0.0005763758 | R17: 0.0005265212 | S17: 0.00060646459 | T17: 0.00019725782 | U17: 0.0011081435 | V17: 0.00018325117 | W17: 0.0022468697 | X17: 0.00029624998 | Y17: 0.0010570949 | Z17: 0.0010572788 | AA17: 0.00035806713 | AB17: 0.0010570765 | AC17: 0.0011758948 | AD17: 0.00084106237 | AE17: 0.0014928979 | AF17: 0.00055388731 | AG17: 0.0013326829 | AH17: 0.00079157437 | AI17: 0.001016478 | AJ17: 0.0026672014 | AK17: 0.002121603 | AL17: 0.00078682832 | AM17: 0.00039619099 | AN17: 0.00054897545 | AO17: 0.00071707627 | AP17: 0.0010984695 | AQ17: 0.00024994476 | AR17: 0.0039003065 | AS17: 0.00086875424 | AT17: 0.0058430894 | AU17: 0.0014170347 | AV17: 9.2212032e-05 | AW17: 0.0018153667 | AX17: 0.00055751842 | AY17: 0.0060618727 | AZ17: 0.30897117 | BA17: 0.00046614178 | BB17: 0.0010618697 | BC17: 0.0032368012 | BD17: 0.00056090973 | BE17: 0.0084031379 | BF17: 0.00047895432 | BG17: 0.0023849552 | BH17: 0.00033273768 | BI17: 0.0013632669 | BJ17: 0.00017861926 | BK17: 0.0022363536 | BL17: 9.5240526e-05 | BM17: 0.018326472 | BN17: 0.0038867177 | BO17: 0.00083708284 | BP17: 0.0072807899 | BQ17: 0.007016667 | BR17: 0.00059905145 | BS17: 0.017390009 | BT17: 0
B18: 1200 | C18: Fabricação de produtos do fumo | D18: 12 | E18: 0.00015040381 | F18: 9.464628e-05 | G18: 6.7912465e-06 | H18: 2.4387374e-05 | I18: 8.7555002e-05 | J18: 5.137219e-05 | K18: 1.844003e-05 | L18: 0.0011286858 | M18: 0.00011200094 | N18: 0.00094620556 | O18: 0.00011476421 | P18: 1.0733793 | Q18: 0.00023013597 | R18: 0.00021974554 | S18: 0.00024377589 | T18: 7.4673778e-05 | U18: 0.00060326428 | V18: 7.9222007e-05 | W18: 0.00024428732 | X18: 9.1323651e-05 | Y18: 0.00025473142 | Z18: 0.00029869222 | AA18: 0.00010174405 | AB18: 0.00028802336 | AC18: 0.00043752503 | AD18: 0.00031446007 | AE18: 0.00043375524 | AF18: 0.00014136521 | AG18: 0.00038889568 | AH18: 0.00027073064 | AI18: 0.0003128474 | AJ18: 0.00064556879 | AK18: 0.00031449284 | AL18: 0.00017896646 | AM18: 8.0256788e-05 | AN18: 0.00019127708 | AO18: 7.6503061e-05 | AP18: 8.8301738e-05 | AQ18: 3.2692113e-05 | AR18: 0.0006353503 | AS18: 9.0420103e-05 | AT18: 0.0011796701 | AU18: 0.00014749147 | AV18: 8.2641406e-06 | AW18: 1.6993218e-05 | AX18: 4.3847995e-05 | AY18: 1.6138989e-05 | AZ18: 0.00017020511 | BA18: 0.00020960601 | BB18: 0.00014126338 | BC18: 0.00094594564 | BD18: 9.3018051e-05 | BE18: 0.00025182608 | BF18: 3.8209253e-05 | BG18: 0.00015620442 | BH18: 0.00010866085 | BI18: 0.00018985495 | BJ18: 2.4206054e-05 | BK18: 0.00016573512 | BL18: 1.3424528e-05 | BM18: 0.0002122194 | BN18: 8.6907841e-05 | BO18: 6.4175047e-05 | BP18: 6.8221018e-05 | BQ18: 0.00010315734 | BR18: 1.7476845e-05 | BS18: 9.349151e-05 | BT18: 0
... B74: 9700 | C74: Serviços domésticos | D74: 68 | E74: 0 | F74: 0 | G74: 0 | H74: 0 | I74: 0 | J74: 0 | K74: 0 | L74: 0 | M74: 0 | N74: 0 | O74: 0 | P74: 0 | Q74: 0 | R74: 0 | S74: 0 | T74: 0 | U74: 0 | V74: 0 | W74: 0 | X74: 0 | Y74: 0 | Z74: 0 | AA74: 0 | AB74: 0 | AC74: 0 | AD74: 0 | AE74: 0 | AF74: 0 | AG74: 0 | AH74: 0 | AI74: 0 | AJ74: 0 | AK74: 0 | AL74: 0 | AM74: 0 | AN74: 0 | AO74: 0 | AP74: 0 | AQ74: 0 | AR74: 0 | AS74: 0 | AT74: 0 | AU74: 0 | AV74: 0 | AW74: 0 | AX74: 0 | AY74: 0 | AZ74: 0 | BA74: 0 | BB74: 0 | BC74: 0 | BD74: 0 | BE74: 0 | BF74: 0 | BG74: 0 | BH74: 0 | BI74: 0 | BJ74: 0 | BK74: 0 | BL74: 0 | BM74: 0 | BN74: 0 | BO74: 0 | BP74: 0 | BQ74: 0 | BR74: 0 | BS74: 0 | BT74: 1

Sheet Q1_Multiplicadores
B2: Questão 1 — Multiplicadores (2020), tipos I e II
B3: Multiplicadores de produção, emprego, renda e valor adicionado para todos os setores. Tipo I: modelo aberto (B_2020). Tipo II: modelo fechado para as famílias (B2_2020). Emprego em ocupações por R$ 1 milhão; renda e VA em R$ por R$ 1,00 de demanda final.
B5: Síntese
B6: • Produção: média 2.061 (tipo I) e 3.979 (tipo II). Maior geração de EMPREGO (II): Serviços domésticos (109.1 ocup./R$ mi); de RENDA (II): Serviços domésticos (R$ 1.395/R$ 1,00).
B7: • Rankings completos de emprego e renda abaixo da tabela principal.
B9: Código | C9: Atividades | D9: nº | E9: Produção I | F9: Produção II | G9: Emprego I (ocup/R$ mi) | H9: Emprego II (ocup/R$ mi) | I9: Renda I | J9: Renda II | K9: VA I | L9: VA II | M9: Rank emprego II | N9: Rank renda II
B10: 0191 | C10: Agricultura, inclusive o apoio à agricultura e a pós-colheita | D10: 1 | E10: =SUM(B_2020!E7:E74) -> 1.7071065 | F10: =SUM(B2_2020!E7:E74) -> 3.401712 | G10: =SUMPRODUCT(Dados_2020!$Q$7:$Q$74,B_2020!E7:E74) -> 14.564395 | H10: =SUMPRODUCT(Dados_2020!$Q$7:$Q$74,B2_2020!E7:E74) -> 27.60451 | I10: =SUMPRODUCT(Dados_2020!$R$7:$R$74,B_2020!E7:E74) -> 0.15692448 | J10: =SUMPRODUCT(Dados_2020!$R$7:$R$74,B2_2020!E7:E74) -> 0.47288915 | K10: =SUMPRODUCT(Dados_2020!$S$7:$S$74,B_2020!E7:E74) -> 0.80087069 | L10: =SUMPRODUCT(Dados_2020!$S$7:$S$74,B2_2020!E7:E74) -> 1.62516 | M10: =RANK(H10,$H$10:$H$77,0) -> 40 | N10: =RANK(J10,$J$10:$J$77,0) -> 66
B11: 0192 | C11: Pecuária, inclusive o apoio à pecuária | D11: 2 | E11: =SUM(B_2020!F7:F74) -> 1.8700944 | F11: =SUM(B2_2020!F7:F74) -> 3.6227308 | G11: =SUMPRODUCT(Dados_2020!$Q$7:$Q$74,B_2020!F7:F74) -> 32.898223 | H11: =SUMPRODUCT(Dados_2020!$Q$7:$Q$74,B2_2020!F7:F74) -> 46.384889 | I11: =SUMPRODUCT(Dados_2020!$R$7:$R$74,B_2020!F7:F74) -> 0.22832362 | J11: =SUMPRODUCT(Dados_2020!$R$7:$R$74,B2_2020!F7:F74) -> 0.55510834 | K11: =SUMPRODUCT(Dados_2020!$S$7:$S$74,B_2020!F7:F74) -> 0.82829609 | L11: =SUMPRODUCT(Dados_2020!$S$7:$S$74,B2_2020!F7:F74) -> 1.6808127 | M11: =RANK(H11,$H$10:$H$77,0) -> 4 | N11: =RANK(J11,$J$10:$J$77,0) -> 60
B12: 0280 | C12: Produção florestal; pesca e aquicultura | D12: 3 | E12: =SUM(B_2020!G7:G74) -> 1.4228934 | F12: =SUM(B2_2020!G7:G74) -> 3.3740689 | G12: =SUMPRODUCT(Dados_2020!$Q$7:$Q$74,B_2020!G7:G74) -> 19.453832 | H12: =SUMPRODUCT(Dados_2020!$Q$7:$Q$74,B2_2020!G7:G74) -> 34.468271 | I12: =SUMPRODUCT(Dados_2020!$R$7:$R$74,B_2020!G7:G74) -> 0.11860218 | J12: =SUMPRODUCT(Dados_2020!$R$7:$R$74,B2_2020!G7:G74) -> 0.48240514 | K12: =SUMPRODUCT(Dados_2020!$S$7:$S$74,B_2020!G7:G74) -> 0.92212566 | L12: =SUMPRODUCT(Dados_2020!$S$7:$S$74,B2_2020!G7:G74) -> 1.8712156 | M12: =RANK(H12,$H$10:$H$77,0) -> 18 | N12: =RANK(J12,$J$10:$J$77,0) -> 65
B13: 0580 | C13: Extração de carvão mineral e de minerais não-metálicos | D13: 4 | E13: =SUM(B_2020!H7:H74) -> 2.0204499 | F13: =SUM(B2_2020!H7:H74) -> 3.7842659 | G13: =SUMPRODUCT(Dados_2020!$Q$7:$Q$74,B_2020!H7:H74) -> 10.041746 | H13: =SUMPRODUCT(Dados_2020!$Q$7:$Q$74,B2_2020!H7:H74) -> 23.614441 | I13: =SUMPRODUCT(Dados_2020!$R$7:$R$74,B_2020!H7:H74) -> 0.35318707 | J13: =SUMPRODUCT(Dados_2020!$R$7:$R$74,B2_2020!H7:H74) -> 0.68205626 | K13: =SUMPRODUCT(Dados_2020!$S$7:$S$74,B_2020!H7:H74) -> 0.83357958 | L13: =SUMPRODUCT(Dados_2020!$S$7:$S$74,B2_2020!H7:H74) -> 1.6915342 | M13: =RANK(H13,$H$10:$H$77,0) -> 48 | N13: =RANK(J13,$J$10:$J$77,0) -> 49
B14: 0680 | C14: Extração de petróleo e gás, inclusive as atividades de apoio | D14: 5 | E14: =SUM(B_2020!I7:I74) -> 1.9097137 | F14: =SUM(B2_2020!I7:I74) -> 3.5380311 | G14: =SUMPRODUCT(Dados_2020!$Q$7:$Q$74,B_2020!I7:I74) -> 4.9467966 | H14: =SUMPRODUCT(Dados_2020!$Q$7:$Q$74,B2_2020!I7:I74) -> 17.476819 | I14: =SUMPRODUCT(Dados_2020!$R$7:$R$74,B_2020!I7:I74) -> 0.25152567 | J14: =SUMPRODUCT(Dados_2020!$R$7:$R$74,B2_2020!I7:I74) -> 0.55513071 | K14: =SUMPRODUCT(Dados_2020!$S$7:$S$74,B_2020!I7:I74) -> 0.76954292 | L14: =SUMPRODUCT(Dados_2020!$S$7:$S$74,B2_2020!I7:I74) -> 1.5615884 | M14: =RANK(H14,$H$10:$H$77,0) -> 62 | N14: =RANK(J14,$J$10:$J$77,0) -> 59
B15: 0791 | C15: Extração de minério de ferro, inclusive beneficiamentos e a aglomeração | D15: 6 | E15: =SUM(B_2020!J7:J74) -> 1.7643559 | F15: =SUM(B2_2020!J7:J74) -> 3.6252073 | G15: =SUMPRODUCT(Dados_2020!$Q$7:$Q$74,B_2020!J7:J74) -> 4.7980874 | H15: =SUMPRODUCT(Dados_2020!$Q$7:$Q$74,B2_2020!J7:J74) -> 19.117477 | I15: =SUMPRODUCT(Dados_2020!$R$7:$R$74,B_2020!J7:J74) -> 0.17640881 | J15: =SUMPRODUCT(Dados_2020!$R$7:$R$74,B2_2020!J7:J74) -> 0.52337058 | K15: =SUMPRODUCT(Dados_2020!$S$7:$S$74,B_2020!J7:J74) -> 0.87943855 | L15: =SUMPRODUCT(Dados_2020!$S$7:$S$74,B2_2020!J7:J74) -> 1.7845931 | M15: =RANK(H15,$H$10:$H$77,0) -> 58 | N15: =RANK(J15,$J$10:$J$77,0) -> 62
B16: 0792 | C16: Extração de minerais metálicos não-ferrosos, inclusive beneficiamentos | D16: 7 | E16: =SUM(B_2020!K7:K74) -> 2.2132314 | F16: =SUM(B2_2020!K7:K74) -> 3.9546114 | G16: =SUMPRODUCT(Dados_2020!$Q$7:$Q$74,B_2020!K7:K74) -> 7.9804299 | H16: =SUMPRODUCT(Dados_2020!$Q$7:$Q$74,B2_2020!K7:K74) -> 21.380478 | I16: =SUMPRODUCT(Dados_2020!$R$7:$R$74,B_2020!K7:K74) -> 0.34076101 | J16: =SUMPRODUCT(Dados_2020!$R$7:$R$74,B2_2020!K7:K74) -> 0.66544694 | K16: =SUMPRODUCT(Dados_2020!$S$7:$S$74,B_2020!K7:K74) -> 0.82297633 | L16: =SUMPRODUCT(Dados_2020!$S$7:$S$74,B2_2020!K7:K74) -> 1.6700176 | M16: =RANK(H16,$H$10:$H$77,0) -> 55 | N16: =RANK(J16,$J$10:$J$77,0) -> 53
B17: 1091 | C17: Abate e produtos de carne, inclusive os produtos do laticínio e da pesca | D17: 8 | E17: =SUM(B_2020!L7:L74) -> 3.5003526 | F17: =SUM(B2_2020!L7:L74) -> 6.2769326 | G17: =SUMPRODUCT(Dados_2020!$Q$7:$Q$74,B_2020!L7:L74) -> 27.745521 | H17: =SUMPRODUCT(Dados_2020!$Q$7:$Q$74,B2_2020!L7:L74) -> 49.111508 | I17: =SUMPRODUCT(Dados_2020!$R$7:$R$74,B_2020!L7:L74) -> 0.56189556 | J17: =SUMPRODUCT(Dados_2020!$R$7:$R$74,B2_2020!L7:L74) -> 1.0795979 | K17: =SUMPRODUCT(Dados_2020!$S$7:$S$74,B_2020!L7:L74) -> 1.3122119 | L17: =SUMPRODUCT(Dados_2020!$S$7:$S$74,B2_2020!L7:L74) -> 2.6627947 | M17: =RANK(H17,$H$10:$H$77,0) -> 3 | N17: =RANK(J17,$J$10:$J$77,0) -> 9
B18: 1092 | C18: Fabricação e refino de açúcar | D18: 9 | E18: =SUM(B_2020!M7:M74) -> 2.5364508 | F18: =SUM(B2_2020!M7:M74) -> 4.5170245 | G18: =SUMPRODUCT(Dados_2020!$Q$7:$Q$74,B_2020!M7:M74) -> 13.973891 | H18: =SUMPRODUCT(Dados_2020!$Q$7:$Q$74,B2_2020!M7:M74) -> 29.214552 | I18: =SUMPRODUCT(Dados_2020!$R$7:$R$74,B_2020!M7:M74) -> 0.34990299 | J18: =SUMPRODUCT(Dados_2020!$R$7:$R$74,B2_2020!M7:M74) -> 0.71918734 | K18: =SUMPRODUCT(Dados_2020!$S$7:$S$74,B_2020!M7:M74) -> 0.93601925 | L18: =SUMPRODUCT(Dados_2020!$S$7:$S$74,B2_2020!M7:M74) -> 1.899409 | M18: =RANK(H18,$H$10:$H$77,0) -> 30 | N18: =RANK(J18,$J$10:$J$77,0) -> 42
B19: 1093 | C19: Outros produtos alimentares | D19: 10 | E19: =SUM(B_2020!N7:N74) -> 2.9111231 | F19: =SUM(B2_2020!N7:N74) -> 5.1425352 | G19: =SUMPRODUCT(Dados_2020!$Q$7:$Q$74,B_2020!N7:N74) -> 18.190805 | H19: =SUMPRODUCT(Dados_2020!$Q$7:$Q$74,B2_2020!N7:N74) -> 35.361686 | I19: =SUMPRODUCT(Dados_2020!$R$7:$R$74,B_2020!N7:N74) -> 0.43159943 | J19: =SUMPRODUCT(Dados_2020!$R$7:$R$74,B2_2020!N7:N74) -> 0.84765342 | K19: =SUMPRODUCT(Dados_2020!$S$7:$S$74,B_2020!N7:N74) -> 1.0545655 | L19: =SUMPRODUCT(Dados_2020!$S$7:$S$74,B2_2020!N7:N74) -> 2.139968 | M19: =RANK(H19,$H$10:$H$77,0) -> 15 | N19: =RANK(J19,$J$10:$J$77,0) -> 24
B20: 1100 | C20: Fabricação de bebidas | D20: 11 | E20: =SUM(B_2020!O7:O74) -> 2.354313 | F20: =SUM(B2_2020!O7:O74) -> 4.1007134 | G20: =SUMPRODUCT(Dados_2020!$Q$7:$Q$74,B_2020!O7:O74) -> 10.439327 | H20: =SUMPRODUCT(Dados_2020!$Q$7:$Q$74,B2_2020!O7:O74) -> 23.878007 | I20: =SUMPRODUCT(Dados_2020!$R$7:$R$74,B_2020!O7:O74) -> 0.36580563 | J20: =SUMPRODUCT(Dados_2020!$R$7:$R$74,B2_2020!O7:O74) -> 0.69142762 | K20: =SUMPRODUCT(Dados_2020!$S$7:$S$74,B_2020!O7:O74) -> 0.82534895 | L20: =SUMPRODUCT(Dados_2020!$S$7:$S$74,B2_2020!O7:O74) -> 1.6748323 | M20: =RANK(H20,$H$10:$H$77,0) -> 47 | N20: =RANK(J20,$J$10:$J$77,0) -> 45
B21: 1200 | C21: Fabricação de produtos do fumo | D21: 12 | E21: =SUM(B_2020!P7:P74) -> 2.4694855 | F21: =SUM(B2_2020!P7:P74) -> 4.4838271 | G21: =SUMPRODUCT(Dados_2020!$Q$7:$Q$74,B_2020!P7:P74) -> 13.259235 | H21: =SUMPRODUCT(Dados_2020!$Q$7:$Q$74,B2_2020!P7:P74) -> 28.759742 | I21: =SUMPRODUCT(Dados_2020!$R$7:$R$74,B_2020!P7:P74) -> 0.38318703 | J21: =SUMPRODUCT(Dados_2020!$R$7:$R$74,B2_2020!P7:P74) -> 0.75876753 | K21: =SUMPRODUCT(Dados_2020!$S$7:$S$74,B_2020!P7:P74) -> 0.951978 | L21: =SUMPRODUCT(Dados_2020!$S$7:$S$74,B2_2020!P7:P74) -> 1.9317932 | M21: =RANK(H21,$H$10:$H$77,0) -> 35 | N21: =RANK(J21,$J$10:$J$77,0) -> 36
B22: 1300 | C22: Fabricação de produtos têxteis | D22: 13 | E22: =SUM(B_2020!Q7:Q74) -> 2.5333943 | F22: =SUM(B2_2020!Q7:Q74) -> 4.4119494 | G22: =SUMPRODUCT(Dados_2020!$Q$7:$Q$74,B_2020!Q7:Q74) -> 22.128091 | H22: =SUMPRODUCT(Dados_2020!$Q$7:$Q$74,B2_2020!Q7:Q74) -> 36.583712 | I22: =SUMPRODUCT(Dados_2020!$R$7:$R$74,B_2020!Q7:Q74) -> 0.46020152 | J22: =SUMPRODUCT(Dados_2020!$R$7:$R$74,B2_2020!Q7:Q74) -> 0.81046418 | K22: =SUMPRODUCT(Dados_2020!$S$7:$S$74,B_2020!Q7:Q74) -> 0.88780528 | L22: =SUMPRODUCT(Dados_2020!$S$7:$S$74,B2_2020!Q7:Q74) -> 1.8015712 | M22: =RANK(H22,$H$10:$H$77,0) -> 13 | N22: =RANK(J22,$J$10:$J$77,0) -> 28
B23: 1400 | C23: Confecção de artefatos do vestuário e acessórios | D23: 14 | E23: =SUM(B_2020!R7:R74) -> 2.294681 | F23: =SUM(B2_2020!R7:R74) -> 4.2981389 | G23: =SUMPRODUCT(Dados_2020!$Q$7:$Q$74,B_2020!R7:R74) -> 35.305714 | H23: =SUMPRODUCT(Dados_2020!$Q$7:$Q$74,B2_2020!R7:R74) -> 50.72247 | I23: =SUMPRODUCT(Dados_2020!$R$7:$R$74,B_2020!R7:R74) -> 0.53097591 | J23: =SUMPRODUCT(Dados_2020!$R$7:$R$74,B2_2020!R7:R74) -> 0.9045271 | K23: =SUMPRODUCT(Dados_2020!$S$7:$S$74,B_2020!R7:R74) -> 0.94683434 | L23: =SUMPRODUCT(Dados_2020!$S$7:$S$74,B2_2020!R7:R74) -> 1.9213555 | M23: =RANK(H23,$H$10:$H$77,0) -> 2 | N23: =RANK(J23,$J$10:$J$77,0) -> 19
B24: 1500 | C24: Fabricação de calçados e de artefatos de couro | D24: 15 | E24: =SUM(B_2020!S7:S74) -> 2.675819 | F24: =SUM(B2_2020!S7:S74) -> 5.1126925 | G24: =SUMPRODUCT(Dados_2020!$Q$7:$Q$74,B_2020!S7:S74) -> 25.353651 | H24: =SUMPRODUCT(Dados_2020!$Q$7:$Q$74,B2_2020!S7:S74) -> 44.105572 | I24: =SUMPRODUCT(Dados_2020!$R$7:$R$74,B_2020!S7:S74) -> 0.62776479 | J24: =SUMPRODUCT(Dados_2020!$R$7:$R$74,B2_2020!S7:S74) -> 1.0821277 | K24: =SUMPRODUCT(Dados_2020!$S$7:$S$74,B_2020!S7:S74) -> 1.1516666 | L24: =SUMPRODUCT(Dados_2020!$S$7:$S$74,B2_2020!S7:S74) -> 2.3370095 | M24: =RANK(H24,$H$10:$H$77,0) -> 5 | N24: =RANK(J24,$J$10:$J$77,0) -> 8
B25: 1600 | C25: Fabricação de produtos da madeira | D25: 16 | E25: =SUM(B_2020!T7:T74) -> 2.4440417 | F25: =SUM(B2_2020!T7:T74) -> 4.6308785 | G25: =SUMPRODUCT(Dados_2020!$Q$7:$Q$74,B_2020!T7:T74) -> 19.992529 | H25: =SUMPRODUCT(Dados_2020!$Q$7:$Q$74,B2_2020!T7:T74) -> 36.820399 | I25: =SUMPRODUCT(Dados_2020!$R$7:$R$74,B_2020!T7:T74) -> 0.46067284 | J25: =SUMPRODUCT(Dados_2020!$R$7:$R$74,B2_2020!T7:T74) -> 0.86841562 | K25: =SUMPRODUCT(Dados_2020!$S$7:$S$74,B_2020!T7:T74) -> 1.0334992 | L25: =SUMPRODUCT(Dados_2020!$S$7:$S$74,B2_2020!T7:T74) -> 2.0972194 | M25: =RANK(H25,$H$10:$H$77,0) -> 11 | N25: =RANK(J25,$J$10:$J$77,0) -> 21
B26: 1700 | C26: Fabricação de celulose, papel e produtos de papel | D26: 17 | E26: =SUM(B_2020!U7:U74) -> 3.0494478 | F26: =SUM(B2_2020!U7:U74) -> 5.595438 | G26: =SUMPRODUCT(Dados_2020!$Q$7:$Q$74,B_2020!U7:U74) -> 16.378492 | H26: =SUMPRODUCT(Dados_2020!$Q$7:$Q$74,B2_2020!U7:U74) -> 35.970074 | I26: =SUMPRODUCT(Dados_2020!$R$7:$R$74,B_2020!U7:U74) -> 0.54334494 | J26: =SUMPRODUCT(Dados_2020!$R$7:$R$74,B2_2020!U7:U74) -> 1.018053 | K26: =SUMPRODUCT(Dados_2020!$S$7:$S$74,B_2020!U7:U74) -> 1.2032352 | L26: =SUMPRODUCT(Dados_2020!$S$7:$S$74,B2_2020!U7:U74) -> 2.4416546 | M26: =RANK(H26,$H$10:$H$77,0) -> 14 | N26: =RANK(J26,$J$10:$J$77,0) -> 12
B27: 1800 | C27: Impressão e reprodução de gravações | D27: 18 | E27: =SUM(B_2020!V7:V74) -> 1.9043625 | F27: =SUM(B2_2020!V7:V74) -> 3.6813558 | G27: =SUMPRODUCT(Dados_2020!$Q$7:$Q$74,B_2020!V7:V74) -> 13.864275 | H27: =SUMPRODUCT(Dados_2020!$Q$7:$Q$74,B2_2020!V7:V74) -> 27.538369 | I27: =SUMPRODUCT(Dados_2020!$R$7:$R$74,B_2020!V7:V74) -> 0.44972536 | J27: =SUMPRODUCT(Dados_2020!$R$7:$R$74,B2_2020!V7:V74) -> 0.7810515 | K27: =SUMPRODUCT(Dados_2020!$S$7:$S$74,B_2020!V7:V74) -> 0.83980718 | L27: =SUMPRODUCT(Dados_2020!$S$7:$S$74,B2_2020!V7:V74) -> 1.7041715 | M27: =RANK(H27,$H$10:$H$77,0) -> 41 | N27: =RANK(J27,$J$10:$J$77,0) -> 33
B28: 1991 | C28: Refino de petróleo e coquerias | D28: 19 | E28: =SUM(B_2020!W7:W74) -> 2.4093384 | F28: =SUM(B2_2020!W7:W74) -> 3.7823548 | G28: =SUMPRODUCT(Dados_2020!$Q$7:$Q$74,B_2020!W7:W74) -> 4.6985277 | H28: =SUMPRODUCT(Dados_2020!$Q$7:$Q$74,B2_2020!W7:W74) -> 15.26399 | I28: =SUMPRODUCT(Dados_2020!$R$7:$R$74,B_2020!W7:W74) -> 0.19431634 | J28: =SUMPRODUCT(Dados_2020!$R$7:$R$74,B2_2020!W7:W74) -> 0.45031967 | K28: =SUMPRODUCT(Dados_2020!$S$7:$S$74,B_2020!W7:W74) -> 0.64888762 | L28: =SUMPRODUCT(Dados_2020!$S$7:$S$74,B2_2020!W7:W74) -> 1.3167496 | M28: =RANK(H28,$H$10:$H$77,0) -> 68 | N28: =RANK(J28,$J$10:$J$77,0) -> 67
B29: 1992 | C29: Fabricação de biocombustíveis | D29: 20 | E29: =SUM(B_2020!X7:X74) -> 2.4937918 | F29: =SUM(B2_2020!X7:X74) -> 4.5346325 | G29: =SUMPRODUCT(Dados_2020!$Q$7:$Q$74,B_2020!X7:X74) -> 13.227105 | H29: =SUMPRODUCT(Dados_2020!$Q$7:$Q$74,B2_2020!X7:X74) -> 28.931525 | I29: =SUMPRODUCT(Dados_2020!$R$7:$R$74,B_2020!X7:X74) -> 0.33181813 | J29: =SUMPRODUCT(Dados_2020!$R$7:$R$74,B2_2020!X7:X74) -> 0.71233947 | K29: =SUMPRODUCT(Dados_2020!$S$7:$S$74,B_2020!X7:X74) -> 0.96450147 | L29: =SUMPRODUCT(Dados_2020!$S$7:$S$74,B2_2020!X7:X74) -> 1.9572063 | M29: =RANK(H29,$H$10:$H$77,0) -> 34 | N29: =RANK(J29,$J$10:$J$77,0) -> 43
B30: 2091 | C30: Fabricação de químicos orgânicos e inorgânicos, resinas e elastômeros | D30: 21 | E30: =SUM(B_2020!Y7:Y74) -> 2.2875291 | F30: =SUM(B2_2020!Y7:Y74) -> 3.7128369 | G30: =SUMPRODUCT(Dados_2020!$Q$7:$Q$74,B_2020!Y7:Y74) -> 7.0158326 | H30: =SUMPRODUCT(Dados_2020!$Q$7:$Q$74,B2_2020!Y7:Y74) -> 17.983681 | I30: =SUMPRODUCT(Dados_2020!$R$7:$R$74,B_2020!Y7:Y74) -> 0.27840861 | J30: =SUMPRODUCT(Dados_2020!$R$7:$R$74,B2_2020!Y7:Y74) -> 0.54416184 | K30: =SUMPRODUCT(Dados_2020!$S$7:$S$74,B_2020!Y7:Y74) -> 0.67360054 | L30: =SUMPRODUCT(Dados_2020!$S$7:$S$74,B2_2020!Y7:Y74) -> 1.3668981 | M30: =RANK(H30,$H$10:$H$77,0) -> 60 | N30: =RANK(J30,$J$10:$J$77,0) -> 61
B31: 2092 | C31: Fabricação de defensivos, desinfestantes, tintas e químicos diversos | D31: 22 | E31: =SUM(B_2020!Z7:Z74) -> 2.5802611 | F31: =SUM(B2_2020!Z7:Z74) -> 4.4396603 | G31: =SUMPRODUCT(Dados_2020!$Q$7:$Q$74,B_2020!Z7:Z74) -> 10.822837 | H31: =SUMPRODUCT(Dados_2020!$Q$7:$Q$74,B2_2020!Z7:Z74) -> 25.131052 | I31: =SUMPRODUCT(Dados_2020!$R$7:$R$74,B_2020!Z7:Z74) -> 0.39288428 | J31: =SUMPRODUCT(Dados_2020!$R$7:$R$74,B2_2020!Z7:Z74) -> 0.73957527 | K31: =SUMPRODUCT(Dados_2020!$S$7:$S$74,B_2020!Z7:Z74) -> 0.87875221 | L31: =SUMPRODUCT(Dados_2020!$S$7:$S$74,B2_2020!Z7:Z74) -> 1.7832004 | M31: =RANK(H31,$H$10:$H$77,0) -> 44 | N31: =RANK(J31,$J$10:$J$77,0) -> 39
B32: 2093 | C32: Fabricação de produtos de limpeza, cosméticos/perfumaria e higiene pessoal | D32: 23 | E32: =SUM(B_2020!AA7:AA74) -> 2.2986112 | F32: =SUM(B2_2020!AA7:AA74) -> 3.8511503 | G32: =SUMPRODUCT(Dados_2020!$Q$7:$Q$74,B_2020!AA7:AA74) -> 9.7513858 | H32: =SUMPRODUCT(Dados_2020!$Q$7:$Q$74,B2_2020!AA7:AA74) -> 21.698288 | I32: =SUMPRODUCT(Dados_2020!$R$7:$R$74,B_2020!AA7:AA74) -> 0.33988305 | J32: =SUMPRODUCT(Dados_2020!$R$7:$R$74,B2_2020!AA7:AA74) -> 0.62935897 | K32: =SUMPRODUCT(Dados_2020!$S$7:$S$74,B_2020!AA7:AA74) -> 0.73373007 | L32: =SUMPRODUCT(Dados_2020!$S$7:$S$74,B2_2020!AA7:AA74) -> 1.4889154 | M32: =RANK(H32,$H$10:$H$77,0) -> 54 | N32: =RANK(J32,$J$10:$J$77,0) -> 55
B33: 2100 | C33: Fabricação de produtos farmoquímicos e farmacêuticos | D33: 24 | E33: =SUM(B_2020!AB7:AB74) -> 2.469956 | F33: =SUM(B2_2020!AB7:AB74) -> 5.0016251 | G33: =SUMPRODUCT(Dados_2020!$Q$7:$Q$74,B_2020!AB7:AB74) -> 12.908143 | H33: =SUMPRODUCT(Dados_2020!$Q$7:$Q$74,B2_2020!AB7:AB74) -> 32.389523 | I33: =SUMPRODUCT(Dados_2020!$R$7:$R$74,B_2020!AB7:AB74) -> 0.50387989 | J33: =SUMPRODUCT(Dados_2020!$R$7:$R$74,B2_2020!AB7:AB74) -> 0.97591776 | K33: =SUMPRODUCT(Dados_2020!$S$7:$S$74,B_2020!AB7:AB74) -> 1.196467 | L33: =SUMPRODUCT(Dados_2020!$S$7:$S$74,B2_2020!AB7:AB74) -> 2.4279204 | M33: =RANK(H33,$H$10:$H$77,0) -> 27 | N33: =RANK(J33,$J$10:$J$77,0) -> 13
B34: 2200 | C34: Fabricação de produtos de borracha e de material plástico | D34: 25 | E34: =SUM(B_2020!AC7:AC74) -> 2.6562219 | F34: =SUM(B2_2020!AC7:AC74) -> 4.6292916 | G34: =SUMPRODUCT(Dados_2020!$Q$7:$Q$74,B_2020!AC7:AC74) -> 13.411396 | H34: =SUMPRODUCT(Dados_2020!$Q$7:$Q$74,B2_2020!AC7:AC74) -> 28.594313 | I34: =SUMPRODUCT(Dados_2020!$R$7:$R$74,B_2020!AC7:AC74) -> 0.48176416 | J34: =SUMPRODUCT(Dados_2020!$R$7:$R$74,B2_2020!AC7:AC74) -> 0.84964936 | K34: =SUMPRODUCT(Dados_2020!$S$7:$S$74,B_2020!AC7:AC74) -> 0.93247286 | L34: =SUMPRODUCT(Dados_2020!$S$7:$S$74,B2_2020!AC7:AC74) -> 1.8922125 | M34: =RANK(H34,$H$10:$H$77,0) -> 37 | N34: =RANK(J34,$J$10:$J$77,0) -> 23
B35: 2300 | C35: Fabricação de produtos de minerais não-metálicos | D35: 26 | E35: =SUM(B_2020!AD7:AD74) -> 2.6300734 | F35: =SUM(B2_2020!AD7:AD74) -> 4.8116878 | G35: =SUMPRODUCT(Dados_2020!$Q$7:$Q$74,B_2020!AD7:AD74) -> 16.475274 | H35: =SUMPRODUCT(Dados_2020!$Q$7:$Q$74,B2_2020!AD7:AD74) -> 33.262958 | I35: =SUMPRODUCT(Dados_2020!$R$7:$R$74,B_2020!AD7:AD74) -> 0.53152233 | J35: =SUMPRODUCT(Dados_2020!$R$7:$R$74,B2_2020!AD7:AD74) -> 0.93829138 | K35: =SUMPRODUCT(Dados_2020!$S$7:$S$74,B_2020!AD7:AD74) -> 1.0310311 | L35: =SUMPRODUCT(Dados_2020!$S$7:$S$74,B2_2020!AD7:AD74) -> 2.0922111 | M35: =RANK(H35,$H$10:$H$77,0) -> 22 | N35: =RANK(J35,$J$10:$J$77,0) -> 15
B36: 2491 | C36: Produção de ferro-gusa/ferroligas, siderurgia e tubos de aço sem costura | D36: 27 | E36: =SUM(B_2020!AE7:AE74) -> 2.7919456 | F36: =SUM(B2_2020!AE7:AE74) -> 4.8133714 | G36: =SUMPRODUCT(Dados_2020!$Q$7:$Q$74,B_2020!AE7:AE74) -> 10.841848 | H36: =SUMPRODUCT(Dados_2020!$Q$7:$Q$74,B2_2020!AE7:AE74) -> 26.396869 | I36: =SUMPRODUCT(Dados_2020!$R$7:$R$74,B_2020!AE7:AE74) -> 0.39967272 | J36: =SUMPRODUCT(Dados_2020!$R$7:$R$74,B2_2020!AE7:AE74) -> 0.77657409 | K36: =SUMPRODUCT(Dados_2020!$S$7:$S$74,B_2020!AE7:AE74) -> 0.955326 | L36: =SUMPRODUCT(Dados_2020!$S$7:$S$74,B2_2020!AE7:AE74) -> 1.9385871 | M36: =RANK(H36,$H$10:$H$77,0) -> 43 | N36: =RANK(J36,$J$10:$J$77,0) -> 34
B37: 2492 | C37: Metalurgia de metais não-ferrosos e a fundição de metais | D37: 28 | E37: =SUM(B_2020!AF7:AF74) -> 2.4623882 | F37: =SUM(B2_2020!AF7:AF74) -> 4.2293686 | G37: =SUMPRODUCT(Dados_2020!$Q$7:$Q$74,B_2020!AF7:AF74) -> 8.7290151 | H37: =SUMPRODUCT(Dados_2020!$Q$7:$Q$74,B2_2020!AF7:AF74) -> 22.326059 | I37: =SUMPRODUCT(Dados_2020!$R$7:$R$74,B_2020!AF7:AF74) -> 0.32646472 | J37: =SUMPRODUCT(Dados_2020!$R$7:$R$74,B2_2020!AF7:AF74) -> 0.65592391 | K37: =SUMPRODUCT(Dados_2020!$S$7:$S$74,B_2020!AF7:AF74) -> 0.83507503 | L37: =SUMPRODUCT(Dados_2020!$S$7:$S$74,B2_2020!AF7:AF74) -> 1.6945688 | M37: =RANK(H37,$H$10:$H$77,0) -> 52 | N37: =RANK(J37,$J$10:$J$77,0) -> 54
B38: 2500 | C38: Fabricação de produtos de metal, exceto máquinas e equipamentos | D38: 29 | E38: =SUM(B_2020!AG7:AG74) -> 2.7545289 | F38: =SUM(B2_2020!AG7:AG74) -> 4.9734409 | G38: =SUMPRODUCT(Dados_2020!$Q$7:$Q$74,B_2020!AG7:AG74) -> 16.106997 | H38: =SUMPRODUCT(Dados_2020!$Q$7:$Q$74,B2_2020!AG7:AG74) -> 33.181688 | I38: =SUMPRODUCT(Dados_2020!$R$7:$R$74,B_2020!AG7:AG74) -> 0.51808342 | J38: =SUMPRODUCT(Dados_2020!$R$7:$R$74,B2_2020!AG7:AG74) -> 0.93180673 | K38: =SUMPRODUCT(Dados_2020!$S$7:$S$74,B_2020!AG7:AG74) -> 1.048658 | L38: =SUMPRODUCT(Dados_2020!$S$7:$S$74,B2_2020!AG7:AG74) -> 2.1279802 | M38: =RANK(H38,$H$10:$H$77,0) -> 23 | N38: =RANK(J38,$J$10:$J$77,0) -> 17
B39: 2600 | C39: Fabricação de equipamentos de informática, produtos eletrônicos e ópticos | D39: 30 | E39: =SUM(B_2020!AH7:AH74) -> 1.9503537 | F39: =SUM(B2_2020!AH7:AH74) -> 3.1264951 | G39: =SUMPRODUCT(Dados_2020!$Q$7:$Q$74,B_2020!AH7:AH74) -> 7.0919335 | H39: =SUMPRODUCT(Dados_2020!$Q$7:$Q$74,B2_2020!AH7:AH74) -> 16.142429 | I39: =SUMPRODUCT(Dados_2020!$R$7:$R$74,B_2020!AH7:AH74) -> 0.27481689 | J39: =SUMPRODUCT(Dados_2020!$R$7:$R$74,B2_2020!AH7:AH74) -> 0.49411226 | K39: =SUMPRODUCT(Dados_2020!$S$7:$S$74,B_2020!AH7:AH74) -> 0.55584453 | L39: =SUMPRODUCT(Dados_2020!$S$7:$S$74,B2_2020!AH7:AH74) -> 1.1279427 | M39: =RANK(H39,$H$10:$H$77,0) -> 67 | N39: =RANK(J39,$J$10:$J$77,0) -> 63
B40: 2700 | C40: Fabricação de máquinas e equipamentos elétricos | D40: 31 | E40: =SUM(B_2020!AI7:AI74) -> 2.6906539 | F40: =SUM(B2_2020!AI7:AI74) -> 4.6521318 | G40: =SUMPRODUCT(Dados_2020!$Q$7:$Q$74,B_2020!AI7:AI74) -> 12.641562 | H40: =SUMPRODUCT(Dados_2020!$Q$7:$Q$74,B2_2020!AI7:AI74) -> 27.735279 | I40: =SUMPRODUCT(Dados_2020!$R$7:$R$74,B_2020!AI7:AI74) -> 0.49018065 | J40: =SUMPRODUCT(Dados_2020!$R$7:$R$74,B2_2020!AI7:AI74) -> 0.85590454 | K40: =SUMPRODUCT(Dados_2020!$S$7:$S$74,B_2020!AI7:AI74) -> 0.92699461 | L40: =SUMPRODUCT(Dados_2020!$S$7:$S$74,B2_2020!AI7:AI74) -> 1.8810959 | M40: =RANK(H40,$H$10:$H$77,0) -> 39 | N40: =RANK(J40,$J$10:$J$77,0) -> 22
B41: 2800 | C41: Fabricação de máquinas e equipamentos mecânicos | D41: 32 | E41: =SUM(B_2020!AJ7:AJ74) -> 2.831818 | F41: =SUM(B2_2020!AJ7:AJ74) -> 5.2018016 | G41: =SUMPRODUCT(Dados_2020!$Q$7:$Q$74,B_2020!AJ7:AJ74) -> 15.911857 | H41: =SUMPRODUCT(Dados_2020!$Q$7:$Q$74,B2_2020!AJ7:AJ74) -> 34.149055 | I41: =SUMPRODUCT(Dados_2020!$R$7:$R$74,B_2020!AJ7:AJ74) -> 0.5796681 | J41: =SUMPRODUCT(Dados_2020!$R$7:$R$74,B2_2020!AJ7:AJ74) -> 1.0215592 | K41: =SUMPRODUCT(Dados_2020!$S$7:$S$74,B_2020!AJ7:AJ74) -> 1.1200544 | L41: =SUMPRODUCT(Dados_2020!$S$7:$S$74,B2_2020!AJ7:AJ74) -> 2.2728608 | M41: =RANK(H41,$H$10:$H$77,0) -> 19 | N41: =RANK(J41,$J$10:$J$77,0) -> 11
B42: 2991 | C42: Fabricação de automóveis, caminhões e ônibus, exceto peças | D42: 33 | E42: =SUM(B_2020!AK7:AK74) -> 2.3467077 | F42: =SUM(B2_2020!AK7:AK74) -> 3.5931437 | G42: =SUMPRODUCT(Dados_2020!$Q$7:$Q$74,B_2020!AK7:AK74) -> 7.675739 | H42: =SUMPRODUCT(Dados_2020!$Q$7:$Q$74,B2_2020!AK7:AK74) -> 17.267156 | I42: =SUMPRODUCT(Dados_2020!$R$7:$R$74,B_2020!AK7:AK74) -> 0.37209764 | J42: =SUMPRODUCT(Dados_2020!$R$7:$R$74,B2_2020!AK7:AK74) -> 0.60449966 | K42: =SUMPRODUCT(Dados_2020!$S$7:$S$74,B_2020!AK7:AK74) -> 0.58906576 | L42: =SUMPRODUCT(Dados_2020!$S$7:$S$74,B2_2020!AK7:AK74) -> 1.1953566 | M42: =RANK(H42,$H$10:$H$77,0) -> 64 | N42: =RANK(J42,$J$10:$J$77,0) -> 56
B43: 2992 | C43: Fabricação de peças e acessórios para veículos automotores | D43: 34 | E43: =SUM(B_2020!AL7:AL74) -> 2.1632818 | F43: =SUM(B2_2020!AL7:AL74) -> 3.6137854 | G43: =SUMPRODUCT(Dados_2020!$Q$7:$Q$74,B_2020!AL7:AL74) -> 8.5029128 | H43: =SUMPRODUCT(Dados_2020!$Q$7:$Q$74,B2_2020!AL7:AL74) -> 19.664645 | I43: =SUMPRODUCT(Dados_2020!$R$7:$R$74,B_2020!AL7:AL74) -> 0.39729839 | J43: =SUMPRODUCT(Dados_2020!$R$7:$R$74,B2_2020!AL7:AL74) -> 0.66774947 | K43: =SUMPRODUCT(Dados_2020!$S$7:$S$74,B_2020!AL7:AL74) -> 0.6855081 | L43: =SUMPRODUCT(Dados_2020!$S$7:$S$74,B2_2020!AL7:AL74) -> 1.3910614 | M43: =RANK(H43,$H$10:$H$77,0) -> 57 | N43: =RANK(J43,$J$10:$J$77,0) -> 51
B44: 3000 | C44: Fabricação de outros equipamentos de transporte, exceto veículos automotores | D44: 35 | E44: =SUM(B_2020!AM7:AM74) -> 1.9263207 | F44: =SUM(B2_2020!AM7:AM74) -> 3.1527797 | G44: =SUMPRODUCT(Dados_2020!$Q$7:$Q$74,B_2020!AM7:AM74) -> 7.0583909 | H44: =SUMPRODUCT(Dados_2020!$Q$7:$Q$74,B2_2020!AM7:AM74) -> 16.496083 | I44: =SUMPRODUCT(Dados_2020!$R$7:$R$74,B_2020!AM7:AM74) -> 0.35001321 | J44: =SUMPRODUCT(Dados_2020!$R$7:$R$74,B2_2020!AM7:AM74) -> 0.57869044 | K44: =SUMPRODUCT(Dados_2020!$S$7:$S$74,B_2020!AM7:AM74) -> 0.57962459 | L44: =SUMPRODUCT(Dados_2020!$S$7:$S$74,B2_2020!AM7:AM74) -> 1.1761982 | M44: =RANK(H44,$H$10:$H$77,0) -> 65 | N44: =RANK(J44,$J$10:$J$77,0) -> 58
B45: 3180 | C45: Fabricação de móveis e de produtos de indústrias diversas | D45: 36 | E45: =SUM(B_2020!AN7:AN74) -> 2.2308641 | F45: =SUM(B2_2020!AN7:AN74) -> 4.3092215 | G45: =SUMPRODUCT(Dados_2020!$Q$7:$Q$74,B_2020!AN7:AN74) -> 17.068958 | H45: =SUMPRODUCT(Dados_2020!$Q$7:$Q$74,B2_2020!AN7:AN74) -> 33.062071 | I45: =SUMPRODUCT(Dados_2020!$R$7:$R$74,B_2020!AN7:AN74) -> 0.44389751 | J45: =SUMPRODUCT(Dados_2020!$R$7:$R$74,B2_2020!AN7:AN74) -> 0.83141394 | K45: =SUMPRODUCT(Dados_2020!$S$7:$S$74,B_2020!AN7:AN74) -> 0.98223181 | L45: =SUMPRODUCT(Dados_2020!$S$7:$S$74,B2_2020!AN7:AN74) -> 1.9931855 | M45: =RANK(H45,$H$10:$H$77,0) -> 24 | N45: =RANK(J45,$J$10:$J$77,0) -> 27
B46: 3300 | C46: Manutenção, reparação e instalação de máquinas e equipamentos | D46: 37 | E46: =SUM(B_2020!AO7:AO74) -> 1.8603163 | F46: =SUM(B2_2020!AO7:AO74) -> 3.344548 | G46: =SUMPRODUCT(Dados_2020!$Q$7:$Q$74,B_2020!AO7:AO74) -> 10.597522 | H46: =SUMPRODUCT(Dados_2020!$Q$7:$Q$74,B2_2020!AO7:AO74) -> 22.018794 | I46: =SUMPRODUCT(Dados_2020!$R$7:$R$74,B_2020!AO7:AO74) -> 0.32691079 | J46: =SUMPRODUCT(Dados_2020!$R$7:$R$74,B2_2020!AO7:AO74) -> 0.60365058 | K46: =SUMPRODUCT(Dados_2020!$S$7:$S$74,B_2020!AO7:AO74) -> 0.70144799 | L46: =SUMPRODUCT(Dados_2020!$S$7:$S$74,B2_2020!AO7:AO74) -> 1.4234073 | M46: =RANK(H46,$H$10:$H$77,0) -> 53 | N46: =RANK(J46,$J$10:$J$77,0) -> 57
B47: 3500 | C47: Energia elétrica, gás natural e outras utilidades | D47: 38 | E47: =SUM(B_2020!AP7:AP74) -> 1.9066197 | F47: =SUM(B2_2020!AP7:AP74) -> 3.6263944 | G47: =SUMPRODUCT(Dados_2020!$Q$7:$Q$74,B_2020!AP7:AP74) -> 3.1405933 | H47: =SUMPRODUCT(Dados_2020!$Q$7:$Q$74,B2_2020!AP7:AP74) -> 16.374387 | I47: =SUMPRODUCT(Dados_2020!$R$7:$R$74,B_2020!AP7:AP74) -> 0.16701189 | J47: =SUMPRODUCT(Dados_2020!$R$7:$R$74,B2_2020!AP7:AP74) -> 0.48766945 | K47: =SUMPRODUCT(Dados_2020!$S$7:$S$74,B_2020!AP7:AP74) -> 0.81276567 | L47: =SUMPRODUCT(Dados_2020!$S$7:$S$74,B2_2020!AP7:AP74) -> 1.6492978 | M47: =RANK(H47,$H$10:$H$77,0) -> 66 | N47: =RANK(J47,$J$10:$J$77,0) -> 64
B48: 3680 | C48: Água, esgoto e gestão de resíduos | D48: 39 | E48: =SUM(B_2020!AQ7:AQ74) -> 1.6252593 | F48: =SUM(B2_2020!AQ7:AQ74) -> 3.4941837 | G48: =SUMPRODUCT(Dados_2020!$Q$7:$Q$74,B_2020!AQ7:AQ74) -> 9.6012039 | H48: =SUMPRODUCT(Dados_2020!$Q$7:$Q$74,B2_2020!AQ7:AQ74) -> 23.982716 | I48: =SUMPRODUCT(Dados_2020!$R$7:$R$74,B_2020!AQ7:AQ74) -> 0.36163653 | J48: =SUMPRODUCT(Dados_2020!$R$7:$R$74,B2_2020!AQ7:AQ74) -> 0.71010353 | K48: =SUMPRODUCT(Dados_2020!$S$7:$S$74,B_2020!AQ7:AQ74) -> 0.88325384 | L48: =SUMPRODUCT(Dados_2020!$S$7:$S$74,B2_2020!AQ7:AQ74) -> 1.7923353 | M48: =RANK(H48,$H$10:$H$77,0) -> 46 | N48: =RANK(J48,$J$10:$J$77,0) -> 44
B49: 4180 | C49: Construção | D49: 40 | E49: =SUM(B_2020!AR7:AR74) -> 1.9702852 | F49: =SUM(B2_2020!AR7:AR74) -> 3.7119541 | G49: =SUMPRODUCT(Dados_2020!$Q$7:$Q$74,B_2020!AR7:AR74) -> 17.529045 | H49: =SUMPRODUCT(Dados_2020!$Q$7:$Q$74,B2_2020!AR7:AR74) -> 30.931316 | I49: =SUMPRODUCT(Dados_2020!$R$7:$R$74,B_2020!AR7:AR74) -> 0.35968597 | J49: =SUMPRODUCT(Dados_2020!$R$7:$R$74,B2_2020!AR7:AR74) -> 0.68442577 | K49: =SUMPRODUCT(Dados_2020!$S$7:$S$74,B_2020!AR7:AR74) -> 0.82311286 | L49: =SUMPRODUCT(Dados_2020!$S$7:$S$74,B2_2020!AR7:AR74) -> 1.6702947 | M49: =RANK(H49,$H$10:$H$77,0) -> 28 | N49: =RANK(J49,$J$10:$J$77,0) -> 48
B50: 4500 | C50: Comércio e reparação de veículos automotores e motocicletas | D50: 41 | E50: =SUM(B_2020!AS7:AS74) -> 1.6560271 | F50: =SUM(B2_2020!AS7:AS74) -> 3.4113459 | G50: =SUMPRODUCT(Dados_2020!$Q$7:$Q$74,B_2020!AS7:AS74) -> 19.261266 | H50: =SUMPRODUCT(Dados_2020!$Q$7:$Q$74,B2_2020!AS7:AS74) -> 32.768574 | I50: =SUMPRODUCT(Dados_2020!$R$7:$R$74,B_2020!AS7:AS74) -> 0.40681302 | J50: =SUMPRODUCT(Dados_2020!$R$7:$R$74,B2_2020!AS7:AS74) -> 0.73409787 | K50: =SUMPRODUCT(Dados_2020!$S$7:$S$74,B_2020!AS7:AS74) -> 0.82956378 | L50: =SUMPRODUCT(Dados_2020!$S$7:$S$74,B2_2020!AS7:AS74) -> 1.6833852 | M50: =RANK(H50,$H$10:$H$77,0) -> 26 | N50: =RANK(J50,$J$10:$J$77,0) -> 40
B51: 4680 | C51: Comércio por atacado e a varejo, exceto veículos automotores | D51: 42 | E51: =SUM(B_2020!AT7:AT74) -> 1.8674535 | F51: =SUM(B2_2020!AT7:AT74) -> 4.0511677 | G51: =SUMPRODUCT(Dados_2020!$Q$7:$Q$74,B_2020!AT7:AT74) -> 18.332054 | H51: =SUMPRODUCT(Dados_2020!$Q$7:$Q$74,B2_2020!AT7:AT74) -> 35.135896 | I51: =SUMPRODUCT(Dados_2020!$R$7:$R$74,B_2020!AT7:AT74) -> 0.4784103 | J51: =SUMPRODUCT(Dados_2020!$R$7:$R$74,B2_2020!AT7:AT74) -> 0.88557085 | K51: =SUMPRODUCT(Dados_2020!$S$7:$S$74,B_2020!AT7:AT74) -> 1.0320235 | L51: =SUMPRODUCT(Dados_2020!$S$7:$S$74,B2_2020!AT7:AT74) -> 2.0942248 | M51: =RANK(H51,$H$10:$H$77,0) -> 17 | N51: =RANK(J51,$J$10:$J$77,0) -> 20
B52: 4900 | C52: Transporte terrestre | D52: 43 | E52: =SUM(B_2020!AU7:AU74) -> 2.1723677 | F52: =SUM(B2_2020!AU7:AU74) -> 3.9405311 | G52: =SUMPRODUCT(Dados_2020!$Q$7:$Q$74,B_2020!AU7:AU74) -> 15.423226 | H52: =SUMPRODUCT(Dados_2020!$Q$7:$Q$74,B2_2020!AU7:AU74) -> 29.029374 | I52: =SUMPRODUCT(Dados_2020!$R$7:$R$74,B_2020!AU7:AU74) -> 0.40203973 | J52: =SUMPRODUCT(Dados_2020!$R$7:$R$74,B2_2020!AU7:AU74) -> 0.73171951 | K52: =SUMPRODUCT(Dados_2020!$S$7:$S$74,B_2020!AU7:AU74) -> 0.83563416 | L52: =SUMPRODUCT(Dados_2020!$S$7:$S$74,B2_2020!AU7:AU74) -> 1.6957035 | M52: =RANK(H52,$H$10:$H$77,0) -> 33 | N52: =RANK(J52,$J$10:$J$77,0) -> 41
B53: 5000 | C53: Transporte aquaviário | D53: 44 | E53: =SUM(B_2020!AV7:AV74) -> 1.8481691 | F53: =SUM(B2_2020!AV7:AV74) -> 3.5599798 | G53: =SUMPRODUCT(Dados_2020!$Q$7:$Q$74,B_2020!AV7:AV74) -> 5.7774603 | H53: =SUMPRODUCT(Dados_2020!$Q$7:$Q$74,B2_2020!AV7:AV74) -> 18.94997 | I53: =SUMPRODUCT(Dados_2020!$R$7:$R$74,B_2020!AV7:AV74) -> 0.34628398 | J53: =SUMPRODUCT(Dados_2020!$R$7:$R$74,B2_2020!AV7:AV74) -> 0.66545661 | K53: =SUMPRODUCT(Dados_2020!$S$7:$S$74,B_2020!AV7:AV74) -> 0.80900185 | L53: =SUMPRODUCT(Dados_2020!$S$7:$S$74,B2_2020!AV7:AV74) -> 1.6416601 | M53: =RANK(H53,$H$10:$H$77,0) -> 59 | N53: =RANK(J53,$J$10:$J$77,0) -> 52
B54: 5100 | C54: Transporte aéreo | D54: 45 | E54: =SUM(B_2020!AW7:AW74) -> 1.9796319 | F54: =SUM(B2_2020!AW7:AW74) -> 3.3342912 | G54: =SUMPRODUCT(Dados_2020!$Q$7:$Q$74,B_2020!AW7:AW74) -> 7.0665524 | H54: =SUMPRODUCT(Dados_2020!$Q$7:$Q$74,B2_2020!AW7:AW74) -> 17.490756 | I54: =SUMPRODUCT(Dados_2020!$R$7:$R$74,B_2020!AW7:AW74) -> 0.43267519 | J54: =SUMPRODUCT(Dados_2020!$R$7:$R$74,B2_2020!AW7:AW74) -> 0.68525579 | K54: =SUMPRODUCT(Dados_2020!$S$7:$S$74,B_2020!AW7:AW74) -> 0.64021208 | L54: =SUMPRODUCT(Dados_2020!$S$7:$S$74,B2_2020!AW7:AW74) -> 1.2991449 | M54: =RANK(H54,$H$10:$H$77,0) -> 61 | N54: =RANK(J54,$J$10:$J$77,0) -> 47
B55: 5280 | C55: Armazenamento, atividades auxiliares dos transportes e correio | D55: 46 | E55: =SUM(B_2020!AX7:AX74) -> 1.6941613 | F55: =SUM(B2_2020!AX7:AX74) -> 3.6136572 | G55: =SUMPRODUCT(Dados_2020!$Q$7:$Q$74,B_2020!AX7:AX74) -> 10.305029 | H55: =SUMPRODUCT(Dados_2020!$Q$7:$Q$74,B2_2020!AX7:AX74) -> 25.075691 | I55: =SUMPRODUCT(Dados_2020!$R$7:$R$74,B_2020!AX7:AX74) -> 0.44384513 | J55: =SUMPRODUCT(Dados_2020!$R$7:$R$74,B2_2020!AX7:AX74) -> 0.80174133 | K55: =SUMPRODUCT(Dados_2020!$S$7:$S$74,B_2020!AX7:AX74) -> 0.90715389 | L55: =SUMPRODUCT(Dados_2020!$S$7:$S$74,B2_2020!AX7:AX74) -> 1.8408342 | M55: =RANK(H55,$H$10:$H$77,0) -> 45 | N55: =RANK(J55,$J$10:$J$77,0) -> 29
B56: 5500 | C56: Alojamento | D56: 47 | E56: =SUM(B_2020!AY7:AY74) -> 1.7587181 | F56: =SUM(B2_2020!AY7:AY74) -> 3.5912897 | G56: =SUMPRODUCT(Dados_2020!$Q$7:$Q$74,B_2020!AY7:AY74) -> 22.591811 | H56: =SUMPRODUCT(Dados_2020!$Q$7:$Q$74,B2_2020!AY7:AY74) -> 36.693585 | I56: =SUMPRODUCT(Dados_2020!$R$7:$R$74,B_2020!AY7:AY74) -> 0.56654464 | J56: =SUMPRODUCT(Dados_2020!$R$7:$R$74,B2_2020!AY7:AY74) -> 0.90823354 | K56: =SUMPRODUCT(Dados_2020!$S$7:$S$74,B_2020!AY7:AY74) -> 0.86607347 | L56: =SUMPRODUCT(Dados_2020!$S$7:$S$74,B2_2020!AY7:AY74) -> 1.7574722 | M56: =RANK(H56,$H$10:$H$77,0) -> 12 | N56: =RANK(J56,$J$10:$J$77,0) -> 18
B57: 5600 | C57: Alimentação | D57: 48 | E57: =SUM(B_2020!AZ7:AZ74) -> 1.9561106 | F57: =SUM(B2_2020!AZ7:AZ74) -> 3.7089487 | G57: =SUMPRODUCT(Dados_2020!$Q$7:$Q$74,B_2020!AZ7:AZ74) -> 25.421133 | H57: =SUMPRODUCT(Dados_2020!$Q$7:$Q$74,B2_2020!AZ7:AZ74) -> 38.909352 | I57: =SUMPRODUCT(Dados_2020!$R$7:$R$74,B_2020!AZ7:AZ74) -> 0.36317649 | J57: =SUMPRODUCT(Dados_2020!$R$7:$R$74,B2_2020!AZ7:AZ74) -> 0.68999881 | K57: =SUMPRODUCT(Dados_2020!$S$7:$S$74,B_2020!AZ7:AZ74) -> 0.82839141 | L57: =SUMPRODUCT(Dados_2020!$S$7:$S$74,B2_2020!AZ7:AZ74) -> 1.6810062 | M57: =RANK(H57,$H$10:$H$77,0) -> 9 | N57: =RANK(J57,$J$10:$J$77,0) -> 46
B58: 5800 | C58: Edição e edição integrada à impressão | D58: 49 | E58: =SUM(B_2020!BA7:BA74) -> 2.3996257 | F58: =SUM(B2_2020!BA7:BA74) -> 4.9717008 | G58: =SUMPRODUCT(Dados_2020!$Q$7:$Q$74,B_2020!BA7:BA74) -> 19.410168 | H58: =SUMPRODUCT(Dados_2020!$Q$7:$Q$74,B2_2020!BA7:BA74) -> 39.202476 | I58: =SUMPRODUCT(Dados_2020!$R$7:$R$74,B_2020!BA7:BA74) -> 0.69662815 | J58: =SUMPRODUCT(Dados_2020!$R$7:$R$74,B2_2020!BA7:BA74) -> 1.1761999 | K58: =SUMPRODUCT(Dados_2020!$S$7:$S$74,B_2020!BA7:BA74) -> 1.2155629 | L58: =SUMPRODUCT(Dados_2020!$S$7:$S$74,B2_2020!BA7:BA74) -> 2.4666705 | M58: =RANK(H58,$H$10:$H$77,0) -> 8 | N58: =RANK(J58,$J$10:$J$77,0) -> 3
B59: 5980 | C59: Atividades de televisão, rádio, cinema e gravação/edição de som e imagem | D59: 50 | E59: =SUM(B_2020!BB7:BB74) -> 2.345608 | F59: =SUM(B2_2020!BB7:BB74) -> 4.699488 | G59: =SUMPRODUCT(Dados_2020!$Q$7:$Q$74,B_2020!BB7:BB74) -> 15.339853 | H59: =SUMPRODUCT(Dados_2020!$Q$7:$Q$74,B2_2020!BB7:BB74) -> 33.453133 | I59: =SUMPRODUCT(Dados_2020!$R$7:$R$74,B_2020!BB7:BB74) -> 0.64983361 | J59: =SUMPRODUCT(Dados_2020!$R$7:$R$74,B2_2020!BB7:BB74) -> 1.0887221 | K59: =SUMPRODUCT(Dados_2020!$S$7:$S$74,B_2020!BB7:BB74) -> 1.1124439 | L59: =SUMPRODUCT(Dados_2020!$S$7:$S$74,B2_2020!BB7:BB74) -> 2.2574171 | M59: =RANK(H59,$H$10:$H$77,0) -> 21 | N59: =RANK(J59,$J$10:$J$77,0) -> 6
B60: 6100 | C60: Telecomunicações | D60: 51 | E60: =SUM(B_2020!BC7:BC74) -> 2.3546532 | F60: =SUM(B2_2020!BC7:BC74) -> 4.9047967 | G60: =SUMPRODUCT(Dados_2020!$Q$7:$Q$74,B_2020!BC7:BC74) -> 13.150267 | H60: =SUMPRODUCT(Dados_2020!$Q$7:$Q$74,B2_2020!BC7:BC74) -> 32.773809 | I60: =SUMPRODUCT(Dados_2020!$R$7:$R$74,B_2020!BC7:BC74) -> 0.46841118 | J60: =SUMPRODUCT(Dados_2020!$R$7:$R$74,B2_2020!BC7:BC74) -> 0.94389366 | K60: =SUMPRODUCT(Dados_2020!$S$7:$S$74,B_2020!BC7:BC74) -> 1.205198 | L60: =SUMPRODUCT(Dados_2020!$S$7:$S$74,B2_2020!BC7:BC74) -> 2.4456377 | M60: =RANK(H60,$H$10:$H$77,0) -> 25 | N60: =RANK(J60,$J$10:$J$77,0) -> 14
B61: 6280 | C61: Desenvolvimento de sistemas e outros serviços de informação | D61: 52 | E61: =SUM(B_2020!BD7:BD74) -> 1.5551563 | F61: =SUM(B2_2020!BD7:BD74) -> 3.5407512 | G61: =SUMPRODUCT(Dados_2020!$Q$7:$Q$74,B_2020!BD7:BD74) -> 8.0108188 | H61: =SUMPRODUCT(Dados_2020!$Q$7:$Q$74,B2_2020!BD7:BD74) -> 23.290118 | I61: =SUMPRODUCT(Dados_2020!$R$7:$R$74,B_2020!BD7:BD74) -> 0.46181008 | J61: =SUMPRODUCT(Dados_2020!$R$7:$R$74,B2_2020!BD7:BD74) -> 0.83203065 | K61: =SUMPRODUCT(Dados_2020!$S$7:$S$74,B_2020!BD7:BD74) -> 0.93839228 | L61: =SUMPRODUCT(Dados_2020!$S$7:$S$74,B2_2020!BD7:BD74) -> 1.9042245 | M61: =RANK(H61,$H$10:$H$77,0) -> 50 | N61: =RANK(J61,$J$10:$J$77,0) -> 26
B62: 6480 | C62: Intermediação financeira, seguros e previdência complementar | D62: 53 | E62: =SUM(B_2020!BE7:BE74) -> 1.4892529 | F62: =SUM(B2_2020!BE7:BE74) -> 3.4687606 | G62: =SUMPRODUCT(Dados_2020!$Q$7:$Q$74,B_2020!BE7:BE74) -> 4.9710698 | H62: =SUMPRODUCT(Dados_2020!$Q$7:$Q$74,B2_2020!BE7:BE74) -> 20.203527 | I62: =SUMPRODUCT(Dados_2020!$R$7:$R$74,B_2020!BE7:BE74) -> 0.39008412 | J62: =SUMPRODUCT(Dados_2020!$R$7:$R$74,B2_2020!BE7:BE74) -> 0.75916971 | K62: =SUMPRODUCT(Dados_2020!$S$7:$S$74,B_2020!BE7:BE74) -> 0.93551545 | L62: =SUMPRODUCT(Dados_2020!$S$7:$S$74,B2_2020!BE7:BE74) -> 1.8983867 | M62: =RANK(H62,$H$10:$H$77,0) -> 56 | N62: =RANK(J62,$J$10:$J$77,0) -> 35
B63: 6800 | C63: Atividades imobiliárias | D63: 54 | E63: =SUM(B_2020!BF7:BF74) -> 1.111802 | F63: =SUM(B2_2020!BF7:BF74) -> 3.1912984 | G63: =SUMPRODUCT(Dados_2020!$Q$7:$Q$74,B_2020!BF7:BF74) -> 1.2678032 | H63: =SUMPRODUCT(Dados_2020!$Q$7:$Q$74,B2_2020!BF7:BF74) -> 17.269681 | I63: =SUMPRODUCT(Dados_2020!$R$7:$R$74,B_2020!BF7:BF74) -> 0.038384238 | J63: =SUMPRODUCT(Dados_2020!$R$7:$R$74,B2_2020!BF7:BF74) -> 0.42611305 | K63: =SUMPRODUCT(Dados_2020!$S$7:$S$74,B_2020!BF7:BF74) -> 0.98277015 | L63: =SUMPRODUCT(Dados_2020!$S$7:$S$74,B2_2020!BF7:BF74) -> 1.9942779 | M63: =RANK(H63,$H$10:$H$77,0) -> 63 | N63: =RANK(J63,$J$10:$J$77,0) -> 68
B64: 6980 | C64: Atividades jurídicas, contábeis, consultoria e sedes de empresas | D64: 55 | E64: =SUM(B_2020!BG7:BG74) -> 1.5263886 | F64: =SUM(B2_2020!BG7:BG74) -> 3.5887327 | G64: =SUMPRODUCT(Dados_2020!$Q$7:$Q$74,B_2020!BG7:BG74) -> 11.963946 | H64: =SUMPRODUCT(Dados_2020!$Q$7:$Q$74,B2_2020!BG7:BG74) -> 27.833836 | I64: =SUMPRODUCT(Dados_2020!$R$7:$R$74,B_2020!BG7:BG74) -> 0.41379938 | J64: =SUMPRODUCT(Dados_2020!$R$7:$R$74,B2_2020!BG7:BG74) -> 0.79833009 | K64: =SUMPRODUCT(Dados_2020!$S$7:$S$74,B_2020!BG7:BG74) -> 0.97466397 | L64: =SUMPRODUCT(Dados_2020!$S$7:$S$74,B2_2020!BG7:BG74) -> 1.9778285 | M64: =RANK(H64,$H$10:$H$77,0) -> 38 | N64: =RANK(J64,$J$10:$J$77,0) -> 30
B65: 7180 | C65: Serviços de arquitetura, engenharia, testes/análises técnicas e P & D | D65: 56 | E65: =SUM(B_2020!BH7:BH74) -> 1.5160197 | F65: =SUM(B2_2020!BH7:BH74) -> 3.3963962 | G65: =SUMPRODUCT(Dados_2020!$Q$7:$Q$74,B_2020!BH7:BH74) -> 12.563234 | H65: =SUMPRODUCT(Dados_2020!$Q$7:$Q$74,B2_2020!BH7:BH74) -> 27.03287 | I65: =SUMPRODUCT(Dados_2020!$R$7:$R$74,B_2020!BH7:BH74) -> 0.40703425 | J65: =SUMPRODUCT(Dados_2020!$R$7:$R$74,B2_2020!BH7:BH74) -> 0.75763652 | K65: =SUMPRODUCT(Dados_2020!$S$7:$S$74,B_2020!BH7:BH74) -> 0.88866607 | L65: =SUMPRODUCT(Dados_2020!$S$7:$S$74,B2_2020!BH7:BH74) -> 1.803318 | M65: =RANK(H65,$H$10:$H$77,0) -> 42 | N65: =RANK(J65,$J$10:$J$77,0) -> 37
B66: 7380 | C66: Outras atividades profissionais, científicas e técnicas | D66: 57 | E66: =SUM(B_2020!BI7:BI74) -> 2.1288531 | F66: =SUM(B2_2020!BI7:BI74) -> 4.1467392 | G66: =SUMPRODUCT(Dados_2020!$Q$7:$Q$74,B_2020!BI7:BI74) -> 13.648135 | H66: =SUMPRODUCT(Dados_2020!$Q$7:$Q$74,B2_2020!BI7:BI74) -> 29.175917 | I66: =SUMPRODUCT(Dados_2020!$R$7:$R$74,B_2020!BI7:BI74) -> 0.46573821 | J66: =SUMPRODUCT(Dados_2020!$R$7:$R$74,B2_2020!BI7:BI74) -> 0.84197959 | K66: =SUMPRODUCT(Dados_2020!$S$7:$S$74,B_2020!BI7:BI74) -> 0.95365313 | L66: =SUMPRODUCT(Dados_2020!$S$7:$S$74,B2_2020!BI7:BI74) -> 1.9351924 | M66: =RANK(H66,$H$10:$H$77,0) -> 31 | N66: =RANK(J66,$J$10:$J$77,0) -> 25
B67: 7700 | C67: Aluguéis não-imobiliários e gestão de ativos de propriedade intelectual | D67: 58 | E67: =SUM(B_2020!BJ7:BJ74) -> 1.5077363 | F67: =SUM(B2_2020!BJ7:BJ74) -> 3.4290048 | G67: =SUMPRODUCT(Dados_2020!$Q$7:$Q$74,B_2020!BJ7:BJ74) -> 8.0021495 | H67: =SUMPRODUCT(Dados_2020!$Q$7:$Q$74,B2_2020!BJ7:BJ74) -> 22.786452 | I67: =SUMPRODUCT(Dados_2020!$R$7:$R$74,B_2020!BJ7:BJ74) -> 0.31801514 | J67: =SUMPRODUCT(Dados_2020!$R$7:$R$74,B2_2020!BJ7:BJ74) -> 0.67624185 | K67: =SUMPRODUCT(Dados_2020!$S$7:$S$74,B_2020!BJ7:BJ74) -> 0.90799161 | L67: =SUMPRODUCT(Dados_2020!$S$7:$S$74,B2_2020!BJ7:BJ74) -> 1.8425342 | M67: =RANK(H67,$H$10:$H$77,0) -> 51 | N67: =RANK(J67,$J$10:$J$77,0) -> 50
B68: 7880 | C68: Outras atividades administrativas e serviços complementares | D68: 59 | E68: =SUM(B_2020!BK7:BK74) -> 1.5191788 | F68: =SUM(B2_2020!BK7:BK74) -> 3.5031414 | G68: =SUMPRODUCT(Dados_2020!$Q$7:$Q$74,B_2020!BK7:BK74) -> 18.853162 | H68: =SUMPRODUCT(Dados_2020!$Q$7:$Q$74,B2_2020!BK7:BK74) -> 34.1199 | I68: =SUMPRODUCT(Dados_2020!$R$7:$R$74,B_2020!BK7:BK74) -> 0.56785209 | J68: =SUMPRODUCT(Dados_2020!$R$7:$R$74,B2_2020!BK7:BK74) -> 0.93776833 | K68: =SUMPRODUCT(Dados_2020!$S$7:$S$74,B_2020!BK7:BK74) -> 0.93762089 | L68: =SUMPRODUCT(Dados_2020!$S$7:$S$74,B2_2020!BK7:BK74) -> 1.9026591 | M68: =RANK(H68,$H$10:$H$77,0) -> 20 | N68: =RANK(J68,$J$10:$J$77,0) -> 16
B69: 8000 | C69: Atividades de vigilância, segurança e investigação | D69: 60 | E69: =SUM(B_2020!BL7:BL74) -> 1.3349369 | F69: =SUM(B2_2020!BL7:BL74) -> 3.39275 | G69: =SUMPRODUCT(Dados_2020!$Q$7:$Q$74,B_2020!BL7:BL74) -> 19.436377 | H69: =SUMPRODUCT(Dados_2020!$Q$7:$Q$74,B2_2020!BL7:BL74) -> 35.2714 | I69: =SUMPRODUCT(Dados_2020!$R$7:$R$74,B_2020!BL7:BL74) -> 0.7693128 | J69: =SUMPRODUCT(Dados_2020!$R$7:$R$74,B2_2020!BL7:BL74) -> 1.1529987 | K69: =SUMPRODUCT(Dados_2020!$S$7:$S$74,B_2020!BL7:BL74) -> 0.97252262 | L69: =SUMPRODUCT(Dados_2020!$S$7:$S$74,B2_2020!BL7:BL74) -> 1.9734832 | M69: =RANK(H69,$H$10:$H$77,0) -> 16 | N69: =RANK(J69,$J$10:$J$77,0) -> 4
B70: 8400 | C70: Administração pública, defesa e seguridade social | D70: 61 | E70: =SUM(B_2020!BM7:BM74) -> 1.3841553 | F70: =SUM(B2_2020!BM7:BM74) -> 3.3746277 | G70: =SUMPRODUCT(Dados_2020!$Q$7:$Q$74,B_2020!BM7:BM74) -> 8.1582389 | H70: =SUMPRODUCT(Dados_2020!$Q$7:$Q$74,B2_2020!BM7:BM74) -> 23.475071 | I70: =SUMPRODUCT(Dados_2020!$R$7:$R$74,B_2020!BM7:BM74) -> 0.72023456 | J70: =SUMPRODUCT(Dados_2020!$R$7:$R$74,B2_2020!BM7:BM74) -> 1.0913646 | K70: =SUMPRODUCT(Dados_2020!$S$7:$S$74,B_2020!BM7:BM74) -> 0.94069739 | L70: =SUMPRODUCT(Dados_2020!$S$7:$S$74,B2_2020!BM7:BM74) -> 1.9089021 | M70: =RANK(H70,$H$10:$H$77,0) -> 49 | N70: =RANK(J70,$J$10:$J$77,0) -> 5
B71: 8591 | C71: Educação pública | D71: 62 | E71: =SUM(B_2020!BN7:BN74) -> 1.2168981 | F71: =SUM(B2_2020!BN7:BN74) -> 3.2457673 | G71: =SUMPRODUCT(Dados_2020!$Q$7:$Q$74,B_2020!BN7:BN74) -> 13.541403 | H71: =SUMPRODUCT(Dados_2020!$Q$7:$Q$74,B2_2020!BN7:BN74) -> 29.153701 | I71: =SUMPRODUCT(Dados_2020!$R$7:$R$74,B_2020!BN7:BN74) -> 0.8816848 | J71: =SUMPRODUCT(Dados_2020!$R$7:$R$74,B2_2020!BN7:BN74) -> 1.259974 | K71: =SUMPRODUCT(Dados_2020!$S$7:$S$74,B_2020!BN7:BN74) -> 0.95884372 | L71: =SUMPRODUCT(Dados_2020!$S$7:$S$74,B2_2020!BN7:BN74) -> 1.9457254 | M71: =RANK(H71,$H$10:$H$77,0) -> 32 | N71: =RANK(J71,$J$10:$J$77,0) -> 2
B72: 8592 | C72: Educação privada | D72: 63 | E72: =SUM(B_2020!BO7:BO74) -> 1.4585362 | F72: =SUM(B2_2020!BO7:BO74) -> 3.4305067 | G72: =SUMPRODUCT(Dados_2020!$Q$7:$Q$74,B_2020!BO7:BO74) -> 21.764758 | H72: =SUMPRODUCT(Dados_2020!$Q$7:$Q$74,B2_2020!BO7:BO74) -> 36.939216 | I72: =SUMPRODUCT(Dados_2020!$R$7:$R$74,B_2020!BO7:BO74) -> 0.71679319 | J72: =SUMPRODUCT(Dados_2020!$R$7:$R$74,B2_2020!BO7:BO74) -> 1.0844734 | K72: =SUMPRODUCT(Dados_2020!$S$7:$S$74,B_2020!BO7:BO74) -> 0.93195339 | L72: =SUMPRODUCT(Dados_2020!$S$7:$S$74,B2_2020!BO7:BO74) -> 1.8911584 | M72: =RANK(H72,$H$10:$H$77,0) -> 10 | N72: =RANK(J72,$J$10:$J$77,0) -> 7
B73: 8691 | C73: Saúde pública | D73: 64 | E73: =SUM(B_2020!BP7:BP74) -> 1.5369732 | F73: =SUM(B2_2020!BP7:BP74) -> 3.3936325 | G73: =SUMPRODUCT(Dados_2020!$Q$7:$Q$74,B_2020!BP7:BP74) -> 14.363398 | H73: =SUMPRODUCT(Dados_2020!$Q$7:$Q$74,B2_2020!BP7:BP74) -> 28.650527 | I73: =SUMPRODUCT(Dados_2020!$R$7:$R$74,B_2020!BP7:BP74) -> 0.71386776 | J73: =SUMPRODUCT(Dados_2020!$R$7:$R$74,B2_2020!BP7:BP74) -> 1.0600479 | K73: =SUMPRODUCT(Dados_2020!$S$7:$S$74,B_2020!BP7:BP74) -> 0.87745729 | L73: =SUMPRODUCT(Dados_2020!$S$7:$S$74,B2_2020!BP7:BP74) -> 1.7805727 | M73: =RANK(H73,$H$10:$H$77,0) -> 36 | N73: =RANK(J73,$J$10:$J$77,0) -> 10
B74: 8692 | C74: Saúde privada | D74: 65 | E74: =SUM(B_2020!BQ7:BQ74) -> 1.5439863 | F74: =SUM(B2_2020!BQ7:BQ74) -> 3.3292794 | G74: =SUMPRODUCT(Dados_2020!$Q$7:$Q$74,B_2020!BQ7:BQ74) -> 15.522783 | H74: =SUMPRODUCT(Dados_2020!$Q$7:$Q$74,B2_2020!BQ7:BQ74) -> 29.260745 | I74: =SUMPRODUCT(Dados_2020!$R$7:$R$74,B_2020!BQ7:BQ74) -> 0.463145 | J74: =SUMPRODUCT(Dados_2020!$R$7:$R$74,B2_2020!BQ7:BQ74) -> 0.79601866 | K74: =SUMPRODUCT(Dados_2020!$S$7:$S$74,B_2020!BQ7:BQ74) -> 0.84372963 | L74: =SUMPRODUCT(Dados_2020!$S$7:$S$74,B2_2020!BQ7:BQ74) -> 1.7121311 | M74: =RANK(H74,$H$10:$H$77,0) -> 29 | N74: =RANK(J74,$J$10:$J$77,0) -> 31
B75: 9080 | C75: Atividades artísticas, criativas e de espetáculos | D75: 66 | E75: =SUM(B_2020!BR7:BR74) -> 1.6523678 | F75: =SUM(B2_2020!BR7:BR74) -> 3.5720532 | G75: =SUMPRODUCT(Dados_2020!$Q$7:$Q$74,B_2020!BR7:BR74) -> 28.499177 | H75: =SUMPRODUCT(Dados_2020!$Q$7:$Q$74,B2_2020!BR7:BR74) -> 43.271298 | I75: =SUMPRODUCT(Dados_2020!$R$7:$R$74,B_2020!BR7:BR74) -> 0.43208104 | J75: =SUMPRODUCT(Dados_2020!$R$7:$R$74,B2_2020!BR7:BR74) -> 0.79001259 | K75: =SUMPRODUCT(Dados_2020!$S$7:$S$74,B_2020!BR7:BR74) -> 0.90724348 | L75: =SUMPRODUCT(Dados_2020!$S$7:$S$74,B2_2020!BR7:BR74) -> 1.841016 | M75: =RANK(H75,$H$10:$H$77,0) -> 7 | N75: =RANK(J75,$J$10:$J$77,0) -> 32
B76: 9480 | C76: Organizações associativas e outros serviços pessoais | D76: 67 | E76: =SUM(B_2020!BS7:BS74) -> 1.7381878 | F76: =SUM(B2_2020!BS7:BS74) -> 3.5271322 | G76: =SUMPRODUCT(Dados_2020!$Q$7:$Q$74,B_2020!BS7:BS74) -> 29.98014 | H76: =SUMPRODUCT(Dados_2020!$Q$7:$Q$74,B2_2020!BS7:BS74) -> 43.746199 | I76: =SUMPRODUCT(Dados_2020!$R$7:$R$74,B_2020!BS7:BS74) -> 0.41873711 | J76: =SUMPRODUCT(Dados_2020!$R$7:$R$74,B2_2020!BS7:BS74) -> 0.75229156 | K76: =SUMPRODUCT(Dados_2020!$S$7:$S$74,B_2020!BS7:BS74) -> 0.84545523 | L76: =SUMPRODUCT(Dados_2020!$S$7:$S$74,B2_2020!BS7:BS74) -> 1.7156328 | M76: =RANK(H76,$H$10:$H$77,0) -> 6 | N76: =RANK(J76,$J$10:$J$77,0) -> 38
B77: 9700 | C77: Serviços domésticos | D77: 68 | E77: =SUM(B_2020!BT7:BT74) -> 1 | F77: =SUM(B2_2020!BT7:BT74) -> 3.115954 | G77: =SUMPRODUCT(Dados_2020!$Q$7:$Q$74,B_2020!BT7:BT74) -> 92.79428 | H77: =SUMPRODUCT(Dados_2020!$Q$7:$Q$74,B2_2020!BT7:BT74) -> 109.0767 | I77: =SUMPRODUCT(Dados_2020!$R$7:$R$74,B_2020!BT7:BT74) -> 1 | J77: =SUMPRODUCT(Dados_2020!$R$7:$R$74,B2_2020!BT7:BT74) -> 1.3945264 | K77: =SUMPRODUCT(Dados_2020!$S$7:$S$74,B_2020!BT7:BT74) -> 1 | L77: =SUMPRODUCT(Dados_2020!$S$7:$S$74,B2_2020!BT7:BT74) -> 2.0292414 | M77: =RANK(H77,$H$10:$H$77,0) -> 1 | N77: =RANK(J77,$J$10:$J$77,0) -> 1
B80: Ranking — geração de emprego (tipo II)
B81: # | C81: Atividades | E81: Multiplicador
B82: 1 | C82: =C77 -> Serviços domésticos | E82: =H77 -> 109.0767
B83: 2 | C83: =C23 -> Confecção de artefatos do vestuário e acessórios | E83: =H23 -> 50.72247
B84: 3 | C84: =C17 -> Abate e produtos de carne, inclusive os produtos do laticínio e da pesca | E84: =H17 -> 49.111508
B85: 4 | C85: =C11 -> Pecuária, inclusive o apoio à pecuária | E85: =H11 -> 46.384889
B86: 5 | C86: =C24 -> Fabricação de calçados e de artefatos de couro | E86: =H24 -> 44.105572
B87: 6 | C87: =C76 -> Organizações associativas e outros serviços pessoais | E87: =H76 -> 43.746199
B88: 7 | C88: =C75 -> Atividades artísticas, criativas e de espetáculos | E88: =H75 -> 43.271298
B89: 8 | C89: =C58 -> Edição e edição integrada à impressão | E89: =H58 -> 39.202476
B90: 9 | C90: =C57 -> Alimentação | E90: =H57 -> 38.909352
B91: 10 | C91: =C72 -> Educação privada | E91: =H72 -> 36.939216
B94: Ranking — geração de renda (tipo II)
B95: # | C95: Atividades | E95: Multiplicador
